Workbook
Name InputAmounts: SharedData!$E$6:$E$25
Name InputCashDates: SharedData!$M$6:$M$15
Name InputCashFlows: SharedData!$L$6:$L$15
Name InputCategories: SharedData!$C$6:$C$25
Name InputDates: SharedData!$D$6:$D$25
Name InputLabels: SharedData!$B$6:$B$25
Name InputNumbers: SharedData!$A$6:$A$25
Name InputWeights: SharedData!$F$6:$F$25

Sheet Overview
A1: CellRune Excel Oracle — deterministic function atlas
A2: Excel-authored cache oracle covering the plan's 10 sheets, CSE/dynamic arrays, reference semantics, structured/3-D references, and a Microsoft function catalog broader than CellRune.
A4: Active oracle formulas | B4: =SUM(B8:B17) -> 672 | D4: Catalogued functions | E4: 522 | G4: CellRune catalog | H4: 279 | J4: Breadth ratio | K4: =E4/H4 -> 1.8709677
A5: Deterministic active functions | B5: 494 | D5: Explicit exclusions | E5: 28 | G5: Date system | H5: 1900 | J5: Saved by | K5: Microsoft Excel for Mac
A7: Oracle sheet | B7: Active formulas | C7: Primary cases | D7: All formulas incl. sentinels | E7: Coverage focus
A8: Arithmetic | B8: =Arithmetic!$S$4 -> 162 | C8: =Arithmetic!$S$3 -> 162 | D8: 200 | E8: Near-zero cancellation, 15-digit residue, math/trig/engineering
A9: Aggregates | B9: =Aggregates!$S$4 -> 174 | C9: =Aggregates!$S$3 -> 174 | D9: 214 | E9: Aggregate, database, statistical, mixed-type and empty-range behavior
A10: ArraysCSE | B10: =ArraysCSE!$S$4 -> 16 | C10: =ArraysCSE!$S$3 -> 16 | D10: 23 | E10: Legacy array formulas, broadcasting, padding, mixed array literals
A11: ArraysDynamic | B11: =ArraysDynamic!$S$4 -> 65 | C11: =ArraysDynamic!$S$3 -> 65 | D11: 83 | E11: Spill arrays, Lambda helpers, shape transforms and blockers
A12: Intersection | B12: =Intersection!$S$4 -> 11 | C12: =Intersection!$S$3 -> 11 | D12: 17 | E12: Implicit intersection, union/intersection/range, whole row/column and 3-D
A13: Financial | B13: =Financial!$S$4 -> 61 | C13: =Financial!$S$3 -> 61 | D13: 78 | E13: Cash-flow solvers, securities, convergence and #NUM! boundaries
A14: Lookup | B14: =Lookup!$S$4 -> 34 | C14: =Lookup!$S$3 -> 34 | D14: 45 | E14: Legacy and modern lookup, approximate match, structured references
A15: TextDate | B15: =TextDate!$S$4 -> 86 | C15: =TextDate!$S$3 -> 86 | D15: 108 | E15: Text, regex, date/time, 1900 leap-year and locale-sensitive formatting
A16: Errors | B16: =Errors!$S$4 -> 43 | C16: =Errors!$S$3 -> 45 | D16: 56 | E16: Error propagation, catchers, error arguments and iterative circular cells
A17: Unsupported | B17: =Unsupported!$S$4 -> 20 | C17: =Unsupported!$S$3 -> 49 | D17: 26 | E17: LET/LAMBDA, 3-D, structured refs, external/volatile exclusions
A20: Oracle rules | B20: No current time or random functions; all input ranges are visible; every cross-sheet reference is quoted; Excel owns the saved cache.
A21: Source catalog | B21: https://support.microsoft.com/en-US/Excel/excel-functions-alphabetical
A23: Recalculation protocol | B23: Open in Microsoft Excel → Calculate Now / F9 → save as .xlsx → verify formula cells contain cached <v> values.
A25: Sentinel chain | B25: =SUM(Arithmetic!$P$5,Aggregates!$P$5,ArraysCSE!$P$5,ArraysDynamic!$P$5,Intersection!$P$5,Financial!$P$5,Lookup!$P$5,TextDate!$P$5,Errors!$P$5,Unsupported!$P$5) -> 1900.6005

Sheet SharedData
A1: SharedData — deterministic workbook inputs | P1: Spill anchor | R1: Blocked spill | S1: T/U/V below are header-less numeric columns for whole-column array cases (T,U = 20 rows; V = 12).
A2: Every oracle sheet references these typed inputs. No mock/random/current-time data is used. | O2: =O3+1 | P2: {=_xlfn.SEQUENCE(5)} -> 1 | R2: {=_xlfn.SEQUENCE(4)} -> #VALUE!
O3: =O2+1 | P3: 2
P4: 3 | R4: blocker
A5: Number | B5: Key | C5: Category | D5: Date | E5: Amount | F5: Quantity | G5: Flag | H5: Mixed | I5: X | J5: Y = 2X+3 | K5: Probability | L5: Cash flow | M5: Cash date | N5: Complex text | P5: 4
A6: 0.1 | B6: K001 | C6: A | D6: 43831 | E6: 10 | F6: 1 | G6: TRUE | I6: 1 | J6: =I6*2+3 -> 5 | K6: 0.05 | L6: -1000 | M6: 43831 | N6: 1+1i | P6: 5 | T6: 1 | U6: 2 | V6: 1
A7: 0.2 | B7: K002 | C7: B | D7: 43862 | E7: 20 | F7: 2 | G7: FALSE | H7: text | I7: 2 | J7: =I7*2+3 -> 7 | K7: 0.05 | L7: 180 | M7: 44012 | N7: 2+2i | T7: 2 | U7: 4 | V7: 2
A8: -0.3 | B8: K003 | C8: C | D8: 43893 | E8: 30 | F8: 3 | G8: TRUE | H8: TRUE | I8: 3 | J8: =I8*2+3 -> 9 | K8: 0.05 | L8: 220 | M8: 44193 | N8: 3+3i | T8: 3 | U8: 6 | V8: 3
A9: 1 | B9: K004 | C9: A | D9: 43924 | E9: 40 | F9: 4 | G9: FALSE | H9: FALSE | I9: 4 | J9: =I9*2+3 -> 11 | K9: 0.05 | L9: 260 | M9: 44374 | N9: 4+4i | T9: 4 | U9: 8 | V9: 4
A10: 2 | B10: K005 | C10: B | D10: 43955 | E10: 50 | F10: 5 | G10: TRUE | H10: 0 | I10: 5 | J10: =I10*2+3 -> 13 | K10: 0.05 | L10: 300 | M10: 44555 | N10: 5+5i | T10: 5 | U10: 10 | V10: 5
A11: 3 | B11: K006 | C11: C | D11: 43986 | E11: 60 | F11: 6 | G11: FALSE | H11: 0 | I11: 6 | J11: =I11*2+3 -> 15 | K11: 0.05 | L11: 340 | M11: 44736 | N11: 6+1i | T11: 6 | U11: 12 | V11: 6
A12: 4 | B12: K007 | C12: A | D12: 44017 | E12: 70 | F12: 7 | G12: TRUE | I12: 7 | J12: =I12*2+3 -> 17 | K12: 0.05 | L12: 380 | M12: 44917 | N12: 7+2i | T12: 7 | U12: 14 | V12: 7
A13: 5 | B13: K008 | C13: B | D13: 44048 | E13: 80 | F13: 1 | G13: FALSE | H13: CellRune | I13: 8 | J13: =I13*2+3 -> 19 | K13: 0.05 | L13: -50 | M13: 45098 | N13: 8+3i | T13: 8 | U13: 16 | V13: 8
A14: 10 | B14: K009 | C14: C | D14: 44079 | E14: 90 | F14: 2 | G14: TRUE | H14: TRUE | I14: 9 | J14: =I14*2+3 -> 21 | K14: 0.05 | L14: 420 | M14: 45279 | N14: 9+4i | T14: 9 | U14: 18 | V14: 9
A15: -10 | B15: K010 | C15: A | D15: 44110 | E15: 100 | F15: 3 | G15: FALSE | H15: -1 | I15: 10 | J15: =I15*2+3 -> 23 | K15: 0.05 | L15: 500 | M15: 45460 | N15: 10+5i | T15: 10 | U15: 20 | V15: 10
A16: 25 | B16: K011 | C16: B | D16: 44141 | E16: 110 | F16: 4 | G16: TRUE | I16: 11 | J16: =I16*2+3 -> 25 | K16: 0.05 | N16: 11+1i | T16: 11 | U16: 22 | V16: 11
A17: 100 | B17: K012 | C17: C | D17: 44172 | E17: 120 | F17: 5 | G17: FALSE | H17: text | I17: 12 | J17: =I17*2+3 -> 27 | K17: 0.05 | N17: 12+2i | T17: 12 | U17: 24 | V17: 12
A18: 0 | B18: K013 | C18: A | D18: 44203 | E18: 130 | F18: 6 | G18: TRUE | H18: TRUE | I18: 13 | J18: =I18*2+3 -> 29 | K18: 0.05 | N18: 13+3i | T18: 13 | U18: 26
A19: 1.5 | B19: K014 | C19: B | D19: 44234 | E19: 140 | F19: 7 | G19: FALSE | H19: FALSE | I19: 14 | J19: =I19*2+3 -> 31 | K19: 0.05 | N19: 14+4i | T19: 14 | U19: 28
A20: 2.5 | B20: K015 | C20: C | D20: 44265 | E20: 150 | F20: 1 | G20: TRUE | H20: 0 | I20: 15 | J20: =I20*2+3 -> 33 | K20: 0.05 | N20: 15+5i | T20: 15 | U20: 30
A21: 3.5 | B21: K016 | C21: A | D21: 44296 | E21: 160 | F21: 2 | G21: FALSE | H21: 0 | I21: 16 | J21: =I21*2+3 -> 35 | K21: 0.05 | N21: 16+1i | T21: 16 | U21: 32
A22: 4.5 | B22: K017 | C22: B | D22: 44327 | E22: 170 | F22: 3 | G22: TRUE | I22: 17 | J22: =I22*2+3 -> 37 | K22: 0.05 | N22: 17+2i | T22: 17 | U22: 34
A23: 5.5 | B23: K018 | C23: C | D23: 44358 | E23: 180 | F23: 4 | G23: FALSE | H23: CellRune | I23: 18 | J23: =I23*2+3 -> 39 | K23: 0.05 | N23: 18+3i | T23: 18 | U23: 36
A24: 0.05 | B24: K019 | C24: A | D24: 44389 | E24: 190 | F24: 5 | G24: TRUE | H24: TRUE | I24: 19 | J24: =I24*2+3 -> 41 | K24: 0.05 | N24: 19+4i | T24: 19 | U24: 38
A25: 0.1 | B25: K020 | C25: B | D25: 44420 | E25: 200 | F25: 6 | G25: FALSE | H25: -1 | I25: 20 | J25: =I25*2+3 -> 43 | K25: 0.05 | N25: 20+5i | T25: 20 | U25: 40
A30: Key | B30: Category | C30: Date | D30: Amount | E30: Quantity | F30: Flag | H30: Category | I30: Amount
A31: K001 | B31: A | C31: 43831 | D31: 10 | E31: 1 | F31: TRUE | H31: A | I31: >50
A32: K002 | B32: B | C32: 43862 | D32: 20 | E32: 2 | F32: FALSE | H32: B | I32: <=120
A33: K003 | B33: C | C33: 43893 | D33: 30 | E33: 3 | F33: TRUE
A34: K004 | B34: A | C34: 43924 | D34: 40 | E34: 4 | F34: FALSE
A35: K005 | B35: B | C35: 43955 | D35: 50 | E35: 5 | F35: TRUE
A36: K006 | B36: C | C36: 43986 | D36: 60 | E36: 6 | F36: FALSE
A37: K007 | B37: A | C37: 44017 | D37: 70 | E37: 7 | F37: TRUE
A38: K008 | B38: B | C38: 44048 | D38: 80 | E38: 1 | F38: FALSE
A39: K009 | B39: C | C39: 44079 | D39: 90 | E39: 2 | F39: TRUE
A40: K010 | B40: A | C40: 44110 | D40: 100 | E40: 3 | F40: FALSE
A41: K011 | B41: B | C41: 44141 | D41: 110 | E41: 4 | F41: TRUE
A42: K012 | B42: C | C42: 44172 | D42: 120 | E42: 5 | F42: FALSE
A43: K013 | B43: A | C43: 44203 | D43: 130 | E43: 6 | F43: TRUE
A44: K014 | B44: B | C44: 44234 | D44: 140 | E44: 7 | F44: FALSE
... A50: K020 | B50: B | C50: 44420 | D50: 200 | E50: 6 | F50: FALSE

Sheet Arithmetic
A1: Arithmetic — CellRune Excel Oracle
A2: Blue cells are formulas. Gray rows are catalogued exclusions. Excel must recalculate and save cached values. | R2: Catalog rows | S2: =COUNTA(A5:A166) -> 162
R3: Primary cases | S3: =COUNTA(A5:A166) -> 162
A4: Case ID | B4: Category | C4: Function | D4: Scenario | E4: Formula text | F4: Result / spill zone | M4: Expectation | N4: Sentinel | O4: Note | P4: Dependency signature | R4: Active formulas | S4: =COUNTA(A5:A166)-COUNTIF(M5:M166,"excluded") -> 162
A5: function:abs | B5: Math and trigonometry | C5: ABS | D5: Curated deterministic boundary with shared-data and cross-sheet inputs | E5: =ABS('SharedData'!$A$8) | F5: =ABS(SharedData!$A$8) -> 0.3 | M5: oracle_probe | N5: =IF(ISERROR(F5),"ERROR "&IFERROR(ERROR.TYPE(F5),""),"OK") -> OK | O5: Recalculate in Excel and compare the saved result. | P5: =IFERROR(N(F5),0)+SUM(SharedData!$A$6:$A$8)+ROW()/100000 -> 0.30005
A6: function:acos | B6: Math and trigonometry | C6: ACOS | D6: Function-catalog probe; genuine error results are retained as oracle evidence | E6: =ACOS(0.5) | F6: =ACOS(0.5) -> 1.0471976 | M6: oracle_probe | O6: Recalculate in Excel and compare the saved result.
A7: function:acosh | B7: Math and trigonometry | C7: ACOSH | D7: Function-catalog probe with a repaired call signature | E7: =ACOSH(2.5) | F7: =ACOSH(2.5) -> 1.5667992 | M7: oracle_probe | O7: Recalculate in Excel and compare the saved result.
A8: function:acot | B8: Math and trigonometry | C8: ACOT | D8: Function-catalog probe; genuine error results are retained as oracle evidence | E8: =ACOT(0.5) | F8: =_xlfn.ACOT(0.5) -> 1.1071487 | M8: oracle_probe | O8: Recalculate in Excel and compare the saved result.
A9: function:acoth | B9: Math and trigonometry | C9: ACOTH | D9: Function-catalog probe; genuine error results are retained as oracle evidence | E9: =ACOTH(0.5) | F9: =_xlfn.ACOTH(0.5) -> #NUM! | M9: oracle_probe | O9: Recalculate in Excel and compare the saved result.
A10: function:aggregate | B10: Math and trigonometry | C10: AGGREGATE | D10: Curated deterministic boundary with shared-data and cross-sheet inputs | E10: =AGGREGATE(9,6,'SharedData'!$E$6:$E$25) | F10: =_xlfn.AGGREGATE(9,6,SharedData!$E$6:$E$25) -> 2100 | M10: oracle_probe | O10: Recalculate in Excel and compare the saved result.
A11: function:arabic | B11: Math and trigonometry | C11: ARABIC | D11: Curated deterministic boundary with shared-data and cross-sheet inputs | E11: =ARABIC("MMXXVI") | F11: =_xlfn.ARABIC("MMXXVI") -> 2026 | M11: oracle_probe | O11: Recalculate in Excel and compare the saved result.
A12: function:asin | B12: Math and trigonometry | C12: ASIN | D12: Function-catalog probe; genuine error results are retained as oracle evidence | E12: =ASIN(0.5) | F12: =ASIN(0.5) -> 0.52359878 | M12: oracle_probe | O12: Recalculate in Excel and compare the saved result.
A13: function:asinh | B13: Math and trigonometry | C13: ASINH | D13: Function-catalog probe; genuine error results are retained as oracle evidence | E13: =ASINH(0.5) | F13: =ASINH(0.5) -> 0.48121183 | M13: oracle_probe | N13: =IF(ISERROR(F13),"ERROR "&IFERROR(ERROR.TYPE(F13),""),"OK") -> OK | O13: Recalculate in Excel and compare the saved result.
A14: function:atan | B14: Math and trigonometry | C14: ATAN | D14: Function-catalog probe; genuine error results are retained as oracle evidence | E14: =ATAN(0.5) | F14: =ATAN(0.5) -> 0.46364761 | M14: oracle_probe | O14: Recalculate in Excel and compare the saved result.
A15: function:atan2 | B15: Math and trigonometry | C15: ATAN2 | D15: Function-catalog probe with a repaired call signature | E15: =ATAN2(1,1) | F15: =ATAN2(1,1) -> 0.78539816 | M15: oracle_probe | O15: Recalculate in Excel and compare the saved result.
A16: function:atanh | B16: Math and trigonometry | C16: ATANH | D16: Function-catalog probe; genuine error results are retained as oracle evidence | E16: =ATANH(0.5) | F16: =ATANH(0.5) -> 0.54930614 | M16: oracle_probe | O16: Recalculate in Excel and compare the saved result.
A17: function:base | B17: Math and trigonometry | C17: BASE | D17: Curated deterministic boundary with shared-data and cross-sheet inputs | E17: =BASE(255,16,4) | F17: =_xlfn.BASE(255,16,4) -> 00FF | M17: oracle_probe | O17: Recalculate in Excel and compare the saved result. | P17: =IFERROR(N(F17),0)+SUM(SharedData!$A$6:$A$8)+ROW()/100000 -> 0.00017
A18: function:besseli | B18: Engineering | C18: BESSELI | D18: Curated deterministic boundary with shared-data and cross-sheet inputs | E18: =BESSELI(1.5,2) | F18: =BESSELI(1.5,2) -> 0.33783462 | M18: oracle_probe | O18: Recalculate in Excel and compare the saved result.
A19: function:besselj | B19: Engineering | C19: BESSELJ | D19: Curated deterministic boundary with shared-data and cross-sheet inputs | E19: =BESSELJ(1.5,2) | F19: =BESSELJ(1.5,2) -> 0.23208768 | M19: oracle_probe | O19: Recalculate in Excel and compare the saved result.
A20: function:besselk | B20: Engineering | C20: BESSELK | D20: Curated deterministic boundary with shared-data and cross-sheet inputs | E20: =BESSELK(1.5,2) | F20: =BESSELK(1.5,2) -> 0.58365597 | M20: oracle_probe | O20: Recalculate in Excel and compare the saved result.
A21: function:bessely | B21: Engineering | C21: BESSELY | D21: Curated deterministic boundary with shared-data and cross-sheet inputs | E21: =BESSELY(1.5,2) | F21: =BESSELY(1.5,2) -> -0.93219376 | M21: oracle_probe | N21: =IF(ISERROR(F21),"ERROR "&IFERROR(ERROR.TYPE(F21),""),"OK") -> OK | O21: Recalculate in Excel and compare the saved result.
A22: function:bin2dec | B22: Engineering | C22: BIN2DEC | D22: Curated deterministic boundary with shared-data and cross-sheet inputs | E22: =BIN2DEC("101101") | F22: =BIN2DEC("101101") -> 45 | M22: oracle_probe | O22: Recalculate in Excel and compare the saved result.
A23: function:bin2hex | B23: Engineering | C23: BIN2HEX | D23: Curated deterministic boundary with shared-data and cross-sheet inputs | E23: =BIN2HEX("101101",4) | F23: =BIN2HEX("101101",4) -> 002D | M23: oracle_probe | O23: Recalculate in Excel and compare the saved result.
A24: function:bin2oct | B24: Engineering | C24: BIN2OCT | D24: Curated deterministic boundary with shared-data and cross-sheet inputs | E24: =BIN2OCT("101101",4) | F24: =BIN2OCT("101101",4) -> 0055 | M24: oracle_probe | O24: Recalculate in Excel and compare the saved result.
A25: function:bitand | B25: Engineering | C25: BITAND | D25: Curated deterministic boundary with shared-data and cross-sheet inputs | E25: =BITAND(29,23) | F25: =_xlfn.BITAND(29,23) -> 21 | M25: oracle_probe | O25: Recalculate in Excel and compare the saved result.
A26: function:bitlshift | B26: Engineering | C26: BITLSHIFT | D26: Curated deterministic boundary with shared-data and cross-sheet inputs | E26: =BITLSHIFT(7,3) | F26: =_xlfn.BITLSHIFT(7,3) -> 56 | M26: oracle_probe | O26: Recalculate in Excel and compare the saved result.
A27: function:bitor | B27: Engineering | C27: BITOR | D27: Curated deterministic boundary with shared-data and cross-sheet inputs | E27: =BITOR(29,23) | F27: =_xlfn.BITOR(29,23) -> 31 | M27: oracle_probe | O27: Recalculate in Excel and compare the saved result.
A28: function:bitrshift | B28: Engineering | C28: BITRSHIFT | D28: Curated deterministic boundary with shared-data and cross-sheet inputs | E28: =BITRSHIFT(128,3) | F28: =_xlfn.BITRSHIFT(128,3) -> 16 | M28: oracle_probe | O28: Recalculate in Excel and compare the saved result.
A29: function:bitxor | B29: Engineering | C29: BITXOR | D29: Curated deterministic boundary with shared-data and cross-sheet inputs | E29: =BITXOR(29,23) | F29: =_xlfn.BITXOR(29,23) -> 10 | M29: oracle_probe | N29: =IF(ISERROR(F29),"ERROR "&IFERROR(ERROR.TYPE(F29),""),"OK") -> OK | O29: Recalculate in Excel and compare the saved result. | P29: =IFERROR(N(F29),0)+SUM(SharedData!$A$6:$A$8)+ROW()/100000 -> 10.00029
A30: function:ceiling | B30: Math and trigonometry | C30: CEILING | D30: Curated deterministic boundary with shared-data and cross-sheet inputs | E30: =CEILING('SharedData'!$A$19,0.25) | F30: =CEILING(SharedData!$A$19,0.25) -> 1.5 | M30: oracle_probe | O30: Recalculate in Excel and compare the saved result.
A31: function:ceiling-math | B31: Math and trigonometry | C31: CEILING.MATH | D31: Curated deterministic boundary with shared-data and cross-sheet inputs | E31: =CEILING.MATH('SharedData'!$A$19,0.25,1) | F31: =_xlfn.CEILING.MATH(SharedData!$A$19,0.25,1) -> 1.5 | M31: oracle_probe | O31: Recalculate in Excel and compare the saved result.
A32: function:ceiling-precise | B32: Math and trigonometry | C32: CEILING.PRECISE | D32: Curated deterministic boundary with shared-data and cross-sheet inputs | E32: =CEILING.PRECISE('SharedData'!$A$19,0.25) | F32: =_xlfn.CEILING.PRECISE(SharedData!$A$19,0.25) -> 1.5 | M32: oracle_probe | O32: Recalculate in Excel and compare the saved result.
A33: function:combin | B33: Math and trigonometry | C33: COMBIN | D33: Curated deterministic boundary with shared-data and cross-sheet inputs | E33: =COMBIN(10,3) | F33: =COMBIN(10,3) -> 120 | M33: oracle_probe | O33: Recalculate in Excel and compare the saved result.
A34: function:combina | B34: Math and trigonometry | C34: COMBINA | D34: Curated deterministic boundary with shared-data and cross-sheet inputs | E34: =COMBINA(10,3) | F34: =_xlfn.COMBINA(10,3) -> 220 | M34: oracle_probe | O34: Recalculate in Excel and compare the saved result.
A35: function:complex | B35: Engineering | C35: COMPLEX | D35: Curated deterministic boundary with shared-data and cross-sheet inputs | E35: =COMPLEX(3,4,"i") | F35: =COMPLEX(3,4,"i") -> 3+4i | M35: oracle_probe | O35: Recalculate in Excel and compare the saved result.
A36: function:convert | B36: Engineering | C36: CONVERT | D36: Curated deterministic boundary with shared-data and cross-sheet inputs | E36: =CONVERT(10,"km","mi") | F36: =CONVERT(10,"km","mi") -> 6.2137119 | M36: oracle_probe | O36: Recalculate in Excel and compare the saved result.
A37: function:cos | B37: Math and trigonometry | C37: COS | D37: Function-catalog probe; genuine error results are retained as oracle evidence | E37: =COS(0.5) | F37: =COS(0.5) -> 0.87758256 | M37: oracle_probe | N37: =IF(ISERROR(F37),"ERROR "&IFERROR(ERROR.TYPE(F37),""),"OK") -> OK | O37: Recalculate in Excel and compare the saved result.
A38: function:cosh | B38: Math and trigonometry | C38: COSH | D38: Function-catalog probe; genuine error results are retained as oracle evidence | E38: =COSH(0.5) | F38: =COSH(0.5) -> 1.127626 | M38: oracle_probe | O38: Recalculate in Excel and compare the saved result.
A39: function:cot | B39: Math and trigonometry | C39: COT | D39: Function-catalog probe; genuine error results are retained as oracle evidence | E39: =COT(0.5) | F39: =_xlfn.COT(0.5) -> 1.8304877 | M39: oracle_probe | O39: Recalculate in Excel and compare the saved result.
A40: function:coth | B40: Math and trigonometry | C40: COTH | D40: Function-catalog probe; genuine error results are retained as oracle evidence | E40: =COTH(0.5) | F40: =_xlfn.COTH(0.5) -> 2.1639534 | M40: oracle_probe | O40: Recalculate in Excel and compare the saved result.
A41: function:csc | B41: Math and trigonometry | C41: CSC | D41: Function-catalog probe; genuine error results are retained as oracle evidence | E41: =CSC(0.5) | F41: =_xlfn.CSC(0.5) -> 2.0858296 | M41: oracle_probe | O41: Recalculate in Excel and compare the saved result. | P41: =IFERROR(N(F41),0)+SUM(SharedData!$A$6:$A$8)+ROW()/100000 -> 2.0862396
A42: function:csch | B42: Math and trigonometry | C42: CSCH | D42: Function-catalog probe; genuine error results are retained as oracle evidence | E42: =CSCH(0.5) | F42: =_xlfn.CSCH(0.5) -> 1.9190348 | M42: oracle_probe | O42: Recalculate in Excel and compare the saved result.
A43: function:dec2bin | B43: Engineering | C43: DEC2BIN | D43: Curated deterministic boundary with shared-data and cross-sheet inputs | E43: =DEC2BIN(45,8) | F43: =DEC2BIN(45,8) -> 00101101 | M43: oracle_probe | O43: Recalculate in Excel and compare the saved result.
A44: function:dec2hex | B44: Engineering | C44: DEC2HEX | D44: Curated deterministic boundary with shared-data and cross-sheet inputs | E44: =DEC2HEX(4095,6) | F44: =DEC2HEX(4095,6) -> 000FFF | M44: oracle_probe | O44: Recalculate in Excel and compare the saved result.
A45: function:dec2oct | B45: Engineering | C45: DEC2OCT | D45: Curated deterministic boundary with shared-data and cross-sheet inputs | E45: =DEC2OCT(511,5) | F45: =DEC2OCT(511,5) -> 00777 | M45: oracle_probe | N45: =IF(ISERROR(F45),"ERROR "&IFERROR(ERROR.TYPE(F45),""),"OK") -> OK | O45: Recalculate in Excel and compare the saved result.
A46: function:decimal | B46: Math and trigonometry | C46: DECIMAL | D46: Curated deterministic boundary with shared-data and cross-sheet inputs | E46: =DECIMAL("FF",16) | F46: =_xlfn.DECIMAL("FF",16) -> 255 | M46: oracle_probe | O46: Recalculate in Excel and compare the saved result.
A47: function:degrees | B47: Math and trigonometry | C47: DEGREES | D47: Curated deterministic boundary with shared-data and cross-sheet inputs | E47: =DEGREES(PI()/3) | F47: =DEGREES(PI()/3) -> 60 | M47: oracle_probe | O47: Recalculate in Excel and compare the saved result.
A48: function:delta | B48: Engineering | C48: DELTA | D48: Curated deterministic boundary with shared-data and cross-sheet inputs | E48: =DELTA('SharedData'!$A$9,'SharedData'!$A$10) | F48: =DELTA(SharedData!$A$9,SharedData!$A$10) -> 0 | M48: oracle_probe | O48: Recalculate in Excel and compare the saved result.
A49: function:erf | B49: Engineering | C49: ERF | D49: Function-catalog probe; genuine error results are retained as oracle evidence | E49: =ERF(10) | F49: =ERF(10) -> 1 | M49: oracle_probe | O49: Recalculate in Excel and compare the saved result.
A50: function:erf-precise | B50: Engineering | C50: ERF.PRECISE | D50: Function-catalog probe; genuine error results are retained as oracle evidence | E50: =ERF.PRECISE(10) | F50: =_xlfn.ERF.PRECISE(10) -> 1 | M50: oracle_probe | O50: Recalculate in Excel and compare the saved result.
A51: function:erfc | B51: Engineering | C51: ERFC | D51: Function-catalog probe; genuine error results are retained as oracle evidence | E51: =ERFC(10) | F51: =ERFC(10) -> 2.0884876e-45 | M51: oracle_probe | O51: Recalculate in Excel and compare the saved result.
A52: function:erfc-precise | B52: Engineering | C52: ERFC.PRECISE | D52: Function-catalog probe; genuine error results are retained as oracle evidence | E52: =ERFC.PRECISE(10) | F52: =_xlfn.ERFC.PRECISE(10) -> 2.0884876e-45 | M52: oracle_probe | O52: Recalculate in Excel and compare the saved result.
A53: function:even | B53: Math and trigonometry | C53: EVEN | D53: Function-catalog probe; genuine error results are retained as oracle evidence | E53: =EVEN(0.5) | F53: =EVEN(0.5) -> 2 | M53: oracle_probe | N53: =IF(ISERROR(F53),"ERROR "&IFERROR(ERROR.TYPE(F53),""),"OK") -> OK | O53: Recalculate in Excel and compare the saved result. | P53: =IFERROR(N(F53),0)+SUM(SharedData!$A$6:$A$8)+ROW()/100000 -> 2.00053
A54: function:exp | B54: Math and trigonometry | C54: EXP | D54: Function-catalog probe; genuine error results are retained as oracle evidence | E54: =EXP(0.5) | F54: =EXP(0.5) -> 1.6487213 | M54: oracle_probe | O54: Recalculate in Excel and compare the saved result.
A55: function:fact | B55: Math and trigonometry | C55: FACT | D55: Function-catalog probe; genuine error results are retained as oracle evidence | E55: =FACT(0.5) | F55: =FACT(0.5) -> 1 | M55: oracle_probe | O55: Recalculate in Excel and compare the saved result.
A56: function:factdouble | B56: Math and trigonometry | C56: FACTDOUBLE | D56: Function-catalog probe; genuine error results are retained as oracle evidence | E56: =FACTDOUBLE(0.5) | F56: =FACTDOUBLE(0.5) -> 1 | M56: oracle_probe | O56: Recalculate in Excel and compare the saved result.
A57: function:floor | B57: Math and trigonometry | C57: FLOOR | D57: Curated deterministic boundary with shared-data and cross-sheet inputs | E57: =FLOOR('SharedData'!$A$19,0.25) | F57: =FLOOR(SharedData!$A$19,0.25) -> 1.5 | M57: oracle_probe | O57: Recalculate in Excel and compare the saved result.
A58: function:floor-math | B58: Math and trigonometry | C58: FLOOR.MATH | D58: Curated deterministic boundary with shared-data and cross-sheet inputs | E58: =FLOOR.MATH('SharedData'!$A$19,0.25,1) | F58: =_xlfn.FLOOR.MATH(SharedData!$A$19,0.25,1) -> 1.5 | M58: oracle_probe | O58: Recalculate in Excel and compare the saved result.
A59: function:floor-precise | B59: Math and trigonometry | C59: FLOOR.PRECISE | D59: Curated deterministic boundary with shared-data and cross-sheet inputs | E59: =FLOOR.PRECISE('SharedData'!$A$19,0.25) | F59: =_xlfn.FLOOR.PRECISE(SharedData!$A$19,0.25) -> 1.5 | M59: oracle_probe | O59: Recalculate in Excel and compare the saved result.
A60: function:gcd | B60: Math and trigonometry | C60: GCD | D60: Curated deterministic boundary with shared-data and cross-sheet inputs | E60: =GCD(48,180,420) | F60: =GCD(48,180,420) -> 12 | M60: oracle_probe | O60: Recalculate in Excel and compare the saved result.
A61: function:gestep | B61: Engineering | C61: GESTEP | D61: Function-catalog probe; genuine error results are retained as oracle evidence | E61: =GESTEP(10) | F61: =GESTEP(10) -> 1 | M61: oracle_probe | N61: =IF(ISERROR(F61),"ERROR "&IFERROR(ERROR.TYPE(F61),""),"OK") -> OK | O61: Recalculate in Excel and compare the saved result.
A62: function:hex2bin | B62: Engineering | C62: HEX2BIN | D62: Curated deterministic boundary with shared-data and cross-sheet inputs | E62: =HEX2BIN("2D",8) | F62: =HEX2BIN("2D",8) -> 00101101 | M62: oracle_probe | O62: Recalculate in Excel and compare the saved result.
A63: function:hex2dec | B63: Engineering | C63: HEX2DEC | D63: Curated deterministic boundary with shared-data and cross-sheet inputs | E63: =HEX2DEC("FFF") | F63: =HEX2DEC("FFF") -> 4095 | M63: oracle_probe | O63: Recalculate in Excel and compare the saved result.
A64: function:hex2oct | B64: Engineering | C64: HEX2OCT | D64: Curated deterministic boundary with shared-data and cross-sheet inputs | E64: =HEX2OCT("1FF",5) | F64: =HEX2OCT("1FF",5) -> 00777 | M64: oracle_probe | O64: Recalculate in Excel and compare the saved result.
A65: function:imabs | B65: Engineering | C65: IMABS | D65: Function-catalog probe; genuine error results are retained as oracle evidence | E65: =IMABS(COMPLEX(3,4)) | F65: =IMABS(COMPLEX(3,4)) -> 5 | M65: oracle_probe | O65: Recalculate in Excel and compare the saved result. | P65: =IFERROR(N(F65),0)+SUM(SharedData!$A$6:$A$8)+ROW()/100000 -> 5.00065
A66: function:imaginary | B66: Engineering | C66: IMAGINARY | D66: Function-catalog probe; genuine error results are retained as oracle evidence | E66: =IMAGINARY(COMPLEX(3,4)) | F66: =IMAGINARY(COMPLEX(3,4)) -> 4 | M66: oracle_probe | O66: Recalculate in Excel and compare the saved result.
A67: function:imargument | B67: Engineering | C67: IMARGUMENT | D67: Function-catalog probe; genuine error results are retained as oracle evidence | E67: =IMARGUMENT(COMPLEX(3,4)) | F67: =IMARGUMENT(COMPLEX(3,4)) -> 0.92729522 | M67: oracle_probe | O67: Recalculate in Excel and compare the saved result.
A68: function:imconjugate | B68: Engineering | C68: IMCONJUGATE | D68: Function-catalog probe; genuine error results are retained as oracle evidence | E68: =IMCONJUGATE(COMPLEX(3,4)) | F68: =IMCONJUGATE(COMPLEX(3,4)) -> 3-4i | M68: oracle_probe | O68: Recalculate in Excel and compare the saved result.
A69: function:imcos | B69: Engineering | C69: IMCOS | D69: Function-catalog probe; genuine error results are retained as oracle evidence | E69: =IMCOS(COMPLEX(3,4)) | F69: =IMCOS(COMPLEX(3,4)) -> -27.0349456030742-3.85115333481178i | M69: oracle_probe | N69: =IF(ISERROR(F69),"ERROR "&IFERROR(ERROR.TYPE(F69),""),"OK") -> OK | O69: Recalculate in Excel and compare the saved result.
A70: function:imcosh | B70: Engineering | C70: IMCOSH | D70: Function-catalog probe; genuine error results are retained as oracle evidence | E70: =IMCOSH(COMPLEX(3,4)) | F70: =_xlfn.IMCOSH(COMPLEX(3,4)) -> -6.58066304055116-7.58155274274654i | M70: oracle_probe | O70: Recalculate in Excel and compare the saved result.
A71: function:imcot | B71: Engineering | C71: IMCOT | D71: Function-catalog probe; genuine error results are retained as oracle evidence | E71: =IMCOT(COMPLEX(3,4)) | F71: =_xlfn.IMCOT(COMPLEX(3,4)) -> -0.000187587737983659-1.00064439247156i | M71: oracle_probe | O71: Recalculate in Excel and compare the saved result.
A72: function:imcsc | B72: Engineering | C72: IMCSC | D72: Function-catalog probe; genuine error results are retained as oracle evidence | E72: =IMCSC(COMPLEX(3,4)) | F72: =_xlfn.IMCSC(COMPLEX(3,4)) -> 0.0051744731840194+0.036275889628626i | M72: oracle_probe | O72: Recalculate in Excel and compare the saved result.
A73: function:imcsch | B73: Engineering | C73: IMCSCH | D73: Function-catalog probe; genuine error results are retained as oracle evidence | E73: =IMCSCH(COMPLEX(3,4)) | F73: =_xlfn.IMCSCH(COMPLEX(3,4)) -> -0.0648774713706355+0.0754898329158637i | M73: oracle_probe | O73: Recalculate in Excel and compare the saved result.
A74: function:imdiv | B74: Engineering | C74: IMDIV | D74: Function-catalog probe; genuine error results are retained as oracle evidence | E74: =IMDIV(COMPLEX(3,4),COMPLEX(1,-2)) | F74: =IMDIV(COMPLEX(3,4),COMPLEX(1,-2)) -> -1+2i | M74: oracle_probe | O74: Recalculate in Excel and compare the saved result.
A75: function:imexp | B75: Engineering | C75: IMEXP | D75: Function-catalog probe; genuine error results are retained as oracle evidence | E75: =IMEXP(COMPLEX(3,4)) | F75: =IMEXP(COMPLEX(3,4)) -> -13.1287830814622-15.200784463068i | M75: oracle_probe | O75: Recalculate in Excel and compare the saved result.
A76: function:imln | B76: Engineering | C76: IMLN | D76: Function-catalog probe; genuine error results are retained as oracle evidence | E76: =IMLN(COMPLEX(3,4)) | F76: =IMLN(COMPLEX(3,4)) -> 1.6094379124341+0.927295218001612i | M76: oracle_probe | O76: Recalculate in Excel and compare the saved result.
A77: function:imlog10 | B77: Engineering | C77: IMLOG10 | D77: Function-catalog probe; genuine error results are retained as oracle evidence | E77: =IMLOG10(COMPLEX(3,4)) | F77: =IMLOG10(COMPLEX(3,4)) -> 0.698970004336019+0.402719196273373i | M77: oracle_probe | N77: =IF(ISERROR(F77),"ERROR "&IFERROR(ERROR.TYPE(F77),""),"OK") -> OK | O77: Recalculate in Excel and compare the saved result. | P77: =IFERROR(N(F77),0)+SUM(SharedData!$A$6:$A$8)+ROW()/100000 -> 0.00077
A78: function:imlog2 | B78: Engineering | C78: IMLOG2 | D78: Function-catalog probe; genuine error results are retained as oracle evidence | E78: =IMLOG2(COMPLEX(3,4)) | F78: =IMLOG2(COMPLEX(3,4)) -> 2.32192809488736+1.33780421245098i | M78: oracle_probe | O78: Recalculate in Excel and compare the saved result.
A79: function:impower | B79: Engineering | C79: IMPOWER | D79: Function-catalog probe with a repaired call signature | E79: =IMPOWER(COMPLEX(3,4),3) | F79: =IMPOWER(COMPLEX(3,4),3) -> -117+44i | M79: oracle_probe | O79: Recalculate in Excel and compare the saved result.
A80: function:improduct | B80: Engineering | C80: IMPRODUCT | D80: Function-catalog probe; genuine error results are retained as oracle evidence | E80: =IMPRODUCT(COMPLEX(3,4),COMPLEX(1,-2)) | F80: =IMPRODUCT(COMPLEX(3,4),COMPLEX(1,-2)) -> 11-2i | M80: oracle_probe | O80: Recalculate in Excel and compare the saved result.
A81: function:imreal | B81: Engineering | C81: IMREAL | D81: Function-catalog probe; genuine error results are retained as oracle evidence | E81: =IMREAL(COMPLEX(3,4)) | F81: =IMREAL(COMPLEX(3,4)) -> 3 | M81: oracle_probe | O81: Recalculate in Excel and compare the saved result.
A82: function:imsec | B82: Engineering | C82: IMSEC | D82: Function-catalog probe; genuine error results are retained as oracle evidence | E82: =IMSEC(COMPLEX(3,4)) | F82: =_xlfn.IMSEC(COMPLEX(3,4)) -> -0.0362534969158689+0.00516434460775318i | M82: oracle_probe | O82: Recalculate in Excel and compare the saved result.
A83: function:imsech | B83: Engineering | C83: IMSECH | D83: Function-catalog probe; genuine error results are retained as oracle evidence | E83: =IMSECH(COMPLEX(3,4)) | F83: =_xlfn.IMSECH(COMPLEX(3,4)) -> -0.065294027857947+0.0752249603027732i | M83: oracle_probe | O83: Recalculate in Excel and compare the saved result.
A84: function:imsin | B84: Engineering | C84: IMSIN | D84: Function-catalog probe; genuine error results are retained as oracle evidence | E84: =IMSIN(COMPLEX(3,4)) | F84: =IMSIN(COMPLEX(3,4)) -> 3.85373803791938-27.0168132580039i | M84: oracle_probe | O84: Recalculate in Excel and compare the saved result.
A85: function:imsinh | B85: Engineering | C85: IMSINH | D85: Function-catalog probe; genuine error results are retained as oracle evidence | E85: =IMSINH(COMPLEX(3,4)) | F85: =_xlfn.IMSINH(COMPLEX(3,4)) -> -6.548120040911-7.61923172032141i | M85: oracle_probe | N85: =IF(ISERROR(F85),"ERROR "&IFERROR(ERROR.TYPE(F85),""),"OK") -> OK | O85: Recalculate in Excel and compare the saved result.
A86: function:imsqrt | B86: Engineering | C86: IMSQRT | D86: Function-catalog probe; genuine error results are retained as oracle evidence | E86: =IMSQRT(COMPLEX(3,4)) | F86: =IMSQRT(COMPLEX(3,4)) -> 2+i | M86: oracle_probe | O86: Recalculate in Excel and compare the saved result.
A87: function:imsub | B87: Engineering | C87: IMSUB | D87: Function-catalog probe; genuine error results are retained as oracle evidence | E87: =IMSUB(COMPLEX(3,4),COMPLEX(1,-2)) | F87: =IMSUB(COMPLEX(3,4),COMPLEX(1,-2)) -> 2+6i | M87: oracle_probe | O87: Recalculate in Excel and compare the saved result.
A88: function:imsum | B88: Engineering | C88: IMSUM | D88: Function-catalog probe; genuine error results are retained as oracle evidence | E88: =IMSUM(COMPLEX(3,4),COMPLEX(1,-2)) | F88: =IMSUM(COMPLEX(3,4),COMPLEX(1,-2)) -> 4+2i | M88: oracle_probe | O88: Recalculate in Excel and compare the saved result.
A89: function:imtan | B89: Engineering | C89: IMTAN | D89: Function-catalog probe; genuine error results are retained as oracle evidence | E89: =IMTAN(COMPLEX(3,4)) | F89: =_xlfn.IMTAN(COMPLEX(3,4)) -> -0.000187346204629478+0.999355987381473i | M89: oracle_probe | O89: Recalculate in Excel and compare the saved result. | P89: =IFERROR(N(F89),0)+SUM(SharedData!$A$6:$A$8)+ROW()/100000 -> 0.00089
A90: function:int | B90: Math and trigonometry | C90: INT | D90: Function-catalog probe; genuine error results are retained as oracle evidence | E90: =INT(0.5) | F90: =INT(0.5) -> 0 | M90: oracle_probe | O90: Recalculate in Excel and compare the saved result.
A91: function:iso-ceiling | B91: Math and trigonometry | C91: ISO.CEILING | D91: Function-catalog probe; genuine error results are retained as oracle evidence | E91: =ISO.CEILING(0.5) | F91: =ISO.CEILING(0.5) -> 1 | M91: oracle_probe | O91: Recalculate in Excel and compare the saved result.
A92: function:lcm | B92: Math and trigonometry | C92: LCM | D92: Curated deterministic boundary with shared-data and cross-sheet inputs | E92: =LCM(12,18,30) | F92: =LCM(12,18,30) -> 180 | M92: oracle_probe | O92: Recalculate in Excel and compare the saved result.
A93: function:ln | B93: Math and trigonometry | C93: LN | D93: Function-catalog probe; genuine error results are retained as oracle evidence | E93: =LN(0.5) | F93: =LN(0.5) -> -0.69314718 | M93: oracle_probe | N93: =IF(ISERROR(F93),"ERROR "&IFERROR(ERROR.TYPE(F93),""),"OK") -> OK | O93: Recalculate in Excel and compare the saved result.
A94: function:log | B94: Math and trigonometry | C94: LOG | D94: Function-catalog probe; genuine error results are retained as oracle evidence | E94: =LOG(0.5) | F94: =LOG(0.5) -> -0.30103 | M94: oracle_probe | O94: Recalculate in Excel and compare the saved result.
A95: function:log10 | B95: Math and trigonometry | C95: LOG10 | D95: Function-catalog probe; genuine error results are retained as oracle evidence | E95: =LOG10(0.5) | F95: =LOG10(0.5) -> -0.30103 | M95: oracle_probe | O95: Recalculate in Excel and compare the saved result.
A96: function:loginv | B96: Math and trigonometry | C96: LOGINV | D96: Function-catalog probe with a repaired call signature | E96: =LOGINV(0.6,2,0.5) | F96: =LOGINV(0.6,2,0.5) -> 8.3869217 | M96: oracle_probe | O96: Recalculate in Excel and compare the saved result.
A97: function:lognorm-dist | B97: Math and trigonometry | C97: LOGNORM.DIST | D97: Function-catalog probe with a repaired call signature | E97: =LOGNORM.DIST(4,2,0.5,TRUE) | F97: =_xlfn.LOGNORM.DIST(4,2,0.5,TRUE) -> 0.10983402 | M97: oracle_probe | O97: Recalculate in Excel and compare the saved result.
A98: function:lognorm-inv | B98: Math and trigonometry | C98: LOGNORM.INV | D98: Function-catalog probe with a repaired call signature | E98: =LOGNORM.INV(0.6,2,0.5) | F98: =_xlfn.LOGNORM.INV(0.6,2,0.5) -> 8.3869217 | M98: oracle_probe | O98: Recalculate in Excel and compare the saved result.
A99: function:lognormdist | B99: Math and trigonometry | C99: LOGNORMDIST | D99: Function-catalog probe with a repaired call signature | E99: =LOGNORMDIST(4,2,0.5) | F99: =LOGNORMDIST(4,2,0.5) -> 0.10983402 | M99: oracle_probe | O99: Recalculate in Excel and compare the saved result.
A100: function:mdeterm | B100: Math and trigonometry | C100: MDETERM | D100: Curated deterministic boundary with shared-data and cross-sheet inputs | E100: =MDETERM({1,2;3,4}) | F100: =MDETERM({1,2;3,4}) -> -2 | M100: oracle_probe | O100: Recalculate in Excel and compare the saved result.
...

Sheet Aggregates
A1: Aggregates — CellRune Excel Oracle
A2: Blue cells are formulas. Gray rows are catalogued exclusions. Excel must recalculate and save cached values. | R2: Catalog rows | S2: =COUNTA(A5:A178) -> 174
R3: Primary cases | S3: =COUNTA(A5:A178) -> 174
A4: Case ID | B4: Category | C4: Function | D4: Scenario | E4: Formula text | F4: Result / spill zone | M4: Expectation | N4: Sentinel | O4: Note | P4: Dependency signature | R4: Active formulas | S4: =COUNTA(A5:A178)-COUNTIF(M5:M178,"excluded") -> 174
A5: function:avedev | B5: Statistical | C5: AVEDEV | D5: Function-catalog probe; genuine error results are retained as oracle evidence | E5: =AVEDEV('SharedData'!$E$6:$E$25) | F5: =AVEDEV(SharedData!$E$6:$E$25) -> 50 | M5: oracle_probe | N5: =IF(ISERROR(F5),"ERROR "&IFERROR(ERROR.TYPE(F5),""),"OK") -> OK | O5: Recalculate in Excel and compare the saved result. | P5: =IFERROR(N(F5),0)+IFERROR(N(Arithmetic!$F$5),0)+ROW()/100000 -> 50.30005
A6: function:average | B6: Statistical | C6: AVERAGE | D6: Function-catalog probe; genuine error results are retained as oracle evidence | E6: =AVERAGE('SharedData'!$E$6:$E$25) | F6: =AVERAGE(SharedData!$E$6:$E$25) -> 105 | M6: oracle_probe | O6: Recalculate in Excel and compare the saved result.
A7: function:averagea | B7: Statistical | C7: AVERAGEA | D7: Function-catalog probe; genuine error results are retained as oracle evidence | E7: =AVERAGEA('SharedData'!$E$6:$E$25) | F7: =AVERAGEA(SharedData!$E$6:$E$25) -> 105 | M7: oracle_probe | O7: Recalculate in Excel and compare the saved result.
A8: function:averageif | B8: Statistical | C8: AVERAGEIF | D8: Curated deterministic boundary with shared-data and cross-sheet inputs | E8: =AVERAGEIF('SharedData'!$C$6:$C$25,"A",'SharedData'!$E$6:$E$25) | F8: =AVERAGEIF(SharedData!$C$6:$C$25,"A",SharedData!$E$6:$E$25) -> 100 | M8: oracle_probe | O8: Recalculate in Excel and compare the saved result.
A9: function:averageifs | B9: Statistical | C9: AVERAGEIFS | D9: Curated deterministic boundary with shared-data and cross-sheet inputs | E9: =AVERAGEIFS('SharedData'!$E$6:$E$25,'SharedData'!$C$6:$C$25,"A",'SharedData'!$F$6:$F$25,">5") | F9: =AVERAGEIFS(SharedData!$E$6:$E$25,SharedData!$C$6:$C$25,"A",SharedData!$F$6:$F$25,">5") -> 100 | M9: oracle_probe | O9: Recalculate in Excel and compare the saved result.
A10: function:beta-dist | B10: Statistical | C10: BETA.DIST | D10: Function-catalog probe with a repaired call signature | E10: =BETA.DIST(0.6,8,10,TRUE,0,1) | F10: =_xlfn.BETA.DIST(0.6,8,10,TRUE,0,1) -> 0.90810075 | M10: oracle_probe | O10: Recalculate in Excel and compare the saved result.
A11: function:beta-inv | B11: Statistical | C11: BETA.INV | D11: Function-catalog probe with a repaired call signature | E11: =BETA.INV(0.6,8,10,0,1) | F11: =_xlfn.BETA.INV(0.6,8,10,0,1) -> 0.47252659 | M11: oracle_probe | O11: Recalculate in Excel and compare the saved result.
A12: function:betadist | B12: Statistical | C12: BETADIST | D12: Curated deterministic boundary with shared-data and cross-sheet inputs | E12: =BETADIST(0.5,2,3,0,1) | F12: =BETADIST(0.5,2,3,0,1) -> 0.6875 | M12: oracle_probe | O12: Recalculate in Excel and compare the saved result.
A13: function:betainv | B13: Statistical | C13: BETAINV | D13: Curated deterministic boundary with shared-data and cross-sheet inputs | E13: =BETAINV(0.5,2,3,0,1) | F13: =BETAINV(0.5,2,3,0,1) -> 0.38572757 | M13: oracle_probe | N13: =IF(ISERROR(F13),"ERROR "&IFERROR(ERROR.TYPE(F13),""),"OK") -> OK | O13: Recalculate in Excel and compare the saved result.
A14: function:binom-dist | B14: Statistical | C14: BINOM.DIST | D14: Curated deterministic boundary with shared-data and cross-sheet inputs | E14: =BINOM.DIST(3,10,0.4,FALSE) | F14: =_xlfn.BINOM.DIST(3,10,0.4,FALSE) -> 0.21499085 | M14: oracle_probe | O14: Recalculate in Excel and compare the saved result.
A15: function:binom-dist-range | B15: Statistical | C15: BINOM.DIST.RANGE | D15: Curated deterministic boundary with shared-data and cross-sheet inputs | E15: =BINOM.DIST.RANGE(10,0.4,3,6) | F15: =_xlfn.BINOM.DIST.RANGE(10,0.4,3,6) -> 0.77794836 | M15: oracle_probe | O15: Recalculate in Excel and compare the saved result.
A16: function:binom-inv | B16: Statistical | C16: BINOM.INV | D16: Curated deterministic boundary with shared-data and cross-sheet inputs | E16: =BINOM.INV(10,0.4,0.6) | F16: =_xlfn.BINOM.INV(10,0.4,0.6) -> 4 | M16: oracle_probe | O16: Recalculate in Excel and compare the saved result.
A17: function:binomdist | B17: Statistical | C17: BINOMDIST | D17: Curated deterministic boundary with shared-data and cross-sheet inputs | E17: =BINOMDIST(3,10,0.4,FALSE) | F17: =BINOMDIST(3,10,0.4,FALSE) -> 0.21499085 | M17: oracle_probe | O17: Recalculate in Excel and compare the saved result. | P17: =IFERROR(N(F17),0)+IFERROR(N(Arithmetic!$F$5),0)+ROW()/100000 -> 0.51516085
A18: function:chidist | B18: Statistical | C18: CHIDIST | D18: Curated deterministic boundary with shared-data and cross-sheet inputs | E18: =CHIDIST(4,3) | F18: =CHIDIST(4,3) -> 0.26146413 | M18: oracle_probe | O18: Recalculate in Excel and compare the saved result.
A19: function:chiinv | B19: Statistical | C19: CHIINV | D19: Curated deterministic boundary with shared-data and cross-sheet inputs | E19: =CHIINV(0.05,3) | F19: =CHIINV(0.05,3) -> 7.8147279 | M19: oracle_probe | O19: Recalculate in Excel and compare the saved result.
A20: function:chisq-dist | B20: Statistical | C20: CHISQ.DIST | D20: Curated deterministic boundary with shared-data and cross-sheet inputs | E20: =CHISQ.DIST(4,3,TRUE) | F20: =_xlfn.CHISQ.DIST(4,3,TRUE) -> 0.73853587 | M20: oracle_probe | O20: Recalculate in Excel and compare the saved result.
A21: function:chisq-dist-rt | B21: Statistical | C21: CHISQ.DIST.RT | D21: Curated deterministic boundary with shared-data and cross-sheet inputs | E21: =CHISQ.DIST.RT(4,3) | F21: =_xlfn.CHISQ.DIST.RT(4,3) -> 0.26146413 | M21: oracle_probe | N21: =IF(ISERROR(F21),"ERROR "&IFERROR(ERROR.TYPE(F21),""),"OK") -> OK | O21: Recalculate in Excel and compare the saved result.
A22: function:chisq-inv | B22: Statistical | C22: CHISQ.INV | D22: Curated deterministic boundary with shared-data and cross-sheet inputs | E22: =CHISQ.INV(0.95,3) | F22: =_xlfn.CHISQ.INV(0.95,3) -> 7.8147279 | M22: oracle_probe | O22: Recalculate in Excel and compare the saved result.
A23: function:chisq-inv-rt | B23: Statistical | C23: CHISQ.INV.RT | D23: Curated deterministic boundary with shared-data and cross-sheet inputs | E23: =CHISQ.INV.RT(0.05,3) | F23: =_xlfn.CHISQ.INV.RT(0.05,3) -> 7.8147279 | M23: oracle_probe | O23: Recalculate in Excel and compare the saved result.
A24: function:chisq-test | B24: Statistical | C24: CHISQ.TEST | D24: Curated deterministic boundary with shared-data and cross-sheet inputs | E24: =CHISQ.TEST('SharedData'!$E$6:$F$8,'SharedData'!$I$6:$J$8) | F24: =_xlfn.CHISQ.TEST(SharedData!$E$6:$F$8,SharedData!$I$6:$J$8) -> 1.3410807e-108 | M24: oracle_probe | O24: Recalculate in Excel and compare the saved result.
A25: function:chitest | B25: Statistical | C25: CHITEST | D25: Curated deterministic boundary with shared-data and cross-sheet inputs | E25: =CHITEST('SharedData'!$E$6:$F$8,'SharedData'!$I$6:$J$8) | F25: =CHITEST(SharedData!$E$6:$F$8,SharedData!$I$6:$J$8) -> 1.3410807e-108 | M25: oracle_probe | O25: Recalculate in Excel and compare the saved result.
A26: function:confidence | B26: Statistical | C26: CONFIDENCE | D26: Curated deterministic boundary with shared-data and cross-sheet inputs | E26: =CONFIDENCE(0.05,2.5,100) | F26: =CONFIDENCE(0.05,2.5,100) -> 0.489991 | M26: oracle_probe | O26: Recalculate in Excel and compare the saved result.
A27: function:confidence-norm | B27: Statistical | C27: CONFIDENCE.NORM | D27: Curated deterministic boundary with shared-data and cross-sheet inputs | E27: =CONFIDENCE.NORM(0.05,2.5,100) | F27: =_xlfn.CONFIDENCE.NORM(0.05,2.5,100) -> 0.489991 | M27: oracle_probe | O27: Recalculate in Excel and compare the saved result.
A28: function:confidence-t | B28: Statistical | C28: CONFIDENCE.T | D28: Curated deterministic boundary with shared-data and cross-sheet inputs | E28: =CONFIDENCE.T(0.05,2.5,100) | F28: =_xlfn.CONFIDENCE.T(0.05,2.5,100) -> 0.49605424 | M28: oracle_probe | O28: Recalculate in Excel and compare the saved result.
A29: function:correl | B29: Statistical | C29: CORREL | D29: Curated deterministic boundary with shared-data and cross-sheet inputs | E29: =CORREL('SharedData'!$I$6:$I$25,'SharedData'!$J$6:$J$25) | F29: =CORREL(SharedData!$I$6:$I$25,SharedData!$J$6:$J$25) -> 1 | M29: oracle_probe | N29: =IF(ISERROR(F29),"ERROR "&IFERROR(ERROR.TYPE(F29),""),"OK") -> OK | O29: Recalculate in Excel and compare the saved result. | P29: =IFERROR(N(F29),0)+IFERROR(N(Arithmetic!$F$17),0)+ROW()/100000 -> 1.00029
A30: function:count | B30: Statistical | C30: COUNT | D30: Function-catalog probe; genuine error results are retained as oracle evidence | E30: =COUNT('SharedData'!$E$6:$E$25) | F30: =COUNT(SharedData!$E$6:$E$25) -> 20 | M30: oracle_probe | O30: Recalculate in Excel and compare the saved result.
A31: function:counta | B31: Statistical | C31: COUNTA | D31: Function-catalog probe; genuine error results are retained as oracle evidence | E31: =COUNTA('SharedData'!$E$6:$E$25) | F31: =COUNTA(SharedData!$E$6:$E$25) -> 20 | M31: oracle_probe | O31: Recalculate in Excel and compare the saved result.
A32: function:countblank | B32: Statistical | C32: COUNTBLANK | D32: Function-catalog probe; genuine error results are retained as oracle evidence | E32: =COUNTBLANK('SharedData'!$E$6:$E$25) | F32: =COUNTBLANK(SharedData!$E$6:$E$25) -> 0 | M32: oracle_probe | O32: Recalculate in Excel and compare the saved result.
A33: function:countif | B33: Statistical | C33: COUNTIF | D33: Curated deterministic boundary with shared-data and cross-sheet inputs | E33: =COUNTIF('SharedData'!$C$6:$C$25,"A") | F33: =COUNTIF(SharedData!$C$6:$C$25,"A") -> 7 | M33: oracle_probe | O33: Recalculate in Excel and compare the saved result.
A34: function:countifs | B34: Statistical | C34: COUNTIFS | D34: Curated deterministic boundary with shared-data and cross-sheet inputs | E34: =COUNTIFS('SharedData'!$C$6:$C$25,"A",'SharedData'!$E$6:$E$25,">50") | F34: =COUNTIFS(SharedData!$C$6:$C$25,"A",SharedData!$E$6:$E$25,">50") -> 5 | M34: oracle_probe | O34: Recalculate in Excel and compare the saved result.
A35: function:covar | B35: Statistical | C35: COVAR | D35: Curated deterministic boundary with shared-data and cross-sheet inputs | E35: =COVAR('SharedData'!$I$6:$I$25,'SharedData'!$J$6:$J$25) | F35: =COVAR(SharedData!$I$6:$I$25,SharedData!$J$6:$J$25) -> 66.5 | M35: oracle_probe | O35: Recalculate in Excel and compare the saved result.
A36: function:covariance-p | B36: Statistical | C36: COVARIANCE.P | D36: Curated deterministic boundary with shared-data and cross-sheet inputs | E36: =COVARIANCE.P('SharedData'!$I$6:$I$25,'SharedData'!$J$6:$J$25) | F36: =_xlfn.COVARIANCE.P(SharedData!$I$6:$I$25,SharedData!$J$6:$J$25) -> 66.5 | M36: oracle_probe | O36: Recalculate in Excel and compare the saved result.
A37: function:covariance-s | B37: Statistical | C37: COVARIANCE.S | D37: Curated deterministic boundary with shared-data and cross-sheet inputs | E37: =COVARIANCE.S('SharedData'!$I$6:$I$25,'SharedData'!$J$6:$J$25) | F37: =_xlfn.COVARIANCE.S(SharedData!$I$6:$I$25,SharedData!$J$6:$J$25) -> 70 | M37: oracle_probe | N37: =IF(ISERROR(F37),"ERROR "&IFERROR(ERROR.TYPE(F37),""),"OK") -> OK | O37: Recalculate in Excel and compare the saved result.
A38: function:critbinom | B38: Statistical | C38: CRITBINOM | D38: Curated deterministic boundary with shared-data and cross-sheet inputs | E38: =CRITBINOM(10,0.4,0.6) | F38: =CRITBINOM(10,0.4,0.6) -> 4 | M38: oracle_probe | O38: Recalculate in Excel and compare the saved result.
A39: function:daverage | B39: Database | C39: DAVERAGE | D39: Function-catalog probe; genuine error results are retained as oracle evidence | E39: =DAVERAGE('SharedData'!$A$30:$F$50,"Amount",'SharedData'!$H$30:$I$32) | F39: =DAVERAGE(SharedData!$A$30:$F$50,"Amount",SharedData!$H$30:$I$32) -> 101.11111 | M39: oracle_probe | O39: Recalculate in Excel and compare the saved result.
A40: function:dcount | B40: Database | C40: DCOUNT | D40: Function-catalog probe; genuine error results are retained as oracle evidence | E40: =DCOUNT('SharedData'!$A$30:$F$50,"Amount",'SharedData'!$H$30:$I$32) | F40: =DCOUNT(SharedData!$A$30:$F$50,"Amount",SharedData!$H$30:$I$32) -> 9 | M40: oracle_probe | O40: Recalculate in Excel and compare the saved result.
A41: function:dcounta | B41: Database | C41: DCOUNTA | D41: Function-catalog probe; genuine error results are retained as oracle evidence | E41: =DCOUNTA('SharedData'!$A$30:$F$50,"Amount",'SharedData'!$H$30:$I$32) | F41: =DCOUNTA(SharedData!$A$30:$F$50,"Amount",SharedData!$H$30:$I$32) -> 9 | M41: oracle_probe | O41: Recalculate in Excel and compare the saved result. | P41: =IFERROR(N(F41),0)+IFERROR(N(Arithmetic!$F$29),0)+ROW()/100000 -> 19.00041
A42: function:devsq | B42: Statistical | C42: DEVSQ | D42: Function-catalog probe; genuine error results are retained as oracle evidence | E42: =DEVSQ('SharedData'!$E$6:$E$25) | F42: =DEVSQ(SharedData!$E$6:$E$25) -> 66500 | M42: oracle_probe | O42: Recalculate in Excel and compare the saved result.
A43: function:dget | B43: Database | C43: DGET | D43: Function-catalog probe; genuine error results are retained as oracle evidence | E43: =DGET('SharedData'!$A$30:$F$50,"Amount",'SharedData'!$H$30:$I$32) | F43: =DGET(SharedData!$A$30:$F$50,"Amount",SharedData!$H$30:$I$32) -> #NUM! | M43: oracle_probe | O43: Recalculate in Excel and compare the saved result.
A44: function:dmax | B44: Database | C44: DMAX | D44: Function-catalog probe; genuine error results are retained as oracle evidence | E44: =DMAX('SharedData'!$A$30:$F$50,"Amount",'SharedData'!$H$30:$I$32) | F44: =DMAX(SharedData!$A$30:$F$50,"Amount",SharedData!$H$30:$I$32) -> 190 | M44: oracle_probe | O44: Recalculate in Excel and compare the saved result.
A45: function:dmin | B45: Database | C45: DMIN | D45: Function-catalog probe; genuine error results are retained as oracle evidence | E45: =DMIN('SharedData'!$A$30:$F$50,"Amount",'SharedData'!$H$30:$I$32) | F45: =DMIN(SharedData!$A$30:$F$50,"Amount",SharedData!$H$30:$I$32) -> 20 | M45: oracle_probe | N45: =IF(ISERROR(F45),"ERROR "&IFERROR(ERROR.TYPE(F45),""),"OK") -> OK | O45: Recalculate in Excel and compare the saved result.
A46: function:dproduct | B46: Database | C46: DPRODUCT | D46: Function-catalog probe; genuine error results are retained as oracle evidence | E46: =DPRODUCT('SharedData'!$A$30:$F$50,"Amount",'SharedData'!$H$30:$I$32) | F46: =DPRODUCT(SharedData!$A$30:$F$50,"Amount",SharedData!$H$30:$I$32) -> 2.434432e+17 | M46: oracle_probe | O46: Recalculate in Excel and compare the saved result.
A47: function:dstdev | B47: Database | C47: DSTDEV | D47: Function-catalog probe; genuine error results are retained as oracle evidence | E47: =DSTDEV('SharedData'!$A$30:$F$50,"Amount",'SharedData'!$H$30:$I$32) | F47: =DSTDEV(SharedData!$A$30:$F$50,"Amount",SharedData!$H$30:$I$32) -> 53.489355 | M47: oracle_probe | O47: Recalculate in Excel and compare the saved result.
A48: function:dstdevp | B48: Database | C48: DSTDEVP | D48: Function-catalog probe; genuine error results are retained as oracle evidence | E48: =DSTDEVP('SharedData'!$A$30:$F$50,"Amount",'SharedData'!$H$30:$I$32) | F48: =DSTDEVP(SharedData!$A$30:$F$50,"Amount",SharedData!$H$30:$I$32) -> 50.430248 | M48: oracle_probe | O48: Recalculate in Excel and compare the saved result.
A49: function:dsum | B49: Database | C49: DSUM | D49: Function-catalog probe; genuine error results are retained as oracle evidence | E49: =DSUM('SharedData'!$A$30:$F$50,"Amount",'SharedData'!$H$30:$I$32) | F49: =DSUM(SharedData!$A$30:$F$50,"Amount",SharedData!$H$30:$I$32) -> 910 | M49: oracle_probe | O49: Recalculate in Excel and compare the saved result.
A50: function:dvar | B50: Database | C50: DVAR | D50: Function-catalog probe; genuine error results are retained as oracle evidence | E50: =DVAR('SharedData'!$A$30:$F$50,"Amount",'SharedData'!$H$30:$I$32) | F50: =DVAR(SharedData!$A$30:$F$50,"Amount",SharedData!$H$30:$I$32) -> 2861.1111 | M50: oracle_probe | O50: Recalculate in Excel and compare the saved result.
A51: function:dvarp | B51: Database | C51: DVARP | D51: Function-catalog probe; genuine error results are retained as oracle evidence | E51: =DVARP('SharedData'!$A$30:$F$50,"Amount",'SharedData'!$H$30:$I$32) | F51: =DVARP(SharedData!$A$30:$F$50,"Amount",SharedData!$H$30:$I$32) -> 2543.2099 | M51: oracle_probe | O51: Recalculate in Excel and compare the saved result.
A52: function:expon-dist | B52: Statistical | C52: EXPON.DIST | D52: Function-catalog probe with a repaired call signature | E52: =EXPON.DIST(0.5,1,TRUE) | F52: =_xlfn.EXPON.DIST(0.5,1,TRUE) -> 0.39346934 | M52: oracle_probe | O52: Recalculate in Excel and compare the saved result.
A53: function:expondist | B53: Statistical | C53: EXPONDIST | D53: Function-catalog probe with a repaired call signature | E53: =EXPONDIST(0.5,1,TRUE) | F53: =EXPONDIST(0.5,1,TRUE) -> 0.39346934 | M53: oracle_probe | N53: =IF(ISERROR(F53),"ERROR "&IFERROR(ERROR.TYPE(F53),""),"OK") -> OK | O53: Recalculate in Excel and compare the saved result. | P53: =IFERROR(N(F53),0)+IFERROR(N(Arithmetic!$F$41),0)+ROW()/100000 -> 2.479829
A54: function:f-dist | B54: Statistical | C54: F.DIST | D54: Function-catalog probe with a repaired call signature | E54: =F.DIST(1.5,6,4,TRUE) | F54: =_xlfn.F.DIST(1.5,6,4,TRUE) -> 0.63810791 | M54: oracle_probe | O54: Recalculate in Excel and compare the saved result.
A55: function:f-dist-rt | B55: Statistical | C55: F.DIST.RT | D55: Function-catalog probe with a repaired call signature | E55: =F.DIST.RT(1.5,6,4) | F55: =_xlfn.F.DIST.RT(1.5,6,4) -> 0.36189209 | M55: oracle_probe | O55: Recalculate in Excel and compare the saved result.
A56: function:f-inv | B56: Statistical | C56: F.INV | D56: Function-catalog probe with a repaired call signature | E56: =F.INV(0.9,6,4) | F56: =_xlfn.F.INV(0.9,6,4) -> 4.0097493 | M56: oracle_probe | O56: Recalculate in Excel and compare the saved result.
A57: function:f-inv-rt | B57: Statistical | C57: F.INV.RT | D57: Function-catalog probe with a repaired call signature | E57: =F.INV.RT(0.1,6,4) | F57: =_xlfn.F.INV.RT(0.1,6,4) -> 4.0097493 | M57: oracle_probe | O57: Recalculate in Excel and compare the saved result.
A58: function:f-test | B58: Statistical | C58: F.TEST | D58: Curated deterministic boundary with shared-data and cross-sheet inputs | E58: =F.TEST('SharedData'!$E$6:$E$15,'SharedData'!$F$6:$F$15) | F58: =_xlfn.F.TEST(SharedData!$E$6:$E$15,SharedData!$F$6:$F$15) -> 4.0987363e-09 | M58: oracle_probe | O58: Recalculate in Excel and compare the saved result.
A59: function:fdist | B59: Statistical | C59: FDIST | D59: Function-catalog probe with a repaired call signature | E59: =FDIST(1.5,6,4) | F59: =FDIST(1.5,6,4) -> 0.36189209 | M59: oracle_probe | O59: Recalculate in Excel and compare the saved result.
A60: function:finv | B60: Statistical | C60: FINV | D60: Function-catalog probe with a repaired call signature | E60: =FINV(0.1,6,4) | F60: =FINV(0.1,6,4) -> 4.0097493 | M60: oracle_probe | O60: Recalculate in Excel and compare the saved result.
A61: function:fisher | B61: Statistical | C61: FISHER | D61: Function-catalog probe with a repaired call signature | E61: =FISHER(0.75) | F61: =FISHER(0.75) -> 0.97295507 | M61: oracle_probe | N61: =IF(ISERROR(F61),"ERROR "&IFERROR(ERROR.TYPE(F61),""),"OK") -> OK | O61: Recalculate in Excel and compare the saved result.
A62: function:fisherinv | B62: Statistical | C62: FISHERINV | D62: Function-catalog probe with a repaired call signature | E62: =FISHERINV(0.9) | F62: =FISHERINV(0.9) -> 0.71629787 | M62: oracle_probe | O62: Recalculate in Excel and compare the saved result.
A63: function:forecast | B63: Statistical | C63: FORECAST | D63: Curated deterministic boundary with shared-data and cross-sheet inputs | E63: =FORECAST(21,'SharedData'!$J$6:$J$25,'SharedData'!$I$6:$I$25) | F63: =FORECAST(21,SharedData!$J$6:$J$25,SharedData!$I$6:$I$25) -> 45 | M63: oracle_probe | O63: Recalculate in Excel and compare the saved result.
A64: function:forecast-ets | B64: Statistical | C64: FORECAST.ETS | D64: Curated deterministic boundary with shared-data and cross-sheet inputs | E64: =FORECAST.ETS('SharedData'!$D$25+30,'SharedData'!$E$6:$E$25,'SharedData'!$D$6:$D$25,1,1,1) | F64: =_xlfn.FORECAST.ETS(SharedData!$D$25+30,SharedData!$E$6:$E$25,SharedData!$D$6:$D$25,1,1,1) -> #N/A | M64: oracle_probe | O64: Recalculate in Excel and compare the saved result.
A65: function:forecast-ets-confint | B65: Statistical | C65: FORECAST.ETS.CONFINT | D65: Curated deterministic boundary with shared-data and cross-sheet inputs | E65: =FORECAST.ETS.CONFINT('SharedData'!$D$25+30,'SharedData'!$E$6:$E$25,'SharedData'!$D$6:$D$25,0.95,1,1,1) | F65: =_xlfn.FORECAST.ETS.CONFINT(SharedData!$D$25+30,SharedData!$E$6:$E$25,SharedData!$D$6:$D$25,0.95,1,1,1) -> #N/A | M65: oracle_probe | O65: Recalculate in Excel and compare the saved result. | P65: =IFERROR(N(F65),0)+IFERROR(N(Arithmetic!$F$53),0)+ROW()/100000 -> 2.00065
A66: function:forecast-ets-seasonality | B66: Statistical | C66: FORECAST.ETS.SEASONALITY | D66: Curated deterministic boundary with shared-data and cross-sheet inputs | E66: =FORECAST.ETS.SEASONALITY('SharedData'!$E$6:$E$25,'SharedData'!$D$6:$D$25,1,1) | F66: =_xlfn.FORECAST.ETS.SEASONALITY(SharedData!$E$6:$E$25,SharedData!$D$6:$D$25,1,1) -> #N/A | M66: oracle_probe | O66: Recalculate in Excel and compare the saved result.
A67: function:forecast-ets-stat | B67: Statistical | C67: FORECAST.ETS.STAT | D67: Curated deterministic boundary with shared-data and cross-sheet inputs | E67: =FORECAST.ETS.STAT('SharedData'!$E$6:$E$25,'SharedData'!$D$6:$D$25,1,1,1,1) | F67: =_xlfn.FORECAST.ETS.STAT(SharedData!$E$6:$E$25,SharedData!$D$6:$D$25,1,1,1,1) -> #N/A | M67: oracle_probe | O67: Recalculate in Excel and compare the saved result.
A68: function:forecast-linear | B68: Statistical | C68: FORECAST.LINEAR | D68: Curated deterministic boundary with shared-data and cross-sheet inputs | E68: =FORECAST.LINEAR(21,'SharedData'!$J$6:$J$25,'SharedData'!$I$6:$I$25) | F68: =_xlfn.FORECAST.LINEAR(21,SharedData!$J$6:$J$25,SharedData!$I$6:$I$25) -> 45 | M68: oracle_probe | O68: Recalculate in Excel and compare the saved result.
A69: function:ftest | B69: Statistical | C69: FTEST | D69: Curated deterministic boundary with shared-data and cross-sheet inputs | E69: =FTEST('SharedData'!$E$6:$E$15,'SharedData'!$F$6:$F$15) | F69: =FTEST(SharedData!$E$6:$E$15,SharedData!$F$6:$F$15) -> 4.0987363e-09 | M69: oracle_probe | N69: =IF(ISERROR(F69),"ERROR "&IFERROR(ERROR.TYPE(F69),""),"OK") -> OK | O69: Recalculate in Excel and compare the saved result.
A70: function:gamma | B70: Statistical | C70: GAMMA | D70: Function-catalog probe with a repaired call signature | E70: =GAMMA(2.5) | F70: =_xlfn.GAMMA(2.5) -> 1.3293404 | M70: oracle_probe | O70: Recalculate in Excel and compare the saved result.
A71: function:gamma-dist | B71: Statistical | C71: GAMMA.DIST | D71: Function-catalog probe with a repaired call signature | E71: =GAMMA.DIST(2,3,1.5,TRUE) | F71: =_xlfn.GAMMA.DIST(2,3,1.5,TRUE) -> 0.15063144 | M71: oracle_probe | O71: Recalculate in Excel and compare the saved result.
A72: function:gamma-inv | B72: Statistical | C72: GAMMA.INV | D72: Function-catalog probe with a repaired call signature | E72: =GAMMA.INV(0.7,3,1.5) | F72: =_xlfn.GAMMA.INV(0.7,3,1.5) -> 5.4233515 | M72: oracle_probe | O72: Recalculate in Excel and compare the saved result.
A73: function:gammadist | B73: Statistical | C73: GAMMADIST | D73: Function-catalog probe with a repaired call signature | E73: =GAMMADIST(2,3,1.5,TRUE) | F73: =GAMMADIST(2,3,1.5,TRUE) -> 0.15063144 | M73: oracle_probe | O73: Recalculate in Excel and compare the saved result.
A74: function:gammainv | B74: Statistical | C74: GAMMAINV | D74: Function-catalog probe with a repaired call signature | E74: =GAMMAINV(0.7,3,1.5) | F74: =GAMMAINV(0.7,3,1.5) -> 5.4233515 | M74: oracle_probe | O74: Recalculate in Excel and compare the saved result.
A75: function:gammaln | B75: Statistical | C75: GAMMALN | D75: Function-catalog probe with a repaired call signature | E75: =GAMMALN(4.5) | F75: =GAMMALN(4.5) -> 2.4537366 | M75: oracle_probe | O75: Recalculate in Excel and compare the saved result.
A76: function:gammaln-precise | B76: Statistical | C76: GAMMALN.PRECISE | D76: Function-catalog probe with a repaired call signature | E76: =GAMMALN.PRECISE(4.5) | F76: =_xlfn.GAMMALN.PRECISE(4.5) -> 2.4537366 | M76: oracle_probe | O76: Recalculate in Excel and compare the saved result.
A77: function:gauss | B77: Statistical | C77: GAUSS | D77: Function-catalog probe with a repaired call signature | E77: =GAUSS(1.28) | F77: =_xlfn.GAUSS(1.28) -> 0.39972743 | M77: oracle_probe | N77: =IF(ISERROR(F77),"ERROR "&IFERROR(ERROR.TYPE(F77),""),"OK") -> OK | O77: Recalculate in Excel and compare the saved result. | P77: =IFERROR(N(F77),0)+IFERROR(N(Arithmetic!$F$65),0)+ROW()/100000 -> 5.4004974
A78: function:geomean | B78: Statistical | C78: GEOMEAN | D78: Function-catalog probe; genuine error results are retained as oracle evidence | E78: =GEOMEAN('SharedData'!$E$6:$E$25) | F78: =GEOMEAN(SharedData!$E$6:$E$25) -> 83.043612 | M78: oracle_probe | O78: Recalculate in Excel and compare the saved result.
A79: function:harmean | B79: Statistical | C79: HARMEAN | D79: Function-catalog probe; genuine error results are retained as oracle evidence | E79: =HARMEAN('SharedData'!$E$6:$E$25) | F79: =HARMEAN(SharedData!$E$6:$E$25) -> 55.590459 | M79: oracle_probe | O79: Recalculate in Excel and compare the saved result.
A80: function:hypgeom-dist | B80: Statistical | C80: HYPGEOM.DIST | D80: Function-catalog probe with a repaired call signature | E80: =HYPGEOM.DIST(1,4,8,20,TRUE) | F80: =_xlfn.HYPGEOM.DIST(1,4,8,20,TRUE) -> 0.46542828 | M80: oracle_probe | O80: Recalculate in Excel and compare the saved result.
A81: function:hypgeomdist | B81: Statistical | C81: HYPGEOMDIST | D81: Function-catalog probe with a repaired call signature | E81: =HYPGEOMDIST(1,4,8,20) | F81: =HYPGEOMDIST(1,4,8,20) -> 0.36326109 | M81: oracle_probe | O81: Recalculate in Excel and compare the saved result.
A82: function:intercept | B82: Statistical | C82: INTERCEPT | D82: Curated deterministic boundary with shared-data and cross-sheet inputs | E82: =INTERCEPT('SharedData'!$J$6:$J$25,'SharedData'!$I$6:$I$25) | F82: =INTERCEPT(SharedData!$J$6:$J$25,SharedData!$I$6:$I$25) -> 3 | M82: oracle_probe | O82: Recalculate in Excel and compare the saved result.
A83: function:kurt | B83: Statistical | C83: KURT | D83: Function-catalog probe; genuine error results are retained as oracle evidence | E83: =KURT('SharedData'!$E$6:$E$25) | F83: =KURT(SharedData!$E$6:$E$25) -> -1.2 | M83: oracle_probe | O83: Recalculate in Excel and compare the saved result.
A84: function:large | B84: Statistical | C84: LARGE | D84: Function-catalog probe with a repaired call signature | E84: =LARGE('SharedData'!$E$6:$E$25,3) | F84: =LARGE(SharedData!$E$6:$E$25,3) -> 180 | M84: oracle_probe | O84: Recalculate in Excel and compare the saved result.
A85: function:max | B85: Statistical | C85: MAX | D85: Function-catalog probe; genuine error results are retained as oracle evidence | E85: =MAX('SharedData'!$E$6:$E$25) | F85: =MAX(SharedData!$E$6:$E$25) -> 200 | M85: oracle_probe | N85: =IF(ISERROR(F85),"ERROR "&IFERROR(ERROR.TYPE(F85),""),"OK") -> OK | O85: Recalculate in Excel and compare the saved result.
A86: function:maxa | B86: Statistical | C86: MAXA | D86: Function-catalog probe; genuine error results are retained as oracle evidence | E86: =MAXA('SharedData'!$E$6:$E$25) | F86: =MAXA(SharedData!$E$6:$E$25) -> 200 | M86: oracle_probe | O86: Recalculate in Excel and compare the saved result.
A87: function:maxifs | B87: Statistical | C87: MAXIFS | D87: Curated deterministic boundary with shared-data and cross-sheet inputs | E87: =MAXIFS('SharedData'!$E$6:$E$25,'SharedData'!$C$6:$C$25,"A") | F87: =_xlfn.MAXIFS(SharedData!$E$6:$E$25,SharedData!$C$6:$C$25,"A") -> 190 | M87: oracle_probe | O87: Recalculate in Excel and compare the saved result.
A88: function:median | B88: Statistical | C88: MEDIAN | D88: Function-catalog probe; genuine error results are retained as oracle evidence | E88: =MEDIAN('SharedData'!$E$6:$E$25) | F88: =MEDIAN(SharedData!$E$6:$E$25) -> 105 | M88: oracle_probe | O88: Recalculate in Excel and compare the saved result.
A89: function:min | B89: Statistical | C89: MIN | D89: Function-catalog probe; genuine error results are retained as oracle evidence | E89: =MIN('SharedData'!$E$6:$E$25) | F89: =MIN(SharedData!$E$6:$E$25) -> 10 | M89: oracle_probe | O89: Recalculate in Excel and compare the saved result. | P89: =IFERROR(N(F89),0)+IFERROR(N(Arithmetic!$F$77),0)+ROW()/100000 -> 10.00089
A90: function:mina | B90: Statistical | C90: MINA | D90: Function-catalog probe; genuine error results are retained as oracle evidence | E90: =MINA('SharedData'!$E$6:$E$25) | F90: =MINA(SharedData!$E$6:$E$25) -> 10 | M90: oracle_probe | O90: Recalculate in Excel and compare the saved result.
A91: function:minifs | B91: Statistical | C91: MINIFS | D91: Curated deterministic boundary with shared-data and cross-sheet inputs | E91: =MINIFS('SharedData'!$E$6:$E$25,'SharedData'!$C$6:$C$25,"A") | F91: =_xlfn.MINIFS(SharedData!$E$6:$E$25,SharedData!$C$6:$C$25,"A") -> 10 | M91: oracle_probe | O91: Recalculate in Excel and compare the saved result.
A92: function:mode | B92: Statistical | C92: MODE | D92: Function-catalog probe with a repaired call signature | E92: =MODE({1,2,2,3,4}) | F92: =MODE({1,2,2,3,4}) -> 2 | M92: oracle_probe | O92: Recalculate in Excel and compare the saved result.
A93: function:mode-sngl | B93: Statistical | C93: MODE.SNGL | D93: Function-catalog probe with a repaired call signature | E93: =MODE.SNGL({1,2,2,3,4}) | F93: =_xlfn.MODE.SNGL({1,2,2,3,4}) -> 2 | M93: oracle_probe | N93: =IF(ISERROR(F93),"ERROR "&IFERROR(ERROR.TYPE(F93),""),"OK") -> OK | O93: Recalculate in Excel and compare the saved result.
A94: function:negbinom-dist | B94: Statistical | C94: NEGBINOM.DIST | D94: Function-catalog probe with a repaired call signature | E94: =NEGBINOM.DIST(6,4,0.4,TRUE) | F94: =_xlfn.NEGBINOM.DIST(6,4,0.4,TRUE) -> 0.6177194 | M94: oracle_probe | O94: Recalculate in Excel and compare the saved result.
A95: function:negbinomdist | B95: Statistical | C95: NEGBINOMDIST | D95: Function-catalog probe with a repaired call signature | E95: =NEGBINOMDIST(6,4,0.4) | F95: =NEGBINOMDIST(6,4,0.4) -> 0.10032906 | M95: oracle_probe | O95: Recalculate in Excel and compare the saved result.
A96: function:norm-dist | B96: Statistical | C96: NORM.DIST | D96: Function-catalog probe with a repaired call signature | E96: =NORM.DIST(105,100,12,TRUE) | F96: =_xlfn.NORM.DIST(105,100,12,TRUE) -> 0.66153888 | M96: oracle_probe | O96: Recalculate in Excel and compare the saved result.
A97: function:norm-inv | B97: Statistical | C97: NORM.INV | D97: Function-catalog probe with a repaired call signature | E97: =NORM.INV(0.66,100,12) | F97: =_xlfn.NORM.INV(0.66,100,12) -> 104.94956 | M97: oracle_probe | O97: Recalculate in Excel and compare the saved result.
A98: function:norm-s-dist | B98: Statistical | C98: NORM.S.DIST | D98: Function-catalog probe with a repaired call signature | E98: =NORM.S.DIST(0.75,TRUE) | F98: =_xlfn.NORM.S.DIST(0.75,TRUE) -> 0.77337265 | M98: oracle_probe | O98: Recalculate in Excel and compare the saved result.
A99: function:norm-s-inv | B99: Statistical | C99: NORM.S.INV | D99: Function-catalog probe with a repaired call signature | E99: =NORM.S.INV(0.9) | F99: =_xlfn.NORM.S.INV(0.9) -> 1.2815516 | M99: oracle_probe | O99: Recalculate in Excel and compare the saved result.
A100: function:normdist | B100: Statistical | C100: NORMDIST | D100: Function-catalog probe with a repaired call signature | E100: =NORMDIST(105,100,12,TRUE) | F100: =NORMDIST(105,100,12,TRUE) -> 0.66153888 | M100: oracle_probe | O100: Recalculate in Excel and compare the saved result.
...

Sheet ArraysCSE
A1: ArraysCSE — CellRune Excel Oracle
A2: Blue cells are formulas. Gray rows are catalogued exclusions. Excel must recalculate and save cached values. | R2: Catalog rows | S2: =COUNTA(A5:A80) -> 16
R3: Primary cases | S3: =COUNTA(A5:A80) -> 16
A4: Case ID | B4: Category | C4: Function | D4: Scenario | E4: Formula text | F4: Result / spill zone | M4: Expectation | N4: Sentinel | O4: Note | P4: Dependency signature | R4: Active formulas | S4: =COUNTA(A5:A80)-COUNTIF(M5:M80,"excluded") -> 16
A5: curated:arrayscse:c001 | B5: Curated behaviour | C5: CURATED | D5: Hand-picked semantic boundary named by the oracle plan | E5: =SUM(IF('SharedData'!$C$6:$C$25="A",'SharedData'!$E$6:$E$25,0)) | F5: {=SUM(IF(SharedData!$C$6:$C$25="A",SharedData!$E$6:$E$25,0))} -> 700 | M5: oracle_probe | N5: =IF(ISERROR(F5),"ERROR "&IFERROR(ERROR.TYPE(F5),""),"OK") -> OK | O5: Uses only deterministic workbook inputs; result must be cached by Excel. | P5: =IFERROR(N(F5),0)+IFERROR(N(Aggregates!$F$5),0)+ROW()/100000 -> 750.00005
A10: curated:arrayscse:c002 | B10: Curated behaviour | C10: CURATED | D10: Hand-picked semantic boundary named by the oracle plan | E10: =SUM(IF('SharedData'!$G$6:$G$25,'SharedData'!$E$6:$E$25*'SharedData'!$F$6:$F$25,0)) | F10: {=SUM(IF(SharedData!$G$6:$G$25,SharedData!$E$6:$E$25*SharedData!$F$6:$F$25,0))} -> 3850 | M10: oracle_probe | O10: Uses only deterministic workbook inputs; result must be cached by Excel.
A15: curated:arrayscse:c003 | B15: Curated behaviour | C15: CURATED | D15: Hand-picked semantic boundary named by the oracle plan | E15: =IF({1,0,1;0,1,0;1,1,0},{10,20,30;40,50,60;70,80,90},NA()) | F15: {=IF({1,0,1;0,1,0;1,1,0},{10,20,30;40,50,60;70,80,90},NA())} -> 10 | G15: #N/A | H15: 30 | M15: oracle_probe | O15: Uses only deterministic workbook inputs; result must be cached by Excel.
F16: #N/A | G16: 50 | H16: #N/A
F17: 70 | G17: 80 | H17: #N/A
A20: curated:arrayscse:c004 | B20: Curated behaviour | C20: CURATED | D20: Hand-picked semantic boundary named by the oracle plan | E20: ={1,2,3}*{1;10;100} | F20: {={1,2,3}*{1;10;100}} -> 1 | G20: 2 | H20: 3 | M20: oracle_probe | O20: Uses only deterministic workbook inputs; result must be cached by Excel.
F21: 10 | G21: 20 | H21: 30
F22: 100 | G22: 200 | H22: 300
A25: curated:arrayscse:c005 | B25: Curated behaviour | C25: CURATED | D25: Hand-picked semantic boundary named by the oracle plan | E25: ={1,2,3,4}*{1;2;3} | F25: {={1,2,3,4}*{1;2;3}} -> 1 | G25: 2 | H25: 3 | I25: 4 | M25: oracle_probe | O25: Uses only deterministic workbook inputs; result must be cached by Excel.
F26: 2 | G26: 4 | H26: 6 | I26: 8
F27: 3 | G27: 6 | H27: 9 | I27: 12
A30: curated:arrayscse:c006 | B30: Curated behaviour | C30: CURATED | D30: Hand-picked semantic boundary named by the oracle plan | E30: =IF({TRUE,FALSE;FALSE,TRUE},{"text",2;TRUE,45351},NA()) | F30: {=IF({TRUE,FALSE;FALSE,TRUE},{"text",2;TRUE,45351},NA())} -> text | G30: #N/A | M30: oracle_probe | O30: Uses only deterministic workbook inputs; result must be cached by Excel.
F31: #N/A | G31: 45351
A35: curated:arrayscse:c007 | B35: Curated behaviour | C35: CURATED | D35: Hand-picked semantic boundary named by the oracle plan | E35: ={1,2,3}+{1,2} | F35: {={1,2,3}+{1,2}} -> 2 | G35: 4 | H35: #N/A | M35: oracle_probe | O35: Uses only deterministic workbook inputs; result must be cached by Excel.
A40: curated:arrayscse:c008 | B40: Curated behaviour | C40: CURATED | D40: Hand-picked semantic boundary named by the oracle plan | E40: ={10,20} | F40: {={10,20}} -> 10 | G40: 20 | H40: #N/A | M40: oracle_probe | O40: Uses only deterministic workbook inputs; result must be cached by Excel.
A45: curated:arrayscse:c009 | B45: Curated behaviour | C45: CURATED | D45: Hand-picked semantic boundary named by the oracle plan | E45: ={1,2;3,4}+{10,20,30;40,50,60} | F45: {={1,2;3,4}+{10,20,30;40,50,60}} -> 11 | G45: 22 | H45: #N/A | M45: oracle_probe | N45: =IF(ISERROR(F45),"ERROR "&IFERROR(ERROR.TYPE(F45),""),"OK") -> OK | O45: Uses only deterministic workbook inputs; result must be cached by Excel.
F46: 43 | G46: 54 | H46: #N/A
A50: curated:arrayscse:c010 | B50: Curated behaviour | C50: CURATED | D50: Hand-picked semantic boundary named by the oracle plan | E50: =MMULT({1,2,3;4,5,6},{7,8;9,10;11,12}) | F50: {=MMULT({1,2,3;4,5,6},{7,8;9,10;11,12})} -> 58 | G50: 64 | M50: oracle_probe | O50: Uses only deterministic workbook inputs; result must be cached by Excel.
F51: 139 | G51: 154
A55: curated:arrayscse:c011 | B55: Curated behaviour | C55: CURATED | D55: Hand-picked semantic boundary named by the oracle plan | E55: =TRANSPOSE('SharedData'!$A$6:$C$8) | F55: {=TRANSPOSE(SharedData!$A$6:$C$8)} -> 0.1 | G55: 0.2 | H55: -0.3 | M55: oracle_probe | O55: Uses only deterministic workbook inputs; result must be cached by Excel.
F56: K001 | G56: K002 | H56: K003
F57: A | G57: B | H57: C
A60: curated:arrayscse:c012 | B60: Curated behaviour | C60: CURATED | D60: Hand-picked semantic boundary named by the oracle plan | E60: =SUM(IF(ISNUMBER('SharedData'!$A$6:$H$25),'SharedData'!$A$6:$H$25,0)) | F60: {=SUM(IF(ISNUMBER(SharedData!$A$6:$H$25),SharedData!$A$6:$H$25,0))} -> 884842.65 | M60: oracle_probe | O60: Uses only deterministic workbook inputs; result must be cached by Excel.
A65: curated:arrayscse:c013 | B65: Curated behaviour | C65: CURATED | D65: Hand-picked semantic boundary named by the oracle plan | E65: =SUM(IF('SharedData'!$H$6:$H$25="text",1,0)) | F65: {=SUM(IF(SharedData!$H$6:$H$25="text",1,0))} -> 2 | M65: oracle_probe | O65: Uses only deterministic workbook inputs; result must be cached by Excel. | P65: =IFERROR(N(F65),0)+IFERROR(N(Aggregates!$F$5),0)+ROW()/100000 -> 52.00065
A70: curated:arrayscse:c014 | B70: Curated behaviour | C70: CURATED | D70: Hand-picked semantic boundary named by the oracle plan | E70: =INDEX('SharedData'!$A$6:$F$25,{1;5;10},{1,3,5}) | F70: {=INDEX(SharedData!$A$6:$F$25,{1;5;10},{1,3,5})} -> 0.1 | G70: A | H70: 10 | M70: oracle_probe | O70: Uses only deterministic workbook inputs; result must be cached by Excel.
F71: 2 | G71: B | H71: 50
F72: -10 | G72: A | H72: 100
A75: curated:arrayscse:c015 | B75: Curated behaviour | C75: CURATED | D75: Hand-picked semantic boundary named by the oracle plan | E75: =IF({1,0,1,0,1},'SharedData'!$E$6:$E$10,'SharedData'!$B$6:$B$10) | F75: {=IF({1,0,1,0,1},SharedData!$E$6:$E$10,SharedData!$B$6:$B$10)} -> 10 | G75: K001 | H75: 10 | I75: K001 | J75: 10 | M75: oracle_probe | O75: Uses only deterministic workbook inputs; result must be cached by Excel.
A80: curated:arrayscse:c016 | B80: Curated behaviour | C80: CURATED | D80: Hand-picked semantic boundary named by the oracle plan | E80: =SUM({1,2,3}*{1;10;100}) | F80: {=SUM({1,2,3}*{1;10;100})} -> 666 | M80: oracle_probe | O80: Uses only deterministic workbook inputs; result must be cached by Excel.

Sheet ArraysDynamic
A1: ArraysDynamic — CellRune Excel Oracle
A2: Blue cells are formulas. Gray rows are catalogued exclusions. Excel must recalculate and save cached values. | R2: Catalog rows | S2: =COUNTA(A5:A1541) -> 65
R3: Primary cases | S3: =COUNTA(A5:A1541) -> 65
A4: Case ID | B4: Category | C4: Function | D4: Scenario | E4: Formula text | F4: Result / spill zone | M4: Expectation | N4: Sentinel | O4: Note | P4: Dependency signature | R4: Active formulas | S4: =COUNTA(A5:A1541)-COUNTIF(M5:M1541,"excluded") -> 65
A5: function:bycol | B5: Dynamic array / Lambda | C5: BYCOL | D5: Curated deterministic boundary with shared-data and cross-sheet inputs | E5: =BYCOL('SharedData'!$E$6:$F$10,LAMBDA(col,SUM(col))) | F5: {=_xlfn.BYCOL(SharedData!$E$6:$F$10,_xlfn.LAMBDA(_xlpm.col,SUM(_xlpm.col)))} -> 150 | G5: 15 | M5: oracle_probe | N5: =IF(ISERROR(F5),"ERROR "&IFERROR(ERROR.TYPE(F5),""),"OK") -> OK | O5: Recalculate in Excel and compare the saved result. | P5: =IFERROR(N(F5),0)+IFERROR(N(ArraysCSE!$F$5),0)+ROW()/100000 -> 850.00005
A29: function:byrow | B29: Dynamic array / Lambda | C29: BYROW | D29: Curated deterministic boundary with shared-data and cross-sheet inputs | E29: =BYROW('SharedData'!$E$6:$F$10,LAMBDA(row,SUM(row))) | F29: {=_xlfn.BYROW(SharedData!$E$6:$F$10,_xlfn.LAMBDA(_xlpm.row,SUM(_xlpm.row)))} -> 11 | M29: oracle_probe | O29: Recalculate in Excel and compare the saved result.
F30: 22
F31: 33
F32: 44
F33: 55
A53: function:choosecols | B53: Dynamic array / Lambda | C53: CHOOSECOLS | D53: Curated deterministic boundary with shared-data and cross-sheet inputs | E53: =CHOOSECOLS('SharedData'!$A$6:$F$10,1,3,5) | F53: {=_xlfn.CHOOSECOLS(SharedData!$A$6:$F$10,1,3,5)} -> 0.1 | G53: A | H53: 10 | M53: oracle_probe | O53: Recalculate in Excel and compare the saved result.
F54: 0.2 | G54: B | H54: 20
F55: -0.3 | G55: C | H55: 30
F56: 1 | G56: A | H56: 40
F57: 2 | G57: B | H57: 50
A77: function:chooserows | B77: Dynamic array / Lambda | C77: CHOOSEROWS | D77: Curated deterministic boundary with shared-data and cross-sheet inputs | E77: =CHOOSEROWS('SharedData'!$A$6:$F$10,1,3,5) | F77: {=_xlfn.CHOOSEROWS(SharedData!$A$6:$F$10,1,3,5)} -> 0.1 | G77: K001 | H77: A | I77: 43831 | J77: 10 | K77: 1 | M77: oracle_probe | O77: Recalculate in Excel and compare the saved result.
F78: -0.3 | G78: K003 | H78: C | I78: 43893 | J78: 30 | K78: 3
F79: 2 | G79: K005 | H79: B | I79: 43955 | J79: 50 | K79: 5
A101: function:drop | B101: Dynamic array / Lambda | C101: DROP | D101: Curated deterministic boundary with shared-data and cross-sheet inputs | E101: =DROP('SharedData'!$A$6:$F$15,2,1) | F101: {=_xlfn.DROP(SharedData!$A$6:$F$15,2,1)} -> K003 | G101: C | H101: 43893 | I101: 30 | J101: 3 | M101: oracle_probe | O101: Recalculate in Excel and compare the saved result.
F102: K004 | G102: A | H102: 43924 | I102: 40 | J102: 4
F103: K005 | G103: B | H103: 43955 | I103: 50 | J103: 5
F104: K006 | G104: C | H104: 43986 | I104: 60 | J104: 6
F105: K007 | G105: A | H105: 44017 | I105: 70 | J105: 7
F106: K008 | G106: B | H106: 44048 | I106: 80 | J106: 1
F107: K009 | G107: C | H107: 44079 | I107: 90 | J107: 2
F108: K010 | G108: A | H108: 44110 | I108: 100 | J108: 3
A125: function:expand | B125: Dynamic array / Lambda | C125: EXPAND | D125: Curated deterministic boundary with shared-data and cross-sheet inputs | E125: =EXPAND('SharedData'!$A$6:$B$8,5,4,"pad") | F125: {=_xlfn.EXPAND(SharedData!$A$6:$B$8,5,4,"pad")} -> 0.1 | G125: K001 | H125: pad | I125: pad | M125: oracle_probe | O125: Recalculate in Excel and compare the saved result.
F126: 0.2 | G126: K002 | H126: pad | I126: pad
F127: -0.3 | G127: K003 | H127: pad | I127: pad
F128: pad | G128: pad | H128: pad | I128: pad
F129: pad | G129: pad | H129: pad | I129: pad
A149: function:filter | B149: Dynamic array / Lambda | C149: FILTER | D149: Curated deterministic boundary with shared-data and cross-sheet inputs | E149: =FILTER('SharedData'!$A$6:$E$25,'SharedData'!$C$6:$C$25="A","none") | F149: {=_xlfn._xlws.FILTER(SharedData!$A$6:$E$25,SharedData!$C$6:$C$25="A","none")} -> 0.1 | G149: K001 | H149: A | I149: 43831 | J149: 10 | M149: oracle_probe | O149: Recalculate in Excel and compare the saved result.
F150: 1 | G150: K004 | H150: A | I150: 43924 | J150: 40
F151: 4 | G151: K007 | H151: A | I151: 44017 | J151: 70
F152: -10 | G152: K010 | H152: A | I152: 44110 | J152: 100
F153: 0 | G153: K013 | H153: A | I153: 44203 | J153: 130
F154: 3.5 | G154: K016 | H154: A | I154: 44296 | J154: 160
F155: 0.05 | G155: K019 | H155: A | I155: 44389 | J155: 190
A173: function:frequency | B173: Dynamic array / Lambda | C173: FREQUENCY | D173: Curated deterministic boundary with shared-data and cross-sheet inputs | E173: =FREQUENCY('SharedData'!$E$6:$E$25,{50,100,150}) | F173: {=FREQUENCY(SharedData!$E$6:$E$25,{50,100,150})} -> 5 | M173: oracle_probe | O173: Recalculate in Excel and compare the saved result.
F174: 5
F175: 5
F176: 5
A197: function:groupby | B197: Dynamic array / Lambda | C197: GROUPBY | D197: Curated deterministic boundary with shared-data and cross-sheet inputs | E197: =GROUPBY('SharedData'!$C$6:$C$25,'SharedData'!$E$6:$E$25,SUM) | F197: {=_xlfn.GROUPBY(SharedData!$C$6:$C$25,SharedData!$E$6:$E$25,_xleta.SUM)} -> A | G197: 700 | M197: oracle_probe | N197: =IF(ISERROR(F197),"ERROR "&IFERROR(ERROR.TYPE(F197),""),"OK") -> OK | O197: Recalculate in Excel and compare the saved result.
F198: B | G198: 770
F199: C | G199: 630
F200: 합계 | G200: 2100
A221: function:growth | B221: Dynamic array / Lambda | C221: GROWTH | D221: Curated deterministic boundary with shared-data and cross-sheet inputs | E221: =GROWTH('SharedData'!$J$6:$J$15,'SharedData'!$I$6:$I$15,{21,22,23}) | F221: {=GROWTH(SharedData!$J$6:$J$15,SharedData!$I$6:$I$15,{21,22,23})} -> 154.1357 | G221: 181.11019 | H221: 212.80534 | M221: oracle_probe | O221: Recalculate in Excel and compare the saved result.
A245: function:hstack | B245: Dynamic array / Lambda | C245: HSTACK | D245: Curated deterministic boundary with shared-data and cross-sheet inputs | E245: =HSTACK('SharedData'!$A$6:$A$10,'SharedData'!$E$6:$E$10) | F245: {=_xlfn.HSTACK(SharedData!$A$6:$A$10,SharedData!$E$6:$E$10)} -> 0.1 | G245: 10 | M245: oracle_probe | O245: Recalculate in Excel and compare the saved result.
F246: 0.2 | G246: 20
F247: -0.3 | G247: 30
F248: 1 | G248: 40
F249: 2 | G249: 50
A269: function:lambda | B269: Dynamic array / Lambda | C269: LAMBDA | D269: Curated deterministic boundary with shared-data and cross-sheet inputs | E269: =LAMBDA(x,x^2+1)(5) | F269: {=_xlfn.LAMBDA(_xlpm.x,_xlpm.x^2+1)(5)} -> 26 | M269: oracle_probe | O269: Recalculate in Excel and compare the saved result.
A293: function:let | B293: Dynamic array / Lambda | C293: LET | D293: Curated deterministic boundary with shared-data and cross-sheet inputs | E293: =LET(x,SUM('SharedData'!$E$6:$E$25),y,AVERAGE('SharedData'!$F$6:$F$25),x/y) | F293: {=_xlfn.LET(_xlpm.x,SUM(SharedData!$E$6:$E$25),_xlpm.y,AVERAGE(SharedData!$F$6:$F$25),_xlpm.x/_xlpm.y)} -> 545.45455 | M293: oracle_probe | O293: Recalculate in Excel and compare the saved result. | P293: =IFERROR(N(F293),0)+IFERROR(N(ArraysCSE!$F$5),0)+ROW()/100000 -> 1245.4575
A317: function:linest | B317: Dynamic array / Lambda | C317: LINEST | D317: Curated deterministic boundary with shared-data and cross-sheet inputs | E317: =LINEST('SharedData'!$J$6:$J$25,'SharedData'!$I$6:$I$25,TRUE,TRUE) | F317: {=LINEST(SharedData!$J$6:$J$25,SharedData!$I$6:$I$25,TRUE,TRUE)} -> 2 | G317: 3 | M317: oracle_probe | O317: Recalculate in Excel and compare the saved result.
F318: 0 | G318: 0
F319: 1 | G319: 0
F320: #NUM! | G320: 18
F321: 2660 | G321: 0
A341: function:logest | B341: Dynamic array / Lambda | C341: LOGEST | D341: Curated deterministic boundary with shared-data and cross-sheet inputs | E341: =LOGEST('SharedData'!$J$6:$J$15,'SharedData'!$I$6:$I$15,TRUE,TRUE) | F341: {=LOGEST(SharedData!$J$6:$J$15,SharedData!$I$6:$I$15,TRUE,TRUE)} -> 1.1750048 | G341: 5.2127957 | M341: oracle_probe | O341: Recalculate in Excel and compare the saved result.
F342: 0.012209382 | G342: 0.075757225
F343: 0.95615825 | G343: 0.11089722
F344: 174.47446 | G344: 8
F345: 2.1457207 | G345: 0.09838555
A365: function:makearray | B365: Dynamic array / Lambda | C365: MAKEARRAY | D365: Curated deterministic boundary with shared-data and cross-sheet inputs | E365: =MAKEARRAY(4,4,LAMBDA(i,j,i*100+j)) | F365: {=_xlfn.MAKEARRAY(4,4,_xlfn.LAMBDA(_xlpm.i,_xlpm.j,_xlpm.i*100+_xlpm.j))} -> 101 | G365: 102 | H365: 103 | I365: 104 | M365: oracle_probe | O365: Recalculate in Excel and compare the saved result.
F366: 201 | G366: 202 | H366: 203 | I366: 204
F367: 301 | G367: 302 | H367: 303 | I367: 304
F368: 401 | G368: 402 | H368: 403 | I368: 404
A389: function:map | B389: Dynamic array / Lambda | C389: MAP | D389: Curated deterministic boundary with shared-data and cross-sheet inputs | E389: =MAP('SharedData'!$E$6:$E$10,LAMBDA(x,x*1.1)) | F389: {=_xlfn.MAP(SharedData!$E$6:$E$10,_xlfn.LAMBDA(_xlpm.x,_xlpm.x*1.1))} -> 11 | M389: oracle_probe | N389: =IF(ISERROR(F389),"ERROR "&IFERROR(ERROR.TYPE(F389),""),"OK") -> OK | O389: Recalculate in Excel and compare the saved result.
F390: 22
F391: 33
F392: 44
F393: 55
A413: function:minverse | B413: Dynamic array / Lambda | C413: MINVERSE | D413: Curated deterministic boundary with shared-data and cross-sheet inputs | E413: =MINVERSE({4,7;2,6}) | F413: {=MINVERSE({4,7;2,6})} -> 0.6 | G413: -0.7 | M413: oracle_probe | O413: Recalculate in Excel and compare the saved result.
F414: -0.2 | G414: 0.4
A437: function:mmult | B437: Dynamic array / Lambda | C437: MMULT | D437: Curated deterministic boundary with shared-data and cross-sheet inputs | E437: =MMULT({1,2;3,4},{5,6;7,8}) | F437: {=MMULT({1,2;3,4},{5,6;7,8})} -> 19 | G437: 22 | M437: oracle_probe | O437: Recalculate in Excel and compare the saved result.
F438: 43 | G438: 50
A461: function:mode-mult | B461: Dynamic array / Lambda | C461: MODE.MULT | D461: Curated deterministic boundary with shared-data and cross-sheet inputs | E461: =MODE.MULT({1,1,2,2,3,4}) | F461: {=_xlfn.MODE.MULT({1,1,2,2,3,4})} -> 1 | M461: oracle_probe | O461: Recalculate in Excel and compare the saved result.
F462: 2
A485: function:munit | B485: Dynamic array / Lambda | C485: MUNIT | D485: Curated deterministic boundary with shared-data and cross-sheet inputs | E485: =MUNIT(4) | F485: {=_xlfn.MUNIT(4)} -> 1 | G485: 0 | H485: 0 | I485: 0 | M485: oracle_probe | O485: Recalculate in Excel and compare the saved result.
F486: 0 | G486: 1 | H486: 0 | I486: 0
F487: 0 | G487: 0 | H487: 1 | I487: 0
F488: 0 | G488: 0 | H488: 0 | I488: 1
A509: function:pivotby | B509: Dynamic array / Lambda | C509: PIVOTBY | D509: Curated deterministic boundary with shared-data and cross-sheet inputs | E509: =PIVOTBY('SharedData'!$C$6:$C$25,'SharedData'!$G$6:$G$25,'SharedData'!$E$6:$E$25,SUM) | F509: {=_xlfn.PIVOTBY(SharedData!$C$6:$C$25,SharedData!$G$6:$G$25,SharedData!$E$6:$E$25,_xleta.SUM)} | G509: FALSE | H509: TRUE | I509: 합계 | M509: oracle_probe | O509: Recalculate in Excel and compare the saved result.
F510: A | G510: 300 | H510: 400 | I510: 700
F511: B | G511: 440 | H511: 330 | I511: 770
F512: C | G512: 360 | H512: 270 | I512: 630
F513: 합계 | G513: 1100 | H513: 1000 | I513: 2100
A533: function:reduce | B533: Dynamic array / Lambda | C533: REDUCE | D533: Curated deterministic boundary with shared-data and cross-sheet inputs | E533: =REDUCE(0,'SharedData'!$E$6:$E$10,LAMBDA(a,v,a+v)) | F533: {=_xlfn.REDUCE(0,SharedData!$E$6:$E$10,_xlfn.LAMBDA(_xlpm.a,_xlpm.v,_xlpm.a+_xlpm.v))} -> 150 | M533: oracle_probe | O533: Recalculate in Excel and compare the saved result.
A557: function:scan | B557: Dynamic array / Lambda | C557: SCAN | D557: Curated deterministic boundary with shared-data and cross-sheet inputs | E557: =SCAN(0,'SharedData'!$E$6:$E$10,LAMBDA(a,v,a+v)) | F557: {=_xlfn.SCAN(0,SharedData!$E$6:$E$10,_xlfn.LAMBDA(_xlpm.a,_xlpm.v,_xlpm.a+_xlpm.v))} -> 10 | M557: oracle_probe | O557: Recalculate in Excel and compare the saved result.
F558: 30
F559: 60
F560: 100
F561: 150
A581: function:sequence | B581: Dynamic array / Lambda | C581: SEQUENCE | D581: Curated deterministic boundary with shared-data and cross-sheet inputs | E581: =SEQUENCE(5,4,10,5) | F581: {=_xlfn.SEQUENCE(5,4,10,5)} -> 10 | G581: 15 | H581: 20 | I581: 25 | M581: oracle_probe | N581: =IF(ISERROR(F581),"ERROR "&IFERROR(ERROR.TYPE(F581),""),"OK") -> OK | O581: Recalculate in Excel and compare the saved result. | P581: =IFERROR(N(F581),0)+IFERROR(N(ArraysCSE!$F$293),0)+ROW()/100000 -> 10.00581
F582: 30 | G582: 35 | H582: 40 | I582: 45
F583: 50 | G583: 55 | H583: 60 | I583: 65
F584: 70 | G584: 75 | H584: 80 | I584: 85
F585: 90 | G585: 95 | H585: 100 | I585: 105
A605: function:sort | B605: Dynamic array / Lambda | C605: SORT | D605: Curated deterministic boundary with shared-data and cross-sheet inputs | E605: =SORT('SharedData'!$A$6:$E$25,5,-1,FALSE) | F605: {=_xlfn._xlws.SORT(SharedData!$A$6:$E$25,5,-1,FALSE)} -> 0.1 | G605: K020 | H605: B | I605: 44420 | J605: 200 | M605: oracle_probe | O605: Recalculate in Excel and compare the saved result.
...

Sheet Intersection
A1: Intersection — CellRune Excel Oracle
A2: Blue cells are formulas. Gray rows are catalogued exclusions. Excel must recalculate and save cached values. | R2: Catalog rows | S2: =COUNTA(A5:A15) -> 11
R3: Primary cases | S3: =COUNTA(A5:A15) -> 11
A4: Case ID | B4: Category | C4: Function | D4: Scenario | E4: Formula text | F4: Result / spill zone | M4: Expectation | N4: Sentinel | O4: Note | P4: Dependency signature | R4: Active formulas | S4: =COUNTA(A5:A15)-COUNTIF(M5:M15,"excluded") -> 11
A5: curated:intersection:c001 | B5: Curated behaviour | C5: CURATED | D5: Hand-picked semantic boundary named by the oracle plan | E5: =@'SharedData'!A6:A25 | F5: =SharedData!A6:A25 -> #VALUE! | M5: oracle_probe | N5: =IF(ISERROR(F5),"ERROR "&IFERROR(ERROR.TYPE(F5),""),"OK") -> ERROR 3 | O5: Uses only deterministic workbook inputs; result must be cached by Excel. | P5: =IFERROR(N(F5),0)+IFERROR(N(ArraysDynamic!$F$5),0)+ROW()/100000 -> 150.00005
A6: curated:intersection:c002 | B6: Curated behaviour | C6: CURATED | D6: Hand-picked semantic boundary named by the oracle plan | E6: =@('SharedData'!A6:A25) | F6: =_xlfn.SINGLE((SharedData!A6:A25)) -> 0.1 | M6: oracle_probe | O6: Uses only deterministic workbook inputs; result must be cached by Excel.
A7: curated:intersection:c003 | B7: Curated behaviour | C7: CURATED | D7: Hand-picked semantic boundary named by the oracle plan | E7: =@('SharedData'!A:A) | F7: =_xlfn.SINGLE((SharedData!A:A)) -> 0.2 | M7: oracle_probe | O7: Uses only deterministic workbook inputs; result must be cached by Excel.
A8: curated:intersection:c004 | B8: Curated behaviour | C8: CURATED | D8: Hand-picked semantic boundary named by the oracle plan | E8: =@(@'SharedData'!A6:A8) | F8: =_xlfn.SINGLE((_xlfn.SINGLE(SharedData!A6:A8))) -> -0.3 | M8: oracle_probe | O8: Uses only deterministic workbook inputs; result must be cached by Excel.
A9: curated:intersection:c005 | B9: Curated behaviour | C9: CURATED | D9: Hand-picked semantic boundary named by the oracle plan | E9: =@'SharedData'!A6:C6 | F9: =SharedData!A6:C6 -> #VALUE! | M9: oracle_probe | O9: Uses only deterministic workbook inputs; result must be cached by Excel.
A10: curated:intersection:c006 | B10: Curated behaviour | C10: CURATED | D10: Hand-picked semantic boundary named by the oracle plan | E10: =SUM('SharedData'!A6:A20 'SharedData'!A12:C12) | F10: =SUM(SharedData!A6:A20 SharedData!A12:C12) -> 4 | M10: oracle_probe | O10: Uses only deterministic workbook inputs; result must be cached by Excel.
A11: curated:intersection:c007 | B11: Curated behaviour | C11: CURATED | D11: Hand-picked semantic boundary named by the oracle plan | E11: =SUM(('SharedData'!A6:A8,'SharedData'!E6:E8)) | F11: =SUM((SharedData!A6:A8,SharedData!E6:E8)) -> 60 | M11: oracle_probe | O11: Uses only deterministic workbook inputs; result must be cached by Excel.
A12: curated:intersection:c008 | B12: Curated behaviour | C12: CURATED | D12: Hand-picked semantic boundary named by the oracle plan | E12: =SUM('SharedData'!A6:INDEX('SharedData'!A:A,10)) | F12: =SUM(SharedData!A6:INDEX(SharedData!A:A,10)) -> 3 | M12: oracle_probe | O12: Uses only deterministic workbook inputs; result must be cached by Excel.
A13: curated:intersection:c009 | B13: Curated behaviour | C13: CURATED | D13: Hand-picked semantic boundary named by the oracle plan | E13: =SUM('SharedData'!6:8) | F13: =SUM(SharedData!6:8) -> 263144.15 | M13: oracle_probe | N13: =IF(ISERROR(F13),"ERROR "&IFERROR(ERROR.TYPE(F13),""),"OK") -> OK | O13: Uses only deterministic workbook inputs; result must be cached by Excel.
A14: curated:intersection:c010 | B14: Curated behaviour | C14: CURATED | D14: Hand-picked semantic boundary named by the oracle plan | E14: =SUM('SharedData'!A:A) | F14: =SUM(SharedData!A:A) -> 157.65 | M14: oracle_probe | O14: Uses only deterministic workbook inputs; result must be cached by Excel.
A15: curated:intersection:c011 | B15: Curated behaviour | C15: CURATED | D15: Hand-picked semantic boundary named by the oracle plan | E15: =COUNT('SharedData'!A:A 'SharedData'!6:8) | F15: =COUNT(SharedData!A:A SharedData!6:8) -> 3 | M15: oracle_probe | O15: Uses only deterministic workbook inputs; result must be cached by Excel.

Sheet Financial
A1: Financial — CellRune Excel Oracle
A2: Blue cells are formulas. Gray rows are catalogued exclusions. Excel must recalculate and save cached values. | R2: Catalog rows | S2: =COUNTA(A5:A65) -> 61
R3: Primary cases | S3: =COUNTA(A5:A65) -> 61
A4: Case ID | B4: Category | C4: Function | D4: Scenario | E4: Formula text | F4: Result / spill zone | M4: Expectation | N4: Sentinel | O4: Note | P4: Dependency signature | R4: Active formulas | S4: =COUNTA(A5:A65)-COUNTIF(M5:M65,"excluded") -> 61
A5: function:accrint | B5: Financial | C5: ACCRINT | D5: Curated deterministic boundary with shared-data and cross-sheet inputs | E5: =ACCRINT(DATE(2024,1,1),DATE(2024,7,1),DATE(2025,1,1),0.05,1000,2) | F5: =ACCRINT(DATE(2024,1,1),DATE(2024,7,1),DATE(2025,1,1),0.05,1000,2) -> 50 | M5: oracle_probe | N5: =IF(ISERROR(F5),"ERROR "&IFERROR(ERROR.TYPE(F5),""),"OK") -> OK | O5: Recalculate in Excel and compare the saved result. | P5: =IFERROR(N(F5),0)+IFERROR(N(Intersection!$F$5),0)+ROW()/100000 -> 50.00005
A6: function:accrintm | B6: Financial | C6: ACCRINTM | D6: Curated deterministic boundary with shared-data and cross-sheet inputs | E6: =ACCRINTM(DATE(2024,1,1),DATE(2025,1,1),0.05,1000,0) | F6: =ACCRINTM(DATE(2024,1,1),DATE(2025,1,1),0.05,1000,0) -> 50 | M6: oracle_probe | O6: Recalculate in Excel and compare the saved result.
A7: function:amordegrc | B7: Financial | C7: AMORDEGRC | D7: Curated deterministic boundary with shared-data and cross-sheet inputs | E7: =AMORDEGRC(10000,DATE(2023,1,1),DATE(2023,12,31),1000,1,0.15,0) | F7: =AMORDEGRC(10000,DATE(2023,1,1),DATE(2023,12,31),1000,1,0.15,0) -> 2344 | M7: oracle_probe | O7: Recalculate in Excel and compare the saved result.
A8: function:amorlinc | B8: Financial | C8: AMORLINC | D8: Curated deterministic boundary with shared-data and cross-sheet inputs | E8: =AMORLINC(10000,DATE(2023,1,1),DATE(2023,12,31),1000,1,0.15,0) | F8: =AMORLINC(10000,DATE(2023,1,1),DATE(2023,12,31),1000,1,0.15,0) -> 1500 | M8: oracle_probe | O8: Recalculate in Excel and compare the saved result.
A9: function:coupdaybs | B9: Financial | C9: COUPDAYBS | D9: Curated deterministic boundary with shared-data and cross-sheet inputs | E9: =COUPDAYBS(DATE(2025,3,15),DATE(2027,1,1),2,0) | F9: =COUPDAYBS(DATE(2025,3,15),DATE(2027,1,1),2,0) -> 74 | M9: oracle_probe | O9: Recalculate in Excel and compare the saved result.
A10: function:coupdays | B10: Financial | C10: COUPDAYS | D10: Curated deterministic boundary with shared-data and cross-sheet inputs | E10: =COUPDAYS(DATE(2025,3,15),DATE(2027,1,1),2,0) | F10: =COUPDAYS(DATE(2025,3,15),DATE(2027,1,1),2,0) -> 180 | M10: oracle_probe | O10: Recalculate in Excel and compare the saved result.
A11: function:coupdaysnc | B11: Financial | C11: COUPDAYSNC | D11: Curated deterministic boundary with shared-data and cross-sheet inputs | E11: =COUPDAYSNC(DATE(2025,3,15),DATE(2027,1,1),2,0) | F11: =COUPDAYSNC(DATE(2025,3,15),DATE(2027,1,1),2,0) -> 106 | M11: oracle_probe | O11: Recalculate in Excel and compare the saved result.
A12: function:coupncd | B12: Financial | C12: COUPNCD | D12: Curated deterministic boundary with shared-data and cross-sheet inputs | E12: =COUPNCD(DATE(2025,3,15),DATE(2027,1,1),2,0) | F12: =COUPNCD(DATE(2025,3,15),DATE(2027,1,1),2,0) -> 45839 | M12: oracle_probe | O12: Recalculate in Excel and compare the saved result.
A13: function:coupnum | B13: Financial | C13: COUPNUM | D13: Curated deterministic boundary with shared-data and cross-sheet inputs | E13: =COUPNUM(DATE(2025,3,15),DATE(2027,1,1),2,0) | F13: =COUPNUM(DATE(2025,3,15),DATE(2027,1,1),2,0) -> 4 | M13: oracle_probe | N13: =IF(ISERROR(F13),"ERROR "&IFERROR(ERROR.TYPE(F13),""),"OK") -> OK | O13: Recalculate in Excel and compare the saved result.
A14: function:couppcd | B14: Financial | C14: COUPPCD | D14: Curated deterministic boundary with shared-data and cross-sheet inputs | E14: =COUPPCD(DATE(2025,3,15),DATE(2027,1,1),2,0) | F14: =COUPPCD(DATE(2025,3,15),DATE(2027,1,1),2,0) -> 45658 | M14: oracle_probe | O14: Recalculate in Excel and compare the saved result.
A15: function:cumipmt | B15: Financial | C15: CUMIPMT | D15: Curated deterministic boundary with shared-data and cross-sheet inputs | E15: =CUMIPMT(0.05/12,60,20000,1,12,0) | F15: =CUMIPMT(0.05/12,60,20000,1,12,0) -> -917.99101 | M15: oracle_probe | O15: Recalculate in Excel and compare the saved result.
A16: function:cumprinc | B16: Financial | C16: CUMPRINC | D16: Curated deterministic boundary with shared-data and cross-sheet inputs | E16: =CUMPRINC(0.05/12,60,20000,1,12,0) | F16: =CUMPRINC(0.05/12,60,20000,1,12,0) -> -3611.1051 | M16: oracle_probe | O16: Recalculate in Excel and compare the saved result.
A17: function:db | B17: Financial | C17: DB | D17: Curated deterministic boundary with shared-data and cross-sheet inputs | E17: =DB(10000,1000,5,2,6) | F17: =DB(10000,1000,5,2,6) -> 3009.195 | M17: oracle_probe | O17: Recalculate in Excel and compare the saved result. | P17: =IFERROR(N(F17),0)+IFERROR(N(Intersection!$F$5),0)+ROW()/100000 -> 3009.1952
A18: function:ddb | B18: Financial | C18: DDB | D18: Curated deterministic boundary with shared-data and cross-sheet inputs | E18: =DDB(10000,1000,5,2,2) | F18: =DDB(10000,1000,5,2,2) -> 2400 | M18: oracle_probe | O18: Recalculate in Excel and compare the saved result.
A19: function:disc | B19: Financial | C19: DISC | D19: Curated deterministic boundary with shared-data and cross-sheet inputs | E19: =DISC(DATE(2025,1,1),DATE(2025,7,1),97,100,0) | F19: =DISC(DATE(2025,1,1),DATE(2025,7,1),97,100,0) -> 0.06 | M19: oracle_probe | O19: Recalculate in Excel and compare the saved result.
A20: function:dollarde | B20: Financial | C20: DOLLARDE | D20: Curated deterministic boundary with shared-data and cross-sheet inputs | E20: =DOLLARDE(1.08,16) | F20: =DOLLARDE(1.08,16) -> 1.5 | M20: oracle_probe | O20: Recalculate in Excel and compare the saved result.
A21: function:dollarfr | B21: Financial | C21: DOLLARFR | D21: Curated deterministic boundary with shared-data and cross-sheet inputs | E21: =DOLLARFR(1.5,16) | F21: =DOLLARFR(1.5,16) -> 1.08 | M21: oracle_probe | N21: =IF(ISERROR(F21),"ERROR "&IFERROR(ERROR.TYPE(F21),""),"OK") -> OK | O21: Recalculate in Excel and compare the saved result.
A22: function:duration | B22: Financial | C22: DURATION | D22: Curated deterministic boundary with shared-data and cross-sheet inputs | E22: =DURATION(DATE(2025,1,1),DATE(2030,1,1),0.05,0.04,2,0) | F22: =DURATION(DATE(2025,1,1),DATE(2030,1,1),0.05,0.04,2,0) -> 4.4989036 | M22: oracle_probe | O22: Recalculate in Excel and compare the saved result.
A23: function:effect | B23: Financial | C23: EFFECT | D23: Curated deterministic boundary with shared-data and cross-sheet inputs | E23: =EFFECT(0.06,12) | F23: =EFFECT(0.06,12) -> 0.061677812 | M23: oracle_probe | O23: Recalculate in Excel and compare the saved result.
A24: function:fv | B24: Financial | C24: FV | D24: Curated deterministic boundary with shared-data and cross-sheet inputs | E24: =FV(0.05/12,60,-250,-5000,0) | F24: =FV(0.05/12,60,-250,-5000,0) -> 23418.314 | M24: oracle_probe | O24: Recalculate in Excel and compare the saved result.
A25: function:fvschedule | B25: Financial | C25: FVSCHEDULE | D25: Curated deterministic boundary with shared-data and cross-sheet inputs | E25: =FVSCHEDULE(1000,{0.02,0.03,0.04,0.05}) | F25: =FVSCHEDULE(1000,{0.02,0.03,0.04,0.05}) -> 1147.2552 | M25: oracle_probe | O25: Recalculate in Excel and compare the saved result.
A26: function:intrate | B26: Financial | C26: INTRATE | D26: Curated deterministic boundary with shared-data and cross-sheet inputs | E26: =INTRATE(DATE(2025,1,1),DATE(2025,7,1),970,1000,0) | F26: =INTRATE(DATE(2025,1,1),DATE(2025,7,1),970,1000,0) -> 0.06185567 | M26: oracle_probe | O26: Recalculate in Excel and compare the saved result.
A27: function:ipmt | B27: Financial | C27: IPMT | D27: Curated deterministic boundary with shared-data and cross-sheet inputs | E27: =IPMT(0.05/12,12,60,20000,0,0) | F27: =IPMT(0.05/12,12,60,20000,0,0) -> -69.569791 | M27: oracle_probe | O27: Recalculate in Excel and compare the saved result.
A28: function:irr | B28: Financial | C28: IRR | D28: Curated deterministic boundary with shared-data and cross-sheet inputs | E28: =IRR('SharedData'!$L$6:$L$15,0.1) | F28: =IRR(SharedData!$L$6:$L$15,0.1) -> 0.21172444 | M28: oracle_probe | O28: Recalculate in Excel and compare the saved result.
A29: function:ispmt | B29: Financial | C29: ISPMT | D29: Curated deterministic boundary with shared-data and cross-sheet inputs | E29: =ISPMT(0.05/12,12,60,20000) | F29: =ISPMT(0.05/12,12,60,20000) -> -66.666667 | M29: oracle_probe | N29: =IF(ISERROR(F29),"ERROR "&IFERROR(ERROR.TYPE(F29),""),"OK") -> OK | O29: Recalculate in Excel and compare the saved result. | P29: =IFERROR(N(F29),0)+IFERROR(N(Intersection!$F$17),0)+ROW()/100000 -> -66.666377
A30: function:mduration | B30: Financial | C30: MDURATION | D30: Curated deterministic boundary with shared-data and cross-sheet inputs | E30: =MDURATION(DATE(2025,1,1),DATE(2030,1,1),0.05,0.04,2,0) | F30: =MDURATION(DATE(2025,1,1),DATE(2030,1,1),0.05,0.04,2,0) -> 4.4106898 | M30: oracle_probe | O30: Recalculate in Excel and compare the saved result.
A31: function:mirr | B31: Financial | C31: MIRR | D31: Curated deterministic boundary with shared-data and cross-sheet inputs | E31: =MIRR('SharedData'!$L$6:$L$15,0.08,0.1) | F31: =MIRR(SharedData!$L$6:$L$15,0.08,0.1) -> 0.15360335 | M31: oracle_probe | O31: Recalculate in Excel and compare the saved result.
A32: function:nominal | B32: Financial | C32: NOMINAL | D32: Curated deterministic boundary with shared-data and cross-sheet inputs | E32: =NOMINAL(0.0617,12) | F32: =NOMINAL(0.0617,12) -> 0.060021003 | M32: oracle_probe | O32: Recalculate in Excel and compare the saved result.
A33: function:nper | B33: Financial | C33: NPER | D33: Curated deterministic boundary with shared-data and cross-sheet inputs | E33: =NPER(0.05/12,-250,5000,0,0) | F33: =NPER(0.05/12,-250,5000,0,0) -> 20.926206 | M33: oracle_probe | O33: Recalculate in Excel and compare the saved result.
A34: function:npv | B34: Financial | C34: NPV | D34: Curated deterministic boundary with shared-data and cross-sheet inputs | E34: =NPV(0.1,'SharedData'!$L$7:$L$15)+'SharedData'!$L$6 | F34: =NPV(0.1,SharedData!$L$7:$L$15)+SharedData!$L$6 -> 553.63778 | M34: oracle_probe | O34: Recalculate in Excel and compare the saved result.
A35: function:oddfprice | B35: Financial | C35: ODDFPRICE | D35: Function-catalog probe with a repaired call signature | E35: =ODDFPRICE(DATE(2025,2,1),DATE(2030,3,1),DATE(2024,11,15),DATE(2025,3,1),0.05,0.06,100,2,0) | F35: =ODDFPRICE(DATE(2025,2,1),DATE(2030,3,1),DATE(2024,11,15),DATE(2025,3,1),0.05,0.06,100,2,0) -> 95.673855 | M35: oracle_probe | O35: Recalculate in Excel and compare the saved result.
A36: function:oddfyield | B36: Financial | C36: ODDFYIELD | D36: Function-catalog probe with a repaired call signature | E36: =ODDFYIELD(DATE(2025,2,1),DATE(2030,3,1),DATE(2024,11,15),DATE(2025,3,1),0.05,95,100,2,0) | F36: =ODDFYIELD(DATE(2025,2,1),DATE(2030,3,1),DATE(2024,11,15),DATE(2025,3,1),0.05,95,100,2,0) -> 0.061605746 | M36: oracle_probe | O36: Recalculate in Excel and compare the saved result.
A37: function:oddlprice | B37: Financial | C37: ODDLPRICE | D37: Function-catalog probe with a repaired call signature | E37: =ODDLPRICE(DATE(2025,2,1),DATE(2025,6,15),DATE(2024,10,15),0.05,0.06,100,2,0) | F37: =ODDLPRICE(DATE(2025,2,1),DATE(2025,6,15),DATE(2024,10,15),0.05,0.06,100,2,0) -> 99.603748 | M37: oracle_probe | N37: =IF(ISERROR(F37),"ERROR "&IFERROR(ERROR.TYPE(F37),""),"OK") -> OK | O37: Recalculate in Excel and compare the saved result.
A38: function:oddlyield | B38: Financial | C38: ODDLYIELD | D38: Function-catalog probe with a repaired call signature | E38: =ODDLYIELD(DATE(2025,2,1),DATE(2025,6,15),DATE(2024,10,15),0.05,99,100,2,0) | F38: =ODDLYIELD(DATE(2025,2,1),DATE(2025,6,15),DATE(2024,10,15),0.05,99,100,2,0) -> 0.076504401 | M38: oracle_probe | O38: Recalculate in Excel and compare the saved result.
A39: function:pduration | B39: Financial | C39: PDURATION | D39: Function-catalog probe with a repaired call signature | E39: =PDURATION(0.05,1000,2000) | F39: =_xlfn.PDURATION(0.05,1000,2000) -> 14.206699 | M39: oracle_probe | O39: Recalculate in Excel and compare the saved result.
A40: function:pmt | B40: Financial | C40: PMT | D40: Curated deterministic boundary with shared-data and cross-sheet inputs | E40: =PMT(0.05/12,60,20000,0,0) | F40: =PMT(0.05/12,60,20000,0,0) -> -377.42467 | M40: oracle_probe | O40: Recalculate in Excel and compare the saved result.
A41: function:ppmt | B41: Financial | C41: PPMT | D41: Curated deterministic boundary with shared-data and cross-sheet inputs | E41: =PPMT(0.05/12,12,60,20000,0,0) | F41: =PPMT(0.05/12,12,60,20000,0,0) -> -307.85488 | M41: oracle_probe | O41: Recalculate in Excel and compare the saved result. | P41: =IFERROR(N(F41),0)+IFERROR(N(Intersection!$F$29),0)+ROW()/100000 -> -307.85447
A42: function:price | B42: Financial | C42: PRICE | D42: Curated deterministic boundary with shared-data and cross-sheet inputs | E42: =PRICE(DATE(2025,1,1),DATE(2030,1,1),0.05,0.04,100,2,0) | F42: =PRICE(DATE(2025,1,1),DATE(2030,1,1),0.05,0.04,100,2,0) -> 104.49129 | M42: oracle_probe | O42: Recalculate in Excel and compare the saved result.
A43: function:pricedisc | B43: Financial | C43: PRICEDISC | D43: Curated deterministic boundary with shared-data and cross-sheet inputs | E43: =PRICEDISC(DATE(2025,1,1),DATE(2025,7,1),0.04,100,0) | F43: =PRICEDISC(DATE(2025,1,1),DATE(2025,7,1),0.04,100,0) -> 98 | M43: oracle_probe | O43: Recalculate in Excel and compare the saved result.
A44: function:pricemat | B44: Financial | C44: PRICEMAT | D44: Curated deterministic boundary with shared-data and cross-sheet inputs | E44: =PRICEMAT(DATE(2025,1,1),DATE(2025,7,1),DATE(2024,7,1),0.05,0.04,0) | F44: =PRICEMAT(DATE(2025,1,1),DATE(2025,7,1),DATE(2024,7,1),0.05,0.04,0) -> 100.44118 | M44: oracle_probe | O44: Recalculate in Excel and compare the saved result.
A45: function:pv | B45: Financial | C45: PV | D45: Curated deterministic boundary with shared-data and cross-sheet inputs | E45: =PV(0.05/12,60,-250,0,0) | F45: =PV(0.05/12,60,-250,0,0) -> 13247.677 | M45: oracle_probe | N45: =IF(ISERROR(F45),"ERROR "&IFERROR(ERROR.TYPE(F45),""),"OK") -> OK | O45: Recalculate in Excel and compare the saved result.
A46: function:rate | B46: Financial | C46: RATE | D46: Curated deterministic boundary with shared-data and cross-sheet inputs | E46: =RATE(60,-250,10000,0,0,0.01) | F46: =RATE(60,-250,10000,0,0,0.01) -> 0.014394781 | M46: oracle_probe | O46: Recalculate in Excel and compare the saved result.
A47: function:received | B47: Financial | C47: RECEIVED | D47: Curated deterministic boundary with shared-data and cross-sheet inputs | E47: =RECEIVED(DATE(2025,1,1),DATE(2025,7,1),970,0.05,0) | F47: =RECEIVED(DATE(2025,1,1),DATE(2025,7,1),970,0.05,0) -> 994.87179 | M47: oracle_probe | O47: Recalculate in Excel and compare the saved result.
A48: function:rri | B48: Financial | C48: RRI | D48: Function-catalog probe with a repaired call signature | E48: =RRI(10,1000,2000) | F48: =_xlfn.RRI(10,1000,2000) -> 0.071773463 | M48: oracle_probe | O48: Recalculate in Excel and compare the saved result.
A49: function:sln | B49: Financial | C49: SLN | D49: Function-catalog probe with a repaired call signature | E49: =SLN(10000,1000,5) | F49: =SLN(10000,1000,5) -> 1800 | M49: oracle_probe | O49: Recalculate in Excel and compare the saved result.
A50: function:syd | B50: Financial | C50: SYD | D50: Function-catalog probe with a repaired call signature | E50: =SYD(10000,1000,5,2) | F50: =SYD(10000,1000,5,2) -> 2400 | M50: oracle_probe | O50: Recalculate in Excel and compare the saved result.
A51: function:tbilleq | B51: Financial | C51: TBILLEQ | D51: Curated deterministic boundary with shared-data and cross-sheet inputs | E51: =TBILLEQ(DATE(2025,1,1),DATE(2025,7,1),0.04) | F51: =TBILLEQ(DATE(2025,1,1),DATE(2025,7,1),0.04) -> 0.041387912 | M51: oracle_probe | O51: Recalculate in Excel and compare the saved result.
A52: function:tbillprice | B52: Financial | C52: TBILLPRICE | D52: Curated deterministic boundary with shared-data and cross-sheet inputs | E52: =TBILLPRICE(DATE(2025,1,1),DATE(2025,7,1),0.04) | F52: =TBILLPRICE(DATE(2025,1,1),DATE(2025,7,1),0.04) -> 97.988889 | M52: oracle_probe | O52: Recalculate in Excel and compare the saved result.
A53: function:tbillyield | B53: Financial | C53: TBILLYIELD | D53: Curated deterministic boundary with shared-data and cross-sheet inputs | E53: =TBILLYIELD(DATE(2025,1,1),DATE(2025,7,1),98) | F53: =TBILLYIELD(DATE(2025,1,1),DATE(2025,7,1),98) -> 0.040590822 | M53: oracle_probe | N53: =IF(ISERROR(F53),"ERROR "&IFERROR(ERROR.TYPE(F53),""),"OK") -> OK | O53: Recalculate in Excel and compare the saved result. | P53: =IFERROR(N(F53),0)+IFERROR(N(Intersection!$F$41),0)+ROW()/100000 -> 0.041120822
A54: function:vdb | B54: Financial | C54: VDB | D54: Curated deterministic boundary with shared-data and cross-sheet inputs | E54: =VDB(10000,1000,5,1,2,2,FALSE) | F54: =VDB(10000,1000,5,1,2,2,FALSE) -> 2400 | M54: oracle_probe | O54: Recalculate in Excel and compare the saved result.
A55: function:xirr | B55: Financial | C55: XIRR | D55: Curated deterministic boundary with shared-data and cross-sheet inputs | E55: =XIRR('SharedData'!$L$6:$L$15,'SharedData'!$M$6:$M$15,0.1) | F55: =XIRR(SharedData!$L$6:$L$15,SharedData!$M$6:$M$15,0.1) -> 0.47295716 | M55: oracle_probe | O55: Recalculate in Excel and compare the saved result.
A56: function:xnpv | B56: Financial | C56: XNPV | D56: Curated deterministic boundary with shared-data and cross-sheet inputs | E56: =XNPV(0.1,'SharedData'!$L$6:$L$15,'SharedData'!$M$6:$M$15) | F56: =XNPV(0.1,SharedData!$L$6:$L$15,SharedData!$M$6:$M$15) -> 979.02426 | M56: oracle_probe | O56: Recalculate in Excel and compare the saved result.
A57: function:yield | B57: Financial | C57: YIELD | D57: Curated deterministic boundary with shared-data and cross-sheet inputs | E57: =YIELD(DATE(2025,1,1),DATE(2030,1,1),0.05,95,100,2,0) | F57: =YIELD(DATE(2025,1,1),DATE(2030,1,1),0.05,95,100,2,0) -> 0.061776246 | M57: oracle_probe | O57: Recalculate in Excel and compare the saved result.
A58: function:yielddisc | B58: Financial | C58: YIELDDISC | D58: Curated deterministic boundary with shared-data and cross-sheet inputs | E58: =YIELDDISC(DATE(2025,1,1),DATE(2025,7,1),97,100,0) | F58: =YIELDDISC(DATE(2025,1,1),DATE(2025,7,1),97,100,0) -> 0.06185567 | M58: oracle_probe | O58: Recalculate in Excel and compare the saved result.
A59: function:yieldmat | B59: Financial | C59: YIELDMAT | D59: Curated deterministic boundary with shared-data and cross-sheet inputs | E59: =YIELDMAT(DATE(2025,1,1),DATE(2025,7,1),DATE(2024,7,1),0.05,98,0) | F59: =YIELDMAT(DATE(2025,1,1),DATE(2025,7,1),DATE(2024,7,1),0.05,98,0) -> 0.089552239 | M59: oracle_probe | O59: Recalculate in Excel and compare the saved result.
A60: curated:financial:c006 | B60: Curated behaviour | C60: CURATED | D60: Hand-picked semantic boundary named by the oracle plan | E60: =PMT(0.05/12,60,PV(0.05/12,60,-250),0,0) | F60: =PMT(0.05/12,60,PV(0.05/12,60,-250),0,0) -> -250 | M60: oracle_probe | O60: Uses only deterministic workbook inputs; result must be cached by Excel.
A61: curated:financial:c007 | B61: Curated behaviour | C61: CURATED | D61: Hand-picked semantic boundary named by the oracle plan | E61: =FV(0.05/12,60,-250,-5000,0)+PV(0.05/12,60,-250,0,0) | F61: =FV(0.05/12,60,-250,-5000,0)+PV(0.05/12,60,-250,0,0) -> 36665.991 | M61: oracle_probe | N61: =IF(ISERROR(F61),"ERROR "&IFERROR(ERROR.TYPE(F61),""),"OK") -> OK | O61: Uses only deterministic workbook inputs; result must be cached by Excel.
A62: curated:financial:c009 | B62: Curated behaviour | C62: CURATED | D62: Hand-picked semantic boundary named by the oracle plan | E62: =IFERROR(IRR({-100,1,1,1,1,1},10),NA()) | F62: =IFERROR(IRR({-100,1,1,1,1,1},10),NA()) -> -0.5535003 | M62: oracle_probe | O62: Uses only deterministic workbook inputs; result must be cached by Excel.
A63: curated:financial:c010 | B63: Curated behaviour | C63: CURATED | D63: Hand-picked semantic boundary named by the oracle plan | E63: =IFERROR(IRR({100,200,300},0.1),NA()) | F63: =IFERROR(IRR({100,200,300},0.1),NA()) -> #N/A | M63: oracle_probe | O63: Uses only deterministic workbook inputs; result must be cached by Excel.
A64: curated:financial:c011 | B64: Curated behaviour | C64: CURATED | D64: Hand-picked semantic boundary named by the oracle plan | E64: =IFERROR(RATE(2,-100,1000,0,0,0.9),NA()) | F64: =IFERROR(RATE(2,-100,1000,0,0,0.9),NA()) -> -0.62984379 | M64: oracle_probe | O64: Uses only deterministic workbook inputs; result must be cached by Excel.
A65: curated:financial:c012 | B65: Curated behaviour | C65: CURATED | D65: Hand-picked semantic boundary named by the oracle plan | E65: =PRICE(DATE(2025,1,1),DATE(2030,1,1),0.05,YIELD(DATE(2025,1,1),DATE(2030,1,1),0.05,95,100,2,0),100,2,0) | F65: =PRICE(DATE(2025,1,1),DATE(2030,1,1),0.05,YIELD(DATE(2025,1,1),DATE(2030,1,1),0.05,95,100,2,0),100,2,0) -> 95 | M65: oracle_probe | O65: Uses only deterministic workbook inputs; result must be cached by Excel. | P65: =IFERROR(N(F65),0)+IFERROR(N(Intersection!$F$53),0)+ROW()/100000 -> 95.00065

Sheet Lookup
A1: Lookup — CellRune Excel Oracle
A2: Blue cells are formulas. Gray rows are catalogued exclusions. Excel must recalculate and save cached values. | R2: Catalog rows | S2: =COUNTA(A5:A38) -> 34
R3: Primary cases | S3: =COUNTA(A5:A38) -> 34
A4: Case ID | B4: Category | C4: Function | D4: Scenario | E4: Formula text | F4: Result / spill zone | M4: Expectation | N4: Sentinel | O4: Note | P4: Dependency signature | R4: Active formulas | S4: =COUNTA(A5:A38)-COUNTIF(M5:M38,"excluded") -> 34
A5: function:address | B5: Lookup and reference | C5: ADDRESS | D5: Curated deterministic boundary with shared-data and cross-sheet inputs | E5: =ADDRESS(12,5,1,TRUE,"SharedData") | F5: =ADDRESS(12,5,1,TRUE,"SharedData") -> SharedData!$E$12 | M5: oracle_probe | N5: =IF(ISERROR(F5),"ERROR "&IFERROR(ERROR.TYPE(F5),""),"OK") -> OK | O5: Recalculate in Excel and compare the saved result. | P5: =IFERROR(N(F5),0)+IFERROR(N(Financial!$F$5),0)+ROW()/100000 -> 50.00005
A6: function:areas | B6: Lookup and reference | C6: AREAS | D6: Curated deterministic boundary with shared-data and cross-sheet inputs | E6: =AREAS(('SharedData'!$A$6:$A$8,'SharedData'!$E$6:$E$8)) | F6: =AREAS((SharedData!$A$6:$A$8,SharedData!$E$6:$E$8)) -> 2 | M6: oracle_probe | O6: Recalculate in Excel and compare the saved result.
A7: function:choose | B7: Lookup and reference | C7: CHOOSE | D7: Curated deterministic boundary with shared-data and cross-sheet inputs | E7: =CHOOSE(3,'SharedData'!$B$6,'SharedData'!$B$7,'SharedData'!$B$8) | F7: =CHOOSE(3,SharedData!$B$6,SharedData!$B$7,SharedData!$B$8) -> K003 | M7: oracle_probe | O7: Recalculate in Excel and compare the saved result.
A8: function:column | B8: Lookup and reference | C8: COLUMN | D8: Curated deterministic boundary with shared-data and cross-sheet inputs | E8: =COLUMN('SharedData'!$E$6) | F8: =COLUMN(SharedData!$E$6) -> 5 | M8: oracle_probe | O8: Recalculate in Excel and compare the saved result.
A9: function:columns | B9: Lookup and reference | C9: COLUMNS | D9: Curated deterministic boundary with shared-data and cross-sheet inputs | E9: =COLUMNS('SharedData'!$A$6:$F$25) | F9: =COLUMNS(SharedData!$A$6:$F$25) -> 6 | M9: oracle_probe | O9: Recalculate in Excel and compare the saved result.
A10: function:hlookup | B10: Lookup and reference | C10: HLOOKUP | D10: Curated deterministic boundary with shared-data and cross-sheet inputs | E10: =HLOOKUP("Amount",'SharedData'!$A$30:$F$50,10,FALSE) | F10: =HLOOKUP("Amount",SharedData!$A$30:$F$50,10,FALSE) -> 90 | M10: oracle_probe | O10: Recalculate in Excel and compare the saved result.
A11: function:hyperlink | B11: Lookup and reference | C11: HYPERLINK | D11: Curated deterministic boundary with shared-data and cross-sheet inputs | E11: =HYPERLINK("https://github.com/emulette/cellrune","CellRune") | F11: =HYPERLINK("https://github.com/emulette/cellrune","CellRune") -> CellRune | M11: oracle_probe | O11: Recalculate in Excel and compare the saved result.
A12: function:index | B12: Lookup and reference | C12: INDEX | D12: Curated deterministic boundary with shared-data and cross-sheet inputs | E12: =INDEX('SharedData'!$E$6:$E$25,MATCH("K010",'SharedData'!$B$6:$B$25,0)) | F12: =INDEX(SharedData!$E$6:$E$25,MATCH("K010",SharedData!$B$6:$B$25,0)) -> 100 | M12: oracle_probe | O12: Recalculate in Excel and compare the saved result.
A13: function:indirect | B13: Lookup and reference | C13: INDIRECT | D13: Curated deterministic boundary with shared-data and cross-sheet inputs | E13: =INDIRECT("'SharedData'!E"&MATCH("K010",'SharedData'!$B$1:$B$25,0)) | F13: =INDIRECT("'SharedData'!E"&MATCH("K010",SharedData!$B$1:$B$25,0)) -> 100 | M13: oracle_probe | N13: =IF(ISERROR(F13),"ERROR "&IFERROR(ERROR.TYPE(F13),""),"OK") -> OK | O13: Recalculate in Excel and compare the saved result.
A14: function:isformula | B14: Lookup and reference | C14: ISFORMULA | D14: Curated deterministic boundary with shared-data and cross-sheet inputs | E14: =ISFORMULA('SharedData'!$J$6) | F14: =_xlfn.ISFORMULA(SharedData!$J$6) -> TRUE | M14: oracle_probe | O14: Recalculate in Excel and compare the saved result.
A15: function:isref | B15: Lookup and reference | C15: ISREF | D15: Curated deterministic boundary with shared-data and cross-sheet inputs | E15: =ISREF('SharedData'!$A$6:$A$10) | F15: =ISREF(SharedData!$A$6:$A$10) -> TRUE | M15: oracle_probe | O15: Recalculate in Excel and compare the saved result.
A16: function:lookup | B16: Lookup and reference | C16: LOOKUP | D16: Curated deterministic boundary with shared-data and cross-sheet inputs | E16: =LOOKUP(75,'SharedData'!$E$6:$E$25,'SharedData'!$B$6:$B$25) | F16: =LOOKUP(75,SharedData!$E$6:$E$25,SharedData!$B$6:$B$25) -> K007 | M16: oracle_probe | O16: Recalculate in Excel and compare the saved result.
A17: function:match | B17: Lookup and reference | C17: MATCH | D17: Curated deterministic boundary with shared-data and cross-sheet inputs | E17: =MATCH("K010",'SharedData'!$B$6:$B$25,0) | F17: =MATCH("K010",SharedData!$B$6:$B$25,0) -> 10 | M17: oracle_probe | O17: Recalculate in Excel and compare the saved result. | P17: =IFERROR(N(F17),0)+IFERROR(N(Financial!$F$5),0)+ROW()/100000 -> 60.00017
A18: function:offset | B18: Lookup and reference | C18: OFFSET | D18: Curated deterministic boundary with shared-data and cross-sheet inputs | E18: =SUM(OFFSET('SharedData'!$E$6,2,0,5,1)) | F18: =SUM(OFFSET(SharedData!$E$6,2,0,5,1)) -> 250 | M18: oracle_probe | O18: Recalculate in Excel and compare the saved result.
A19: function:row | B19: Lookup and reference | C19: ROW | D19: Curated deterministic boundary with shared-data and cross-sheet inputs | E19: =ROW('SharedData'!$E$12) | F19: =ROW(SharedData!$E$12) -> 12 | M19: oracle_probe | O19: Recalculate in Excel and compare the saved result.
A20: function:rows | B20: Lookup and reference | C20: ROWS | D20: Curated deterministic boundary with shared-data and cross-sheet inputs | E20: =ROWS('SharedData'!$E$6:$E$25) | F20: =ROWS(SharedData!$E$6:$E$25) -> 20 | M20: oracle_probe | O20: Recalculate in Excel and compare the saved result.
A21: function:sheet | B21: Lookup and reference | C21: SHEET | D21: Curated deterministic boundary with shared-data and cross-sheet inputs | E21: =SHEET('Financial'!$A$1) | F21: =_xlfn.SHEET(Financial!$A$1) -> 8 | M21: oracle_probe | N21: =IF(ISERROR(F21),"ERROR "&IFERROR(ERROR.TYPE(F21),""),"OK") -> OK | O21: Recalculate in Excel and compare the saved result.
A22: function:sheets | B22: Lookup and reference | C22: SHEETS | D22: Curated deterministic boundary with shared-data and cross-sheet inputs | E22: =SHEETS('Arithmetic:Unsupported'!$A$1) | F22: =_xlfn.SHEETS(Arithmetic:Unsupported!$A$1) -> 10 | M22: oracle_probe | O22: Recalculate in Excel and compare the saved result.
A23: function:vlookup | B23: Lookup and reference | C23: VLOOKUP | D23: Curated deterministic boundary with shared-data and cross-sheet inputs | E23: =VLOOKUP("K010",'SharedData'!$B$6:$E$25,4,FALSE) | F23: =VLOOKUP("K010",SharedData!$B$6:$E$25,4,FALSE) -> 100 | M23: oracle_probe | O23: Recalculate in Excel and compare the saved result.
A24: function:xlookup | B24: Lookup and reference | C24: XLOOKUP | D24: Curated deterministic boundary with shared-data and cross-sheet inputs | E24: =XLOOKUP("K010",'SharedData'!$B$6:$B$25,'SharedData'!$E$6:$E$25,"missing",0,1) | F24: =_xlfn.XLOOKUP("K010",SharedData!$B$6:$B$25,SharedData!$E$6:$E$25,"missing",0,1) -> 100 | M24: oracle_probe | O24: Recalculate in Excel and compare the saved result.
A25: function:xmatch | B25: Lookup and reference | C25: XMATCH | D25: Curated deterministic boundary with shared-data and cross-sheet inputs | E25: =XMATCH("K010",'SharedData'!$B$6:$B$25,0,1) | F25: =_xlfn.XMATCH("K010",SharedData!$B$6:$B$25,0,1) -> 10 | M25: oracle_probe | O25: Recalculate in Excel and compare the saved result.
A26: curated:lookup:c001 | B26: Curated behaviour | C26: CURATED | D26: Hand-picked semantic boundary named by the oracle plan | E26: =XLOOKUP("K010",'SharedData'!$B$6:$B$25,'SharedData'!$E$6:$F$25,"missing",0,1) | F26: =_xlfn.XLOOKUP("K010",SharedData!$B$6:$B$25,SharedData!$E$6:$F$25,"missing",0,1) -> 3 | M26: oracle_probe | O26: Uses only deterministic workbook inputs; result must be cached by Excel.
A27: curated:lookup:c002 | B27: Curated behaviour | C27: CURATED | D27: Hand-picked semantic boundary named by the oracle plan | E27: =INDEX('SharedData'!$E$6:$E$25,XMATCH(MAX('SharedData'!$E$6:$E$25),'SharedData'!$E$6:$E$25,0)) | F27: =INDEX(SharedData!$E$6:$E$25,_xlfn.XMATCH(MAX(SharedData!$E$6:$E$25),SharedData!$E$6:$E$25,0)) -> 200 | M27: oracle_probe | O27: Uses only deterministic workbook inputs; result must be cached by Excel.
A28: curated:lookup:c003 | B28: Curated behaviour | C28: CURATED | D28: Hand-picked semantic boundary named by the oracle plan | E28: =VLOOKUP("K010",'SharedData'!$B$6:$F$25,4,FALSE) | F28: =VLOOKUP("K010",SharedData!$B$6:$F$25,4,FALSE) -> 100 | M28: oracle_probe | O28: Uses only deterministic workbook inputs; result must be cached by Excel.
A29: curated:lookup:c004 | B29: Curated behaviour | C29: CURATED | D29: Hand-picked semantic boundary named by the oracle plan | E29: =VLOOKUP(75,'SharedData'!$E$6:$F$25,2,TRUE) | F29: =VLOOKUP(75,SharedData!$E$6:$F$25,2,TRUE) -> 7 | M29: oracle_probe | N29: =IF(ISERROR(F29),"ERROR "&IFERROR(ERROR.TYPE(F29),""),"OK") -> OK | O29: Uses only deterministic workbook inputs; result must be cached by Excel. | P29: =IFERROR(N(F29),0)+IFERROR(N(Financial!$F$17),0)+ROW()/100000 -> 3016.1953
A30: curated:lookup:c005 | B30: Curated behaviour | C30: CURATED | D30: Hand-picked semantic boundary named by the oracle plan | E30: =MATCH(75,'SharedData'!$E$6:$E$25,1) | F30: =MATCH(75,SharedData!$E$6:$E$25,1) -> 7 | M30: oracle_probe | O30: Uses only deterministic workbook inputs; result must be cached by Excel.
A31: curated:lookup:c006 | B31: Curated behaviour | C31: CURATED | D31: Hand-picked semantic boundary named by the oracle plan | E31: =MATCH(75,'SharedData'!$E$6:$E$25,-1) | F31: =MATCH(75,SharedData!$E$6:$E$25,-1) -> #N/A | M31: oracle_probe | O31: Uses only deterministic workbook inputs; result must be cached by Excel.
A32: curated:lookup:c008 | B32: Curated behaviour | C32: CURATED | D32: Hand-picked semantic boundary named by the oracle plan | E32: =HLOOKUP("Amount",'SharedData'!$A$5:$F$25,5,FALSE) | F32: =HLOOKUP("Amount",SharedData!$A$5:$F$25,5,FALSE) -> 40 | M32: oracle_probe | O32: Uses only deterministic workbook inputs; result must be cached by Excel.
A33: curated:lookup:c009 | B33: Curated behaviour | C33: CURATED | D33: Hand-picked semantic boundary named by the oracle plan | E33: =INDEX('SharedData'!$A$6:$F$25,MATCH("K010",'SharedData'!$B$6:$B$25,0),MATCH("Amount",'SharedData'!$A$5:$F$5,0)) | F33: =INDEX(SharedData!$A$6:$F$25,MATCH("K010",SharedData!$B$6:$B$25,0),MATCH("Amount",SharedData!$A$5:$F$5,0)) -> 100 | M33: oracle_probe | O33: Uses only deterministic workbook inputs; result must be cached by Excel.
A34: curated:lookup:c010 | B34: Curated behaviour | C34: CURATED | D34: Hand-picked semantic boundary named by the oracle plan | E34: =SUM(OFFSET('SharedData'!$E$6,MATCH("K010",'SharedData'!$B$6:$B$25,0)-1,0,3,1)) | F34: =SUM(OFFSET(SharedData!$E$6,MATCH("K010",SharedData!$B$6:$B$25,0)-1,0,3,1)) -> 330 | M34: oracle_probe | O34: Uses only deterministic workbook inputs; result must be cached by Excel.
A35: curated:lookup:c011 | B35: Curated behaviour | C35: CURATED | D35: Hand-picked semantic boundary named by the oracle plan | E35: =INDIRECT(ADDRESS(MATCH("K010",'SharedData'!$B$1:$B$25,0),5,1,TRUE,"SharedData")) | F35: =INDIRECT(ADDRESS(MATCH("K010",SharedData!$B$1:$B$25,0),5,1,TRUE,"SharedData")) -> 100 | M35: oracle_probe | O35: Uses only deterministic workbook inputs; result must be cached by Excel.
A36: curated:lookup:c012 | B36: Curated behaviour | C36: CURATED | D36: Hand-picked semantic boundary named by the oracle plan | E36: =XLOOKUP(74,'SharedData'!$E$6:$E$25,'SharedData'!$B$6:$B$25,"none",-1,2) | F36: =_xlfn.XLOOKUP(74,SharedData!$E$6:$E$25,SharedData!$B$6:$B$25,"none",-1,2) -> K007 | M36: oracle_probe | O36: Uses only deterministic workbook inputs; result must be cached by Excel.
A37: curated:lookup:c013 | B37: Curated behaviour | C37: CURATED | D37: Hand-picked semantic boundary named by the oracle plan | E37: =SUM(DataTable[Amount]) | F37: =SUM(DataTable[Amount]) -> 2100 | M37: oracle_probe | N37: =IF(ISERROR(F37),"ERROR "&IFERROR(ERROR.TYPE(F37),""),"OK") -> OK | O37: Uses only deterministic workbook inputs; result must be cached by Excel.
A38: curated:lookup:c014 | B38: Curated behaviour | C38: CURATED | D38: Hand-picked semantic boundary named by the oracle plan | E38: =XLOOKUP("K010",DataTable[Key],DataTable[Amount],"missing") | F38: =_xlfn.XLOOKUP("K010",DataTable[Key],DataTable[Amount],"missing") -> 100 | M38: oracle_probe | O38: Uses only deterministic workbook inputs; result must be cached by Excel.

Sheet TextDate
A1: TextDate — CellRune Excel Oracle
A2: Blue cells are formulas. Gray rows are catalogued exclusions. Excel must recalculate and save cached values. | R2: Catalog rows | S2: =COUNTA(A5:A90) -> 86
R3: Primary cases | S3: =COUNTA(A5:A90) -> 86
A4: Case ID | B4: Category | C4: Function | D4: Scenario | E4: Formula text | F4: Result / spill zone | M4: Expectation | N4: Sentinel | O4: Note | P4: Dependency signature | R4: Active formulas | S4: =COUNTA(A5:A90)-COUNTIF(M5:M90,"excluded") -> 86
A5: function:arraytotext | B5: Text | C5: ARRAYTOTEXT | D5: Curated deterministic boundary with shared-data and cross-sheet inputs | E5: =ARRAYTOTEXT('SharedData'!$A$6:$C$8,1) | F5: =_xlfn.ARRAYTOTEXT(SharedData!$A$6:$C$8,1) -> {0.1,"K001","A";0.2,"K002","B";-0.3,"K003","C"} | M5: oracle_probe | N5: =IF(ISERROR(F5),"ERROR "&IFERROR(ERROR.TYPE(F5),""),"OK") -> OK | O5: Recalculate in Excel and compare the saved result. | P5: =IFERROR(N(F5),0)+IFERROR(N(Lookup!$F$5),0)+ROW()/100000 -> 5e-05
A6: function:asc | B6: Text | C6: ASC | D6: Curated deterministic boundary with shared-data and cross-sheet inputs | E6: =ASC("ＡＢＣ１２３") | F6: =ASC("ＡＢＣ１２３") -> ABC123 | M6: oracle_probe | O6: Recalculate in Excel and compare the saved result.
A7: function:bahttext | B7: Text | C7: BAHTTEXT | D7: Curated deterministic boundary with shared-data and cross-sheet inputs | E7: =BAHTTEXT(1234.5) | F7: =BAHTTEXT(1234.5) -> หนึ่งพันสองร้อยสามสิบสี่บาทห้าสิบสตางค์ | M7: oracle_probe | O7: Recalculate in Excel and compare the saved result.
A8: function:char | B8: Text | C8: CHAR | D8: Curated deterministic boundary with shared-data and cross-sheet inputs | E8: =CHAR(65) | F8: =CHAR(65) -> A | M8: oracle_probe | O8: Recalculate in Excel and compare the saved result.
A9: function:clean | B9: Text | C9: CLEAN | D9: Curated deterministic boundary with shared-data and cross-sheet inputs | E9: =CLEAN("Cell"&CHAR(9)&"Rune") | F9: =CLEAN("Cell"&CHAR(9)&"Rune") -> CellRune | M9: oracle_probe | O9: Recalculate in Excel and compare the saved result.
A10: function:code | B10: Text | C10: CODE | D10: Curated deterministic boundary with shared-data and cross-sheet inputs | E10: =CODE("A") | F10: =CODE("A") -> 65 | M10: oracle_probe | O10: Recalculate in Excel and compare the saved result.
A11: function:concat | B11: Text | C11: CONCAT | D11: Curated deterministic boundary with shared-data and cross-sheet inputs | E11: =CONCAT('SharedData'!$B$6:$B$10) | F11: =_xlfn.CONCAT(SharedData!$B$6:$B$10) -> K001K002K003K004K005 | M11: oracle_probe | O11: Recalculate in Excel and compare the saved result.
A12: function:concatenate | B12: Text | C12: CONCATENATE | D12: Curated deterministic boundary with shared-data and cross-sheet inputs | E12: =CONCATENATE('SharedData'!$B$6,"-",'SharedData'!$B$7) | F12: =CONCATENATE(SharedData!$B$6,"-",SharedData!$B$7) -> K001-K002 | M12: oracle_probe | O12: Recalculate in Excel and compare the saved result.
A13: function:date | B13: Date and time | C13: DATE | D13: Curated deterministic boundary with shared-data and cross-sheet inputs | E13: =DATE(2024,2,29) | F13: =DATE(2024,2,29) -> 45351 | M13: oracle_probe | N13: =IF(ISERROR(F13),"ERROR "&IFERROR(ERROR.TYPE(F13),""),"OK") -> OK | O13: Recalculate in Excel and compare the saved result.
A14: function:datedif | B14: Date and time | C14: DATEDIF | D14: Curated deterministic boundary with shared-data and cross-sheet inputs | E14: =DATEDIF(DATE(2020,1,15),DATE(2026,7,27),"ym") | F14: =DATEDIF(DATE(2020,1,15),DATE(2026,7,27),"ym") -> 6 | M14: oracle_probe | O14: Recalculate in Excel and compare the saved result.
A15: function:datevalue | B15: Date and time | C15: DATEVALUE | D15: Curated deterministic boundary with shared-data and cross-sheet inputs | E15: =DATEVALUE("2024-02-29") | F15: =DATEVALUE("2024-02-29") -> 45351 | M15: oracle_probe | O15: Recalculate in Excel and compare the saved result.
A16: function:day | B16: Date and time | C16: DAY | D16: Curated deterministic boundary with shared-data and cross-sheet inputs | E16: =DAY('SharedData'!$D$6) | F16: =DAY(SharedData!$D$6) -> 1 | M16: oracle_probe | O16: Recalculate in Excel and compare the saved result.
A17: function:days | B17: Date and time | C17: DAYS | D17: Curated deterministic boundary with shared-data and cross-sheet inputs | E17: =DAYS('SharedData'!$D$25,'SharedData'!$D$6) | F17: =_xlfn.DAYS(SharedData!$D$25,SharedData!$D$6) -> 589 | M17: oracle_probe | O17: Recalculate in Excel and compare the saved result. | P17: =IFERROR(N(F17),0)+IFERROR(N(Lookup!$F$5),0)+ROW()/100000 -> 589.00017
A18: function:days360 | B18: Date and time | C18: DAYS360 | D18: Curated deterministic boundary with shared-data and cross-sheet inputs | E18: =DAYS360('SharedData'!$D$6,'SharedData'!$D$25,FALSE) | F18: =DAYS360(SharedData!$D$6,SharedData!$D$25,FALSE) -> 581 | M18: oracle_probe | O18: Recalculate in Excel and compare the saved result.
A19: function:dbcs | B19: Text | C19: DBCS | D19: Function-catalog probe; genuine error results are retained as oracle evidence | E19: =DBCS("CellRune Oracle 2026") | F19: =DBCS("CellRune Oracle 2026") -> ＣｅｌｌＲｕｎｅ Ｏｒａｃｌｅ ２０２６ | M19: oracle_probe | O19: Recalculate in Excel and compare the saved result.
A20: function:dollar | B20: Text | C20: DOLLAR | D20: Curated deterministic boundary with shared-data and cross-sheet inputs | E20: =DOLLAR(1234.567,2) | F20: =DOLLAR(1234.567,2) -> ₩1,234.57 | M20: oracle_probe | O20: Recalculate in Excel and compare the saved result.
A21: function:edate | B21: Date and time | C21: EDATE | D21: Curated deterministic boundary with shared-data and cross-sheet inputs | E21: =EDATE('SharedData'!$D$6,18) | F21: =EDATE(SharedData!$D$6,18) -> 44378 | M21: oracle_probe | N21: =IF(ISERROR(F21),"ERROR "&IFERROR(ERROR.TYPE(F21),""),"OK") -> OK | O21: Recalculate in Excel and compare the saved result.
A22: function:eomonth | B22: Date and time | C22: EOMONTH | D22: Curated deterministic boundary with shared-data and cross-sheet inputs | E22: =EOMONTH('SharedData'!$D$6,3) | F22: =EOMONTH(SharedData!$D$6,3) -> 43951 | M22: oracle_probe | O22: Recalculate in Excel and compare the saved result.
A23: function:exact | B23: Text | C23: EXACT | D23: Curated deterministic boundary with shared-data and cross-sheet inputs | E23: =EXACT("CellRune","cellrune") | F23: =EXACT("CellRune","cellrune") -> FALSE | M23: oracle_probe | O23: Recalculate in Excel and compare the saved result.
A24: function:find | B24: Text | C24: FIND | D24: Curated deterministic boundary with shared-data and cross-sheet inputs | E24: =FIND("Rune","CellRune Oracle") | F24: =FIND("Rune","CellRune Oracle") -> 5 | M24: oracle_probe | O24: Recalculate in Excel and compare the saved result.
A25: function:findb | B25: Text | C25: FINDB | D25: Curated deterministic boundary with shared-data and cross-sheet inputs | E25: =FINDB("Rune","CellRune Oracle") | F25: =FINDB("Rune","CellRune Oracle") -> 5 | M25: oracle_probe | O25: Recalculate in Excel and compare the saved result.
A26: function:fixed | B26: Text | C26: FIXED | D26: Curated deterministic boundary with shared-data and cross-sheet inputs | E26: =FIXED(12345.6789,2,TRUE) | F26: =FIXED(12345.6789,2,TRUE) -> 12345.68 | M26: oracle_probe | O26: Recalculate in Excel and compare the saved result.
A27: function:formulatext | B27: Text | C27: FORMULATEXT | D27: Curated deterministic boundary with shared-data and cross-sheet inputs | E27: =FORMULATEXT('SharedData'!$J$6) | F27: =_xlfn.FORMULATEXT(SharedData!$J$6) -> =I6*2+3 | M27: oracle_probe | O27: Recalculate in Excel and compare the saved result.
A28: function:hour | B28: Date and time | C28: HOUR | D28: Curated deterministic boundary with shared-data and cross-sheet inputs | E28: =HOUR(TIME(14,35,42)) | F28: =HOUR(TIME(14,35,42)) -> 14 | M28: oracle_probe | O28: Recalculate in Excel and compare the saved result.
A29: function:isoweeknum | B29: Date and time | C29: ISOWEEKNUM | D29: Curated deterministic boundary with shared-data and cross-sheet inputs | E29: =ISOWEEKNUM(DATE(2026,1,1)) | F29: =_xlfn.ISOWEEKNUM(DATE(2026,1,1)) -> 1 | M29: oracle_probe | N29: =IF(ISERROR(F29),"ERROR "&IFERROR(ERROR.TYPE(F29),""),"OK") -> OK | O29: Recalculate in Excel and compare the saved result. | P29: =IFERROR(N(F29),0)+IFERROR(N(Lookup!$F$17),0)+ROW()/100000 -> 11.00029
A30: function:left | B30: Text | C30: LEFT | D30: Curated deterministic boundary with shared-data and cross-sheet inputs | E30: =LEFT("CellRune Oracle",4) | F30: =LEFT("CellRune Oracle",4) -> Cell | M30: oracle_probe | O30: Recalculate in Excel and compare the saved result.
A31: function:leftb | B31: Text | C31: LEFTB | D31: Curated deterministic boundary with shared-data and cross-sheet inputs | E31: =LEFTB("CellRune Oracle",4) | F31: =LEFTB("CellRune Oracle",4) -> Cell | M31: oracle_probe | O31: Recalculate in Excel and compare the saved result.
A32: function:len | B32: Text | C32: LEN | D32: Curated deterministic boundary with shared-data and cross-sheet inputs | E32: =LEN("CellRune 오라클") | F32: =LEN("CellRune 오라클") -> 12 | M32: oracle_probe | O32: Recalculate in Excel and compare the saved result.
A33: function:lenb | B33: Text | C33: LENB | D33: Curated deterministic boundary with shared-data and cross-sheet inputs | E33: =LENB("CellRune 오라클") | F33: =LENB("CellRune 오라클") -> 15 | M33: oracle_probe | O33: Recalculate in Excel and compare the saved result.
A34: function:lower | B34: Text | C34: LOWER | D34: Function-catalog probe; genuine error results are retained as oracle evidence | E34: =LOWER("CellRune Oracle 2026") | F34: =LOWER("CellRune Oracle 2026") -> cellrune oracle 2026 | M34: oracle_probe | O34: Recalculate in Excel and compare the saved result.
A35: function:mid | B35: Text | C35: MID | D35: Curated deterministic boundary with shared-data and cross-sheet inputs | E35: =MID("CellRune Oracle",5,4) | F35: =MID("CellRune Oracle",5,4) -> Rune | M35: oracle_probe | O35: Recalculate in Excel and compare the saved result.
A36: function:midb | B36: Text | C36: MIDB | D36: Curated deterministic boundary with shared-data and cross-sheet inputs | E36: =MIDB("CellRune Oracle",5,4) | F36: =MIDB("CellRune Oracle",5,4) -> Rune | M36: oracle_probe | O36: Recalculate in Excel and compare the saved result.
A37: function:minute | B37: Date and time | C37: MINUTE | D37: Curated deterministic boundary with shared-data and cross-sheet inputs | E37: =MINUTE(TIME(14,35,42)) | F37: =MINUTE(TIME(14,35,42)) -> 35 | M37: oracle_probe | N37: =IF(ISERROR(F37),"ERROR "&IFERROR(ERROR.TYPE(F37),""),"OK") -> OK | O37: Recalculate in Excel and compare the saved result.
A38: function:month | B38: Date and time | C38: MONTH | D38: Function-catalog probe; genuine error results are retained as oracle evidence | E38: =MONTH(DATE(2026,7,27)) | F38: =MONTH(DATE(2026,7,27)) -> 7 | M38: oracle_probe | O38: Recalculate in Excel and compare the saved result.
A39: function:networkdays | B39: Date and time | C39: NETWORKDAYS | D39: Function-catalog probe with a repaired call signature | E39: =NETWORKDAYS(DATE(2026,1,1),DATE(2026,3,31),'SharedData'!$D$8:$D$12) | F39: =NETWORKDAYS(DATE(2026,1,1),DATE(2026,3,31),SharedData!$D$8:$D$12) -> 64 | M39: oracle_probe | O39: Recalculate in Excel and compare the saved result.
A40: function:networkdays-intl | B40: Date and time | C40: NETWORKDAYS.INTL | D40: Curated deterministic boundary with shared-data and cross-sheet inputs | E40: =NETWORKDAYS.INTL(DATE(2026,1,1),DATE(2026,3,31),1,'SharedData'!$D$8:$D$10) | F40: =NETWORKDAYS.INTL(DATE(2026,1,1),DATE(2026,3,31),1,SharedData!$D$8:$D$10) -> 64 | M40: oracle_probe | O40: Recalculate in Excel and compare the saved result.
A41: function:numbervalue | B41: Text | C41: NUMBERVALUE | D41: Curated deterministic boundary with shared-data and cross-sheet inputs | E41: =NUMBERVALUE("1,234.56",".",",") | F41: =_xlfn.NUMBERVALUE("1,234.56",".",",") -> 1234.56 | M41: oracle_probe | O41: Recalculate in Excel and compare the saved result. | P41: =IFERROR(N(F41),0)+IFERROR(N(Lookup!$F$29),0)+ROW()/100000 -> 1241.5604
A42: function:phonetic | B42: Text | C42: PHONETIC | D42: Function-catalog probe with a repaired call signature | E42: =PHONETIC('SharedData'!$B$6) | F42: =PHONETIC(SharedData!$B$6) -> K001 | M42: oracle_probe | O42: Recalculate in Excel and compare the saved result.
A43: function:proper | B43: Text | C43: PROPER | D43: Function-catalog probe; genuine error results are retained as oracle evidence | E43: =PROPER("CellRune Oracle 2026") | F43: =PROPER("CellRune Oracle 2026") -> Cellrune Oracle 2026 | M43: oracle_probe | O43: Recalculate in Excel and compare the saved result.
A44: function:regexextract | B44: Text | C44: REGEXEXTRACT | D44: Curated deterministic boundary with shared-data and cross-sheet inputs | E44: =REGEXEXTRACT("CR-2026-0727","[0-9]{4}") | F44: =_xlfn.REGEXEXTRACT("CR-2026-0727","[0-9]{4}") -> 2026 | M44: oracle_probe | O44: Recalculate in Excel and compare the saved result.
A45: function:regexreplace | B45: Text | C45: REGEXREPLACE | D45: Curated deterministic boundary with shared-data and cross-sheet inputs | E45: =REGEXREPLACE("CR-2026-0727","[0-9]","#") | F45: =_xlfn.REGEXREPLACE("CR-2026-0727","[0-9]","#") -> CR-####-#### | M45: oracle_probe | N45: =IF(ISERROR(F45),"ERROR "&IFERROR(ERROR.TYPE(F45),""),"OK") -> OK | O45: Recalculate in Excel and compare the saved result.
A46: function:regextest | B46: Text | C46: REGEXTEST | D46: Curated deterministic boundary with shared-data and cross-sheet inputs | E46: =REGEXTEST("CR-2026-0727","^CR-[0-9]{4}") | F46: =_xlfn.REGEXTEST("CR-2026-0727","^CR-[0-9]{4}") -> TRUE | M46: oracle_probe | O46: Recalculate in Excel and compare the saved result.
A47: function:replace | B47: Text | C47: REPLACE | D47: Curated deterministic boundary with shared-data and cross-sheet inputs | E47: =REPLACE("CellRune",5,4,"Oracle") | F47: =REPLACE("CellRune",5,4,"Oracle") -> CellOracle | M47: oracle_probe | O47: Recalculate in Excel and compare the saved result.
A48: function:replaceb | B48: Text | C48: REPLACEB | D48: Curated deterministic boundary with shared-data and cross-sheet inputs | E48: =REPLACEB("CellRune",5,4,"Oracle") | F48: =REPLACEB("CellRune",5,4,"Oracle") -> CellOracle | M48: oracle_probe | O48: Recalculate in Excel and compare the saved result.
A49: function:rept | B49: Text | C49: REPT | D49: Function-catalog probe with a repaired call signature | E49: =REPT("CR",3) | F49: =REPT("CR",3) -> CRCRCR | M49: oracle_probe | O49: Recalculate in Excel and compare the saved result.
A50: function:right | B50: Text | C50: RIGHT | D50: Curated deterministic boundary with shared-data and cross-sheet inputs | E50: =RIGHT("CellRune Oracle",6) | F50: =RIGHT("CellRune Oracle",6) -> Oracle | M50: oracle_probe | O50: Recalculate in Excel and compare the saved result.
A51: function:rightb | B51: Text | C51: RIGHTB | D51: Curated deterministic boundary with shared-data and cross-sheet inputs | E51: =RIGHTB("CellRune Oracle",6) | F51: =RIGHTB("CellRune Oracle",6) -> Oracle | M51: oracle_probe | O51: Recalculate in Excel and compare the saved result.
A52: function:search | B52: Text | C52: SEARCH | D52: Curated deterministic boundary with shared-data and cross-sheet inputs | E52: =SEARCH("rune","CellRune Oracle") | F52: =SEARCH("rune","CellRune Oracle") -> 5 | M52: oracle_probe | O52: Recalculate in Excel and compare the saved result.
A53: function:searchb | B53: Text | C53: SEARCHB | D53: Curated deterministic boundary with shared-data and cross-sheet inputs | E53: =SEARCHB("rune","CellRune Oracle") | F53: =SEARCHB("rune","CellRune Oracle") -> 5 | M53: oracle_probe | N53: =IF(ISERROR(F53),"ERROR "&IFERROR(ERROR.TYPE(F53),""),"OK") -> OK | O53: Recalculate in Excel and compare the saved result. | P53: =IFERROR(N(F53),0)+IFERROR(N(Lookup!$F$41),0)+ROW()/100000 -> 5.00053
A54: function:second | B54: Date and time | C54: SECOND | D54: Curated deterministic boundary with shared-data and cross-sheet inputs | E54: =SECOND(TIME(14,35,42)) | F54: =SECOND(TIME(14,35,42)) -> 42 | M54: oracle_probe | O54: Recalculate in Excel and compare the saved result.
A55: function:substitute | B55: Text | C55: SUBSTITUTE | D55: Function-catalog probe with a repaired call signature | E55: =SUBSTITUTE("CellRune Oracle 2026","Oracle","Atlas") | F55: =SUBSTITUTE("CellRune Oracle 2026","Oracle","Atlas") -> CellRune Atlas 2026 | M55: oracle_probe | O55: Recalculate in Excel and compare the saved result.
A56: function:t | B56: Text | C56: T | D56: Curated deterministic boundary with shared-data and cross-sheet inputs | E56: =T('SharedData'!$B$6) | F56: =T(SharedData!$B$6) -> K001 | M56: oracle_probe | O56: Recalculate in Excel and compare the saved result.
A57: function:text | B57: Text | C57: TEXT | D57: Curated deterministic boundary with shared-data and cross-sheet inputs | E57: =TEXT(DATE(2026,7,27),"yyyy-mm-dd") | F57: =TEXT(DATE(2026,7,27),"yyyy-mm-dd") -> 2026-07-27 | M57: oracle_probe | O57: Recalculate in Excel and compare the saved result.
A58: function:textafter | B58: Text | C58: TEXTAFTER | D58: Curated deterministic boundary with shared-data and cross-sheet inputs | E58: =TEXTAFTER("alpha|beta|gamma","|",2) | F58: =_xlfn.TEXTAFTER("alpha|beta|gamma","|",2) -> gamma | M58: oracle_probe | O58: Recalculate in Excel and compare the saved result.
A59: function:textbefore | B59: Text | C59: TEXTBEFORE | D59: Curated deterministic boundary with shared-data and cross-sheet inputs | E59: =TEXTBEFORE("alpha|beta|gamma","|",2) | F59: =_xlfn.TEXTBEFORE("alpha|beta|gamma","|",2) -> alpha|beta | M59: oracle_probe | O59: Recalculate in Excel and compare the saved result.
A60: function:textjoin | B60: Text | C60: TEXTJOIN | D60: Function-catalog probe with a repaired call signature | E60: =TEXTJOIN("|",TRUE,'SharedData'!$B$6:$B$10) | F60: =_xlfn.TEXTJOIN("|",TRUE,SharedData!$B$6:$B$10) -> K001|K002|K003|K004|K005 | M60: oracle_probe | O60: Recalculate in Excel and compare the saved result.
A61: function:textsplit | B61: Text | C61: TEXTSPLIT | D61: Curated deterministic boundary with shared-data and cross-sheet inputs | E61: =TEXTSPLIT("alpha|beta;gamma|delta","|",";") | F61: =_xlfn.TEXTSPLIT("alpha|beta;gamma|delta","|",";") -> alpha | M61: oracle_probe | N61: =IF(ISERROR(F61),"ERROR "&IFERROR(ERROR.TYPE(F61),""),"OK") -> OK | O61: Recalculate in Excel and compare the saved result.
A62: function:time | B62: Date and time | C62: TIME | D62: Curated deterministic boundary with shared-data and cross-sheet inputs | E62: =TIME(14,35,42) | F62: =TIME(14,35,42) -> 0.608125 | M62: oracle_probe | O62: Recalculate in Excel and compare the saved result.
A63: function:timevalue | B63: Date and time | C63: TIMEVALUE | D63: Curated deterministic boundary with shared-data and cross-sheet inputs | E63: =TIMEVALUE("14:35:42") | F63: =TIMEVALUE("14:35:42") -> 0.608125 | M63: oracle_probe | O63: Recalculate in Excel and compare the saved result.
A64: function:trim | B64: Text | C64: TRIM | D64: Function-catalog probe; genuine error results are retained as oracle evidence | E64: =TRIM("CellRune Oracle 2026") | F64: =TRIM("CellRune Oracle 2026") -> CellRune Oracle 2026 | M64: oracle_probe | O64: Recalculate in Excel and compare the saved result.
A65: function:unichar | B65: Text | C65: UNICHAR | D65: Function-catalog probe; genuine error results are retained as oracle evidence | E65: =UNICHAR("CellRune Oracle 2026") | F65: =_xlfn.UNICHAR("CellRune Oracle 2026") -> #VALUE! | M65: oracle_probe | O65: Recalculate in Excel and compare the saved result. | P65: =IFERROR(N(F65),0)+IFERROR(N(Lookup!$F$53),0)+ROW()/100000 -> 0.00065
A66: function:unicode | B66: Text | C66: UNICODE | D66: Function-catalog probe; genuine error results are retained as oracle evidence | E66: =UNICODE("CellRune Oracle 2026") | F66: =_xlfn.UNICODE("CellRune Oracle 2026") -> 67 | M66: oracle_probe | O66: Recalculate in Excel and compare the saved result.
A67: function:upper | B67: Text | C67: UPPER | D67: Function-catalog probe; genuine error results are retained as oracle evidence | E67: =UPPER("CellRune Oracle 2026") | F67: =UPPER("CellRune Oracle 2026") -> CELLRUNE ORACLE 2026 | M67: oracle_probe | O67: Recalculate in Excel and compare the saved result.
A68: function:value | B68: Text | C68: VALUE | D68: Function-catalog probe with a repaired call signature | E68: =VALUE("1234.56") | F68: =VALUE("1234.56") -> 1234.56 | M68: oracle_probe | O68: Recalculate in Excel and compare the saved result.
A69: function:valuetotext | B69: Text | C69: VALUETOTEXT | D69: Curated deterministic boundary with shared-data and cross-sheet inputs | E69: =VALUETOTEXT('SharedData'!$A$6:$C$8,1) | F69: =_xlfn.VALUETOTEXT(SharedData!$A$6:$C$8,1) -> #VALUE! | M69: oracle_probe | N69: =IF(ISERROR(F69),"ERROR "&IFERROR(ERROR.TYPE(F69),""),"OK") -> OK | O69: Recalculate in Excel and compare the saved result.
A70: function:weekday | B70: Date and time | C70: WEEKDAY | D70: Curated deterministic boundary with shared-data and cross-sheet inputs | E70: =WEEKDAY(DATE(1900,2,28),1) | F70: =WEEKDAY(DATE(1900,2,28),1) -> 3 | M70: oracle_probe | O70: Recalculate in Excel and compare the saved result.
A71: function:weeknum | B71: Date and time | C71: WEEKNUM | D71: Curated deterministic boundary with shared-data and cross-sheet inputs | E71: =WEEKNUM(DATE(2026,1,1),21) | F71: =WEEKNUM(DATE(2026,1,1),21) -> 1 | M71: oracle_probe | O71: Recalculate in Excel and compare the saved result.
A72: function:workday | B72: Date and time | C72: WORKDAY | D72: Curated deterministic boundary with shared-data and cross-sheet inputs | E72: =WORKDAY(DATE(2026,1,1),40,'SharedData'!$D$8:$D$10) | F72: =WORKDAY(DATE(2026,1,1),40,SharedData!$D$8:$D$10) -> 46079 | M72: oracle_probe | O72: Recalculate in Excel and compare the saved result.
A73: function:workday-intl | B73: Date and time | C73: WORKDAY.INTL | D73: Curated deterministic boundary with shared-data and cross-sheet inputs | E73: =WORKDAY.INTL(DATE(2026,1,1),40,1,'SharedData'!$D$8:$D$10) | F73: =WORKDAY.INTL(DATE(2026,1,1),40,1,SharedData!$D$8:$D$10) -> 46079 | M73: oracle_probe | O73: Recalculate in Excel and compare the saved result.
A74: function:year | B74: Date and time | C74: YEAR | D74: Curated deterministic boundary with shared-data and cross-sheet inputs | E74: =YEAR('SharedData'!$D$6) | F74: =YEAR(SharedData!$D$6) -> 2020 | M74: oracle_probe | O74: Recalculate in Excel and compare the saved result.
A75: function:yearfrac | B75: Date and time | C75: YEARFRAC | D75: Curated deterministic boundary with shared-data and cross-sheet inputs | E75: =YEARFRAC('SharedData'!$D$6,'SharedData'!$D$25,1) | F75: =YEARFRAC(SharedData!$D$6,SharedData!$D$25,1) -> 1.6114911 | M75: oracle_probe | O75: Recalculate in Excel and compare the saved result.
A76: curated:textdate:c001 | B76: Curated behaviour | C76: CURATED | D76: Hand-picked semantic boundary named by the oracle plan | E76: =TEXTJOIN("|",TRUE,TEXT('SharedData'!$D$6:$D$10,"yyyy-mm-dd")) | F76: {=_xlfn.TEXTJOIN("|",TRUE,TEXT(SharedData!$D$6:$D$10,"yyyy-mm-dd"))} -> 2020-01-01|2020-02-01|2020-03-03|2020-04-03|2020-05-04 | M76: oracle_probe | O76: Uses only deterministic workbook inputs; result must be cached by Excel.
A77: curated:textdate:c003 | B77: Curated behaviour | C77: CURATED | D77: Hand-picked semantic boundary named by the oracle plan | E77: =DATE(1900,2,29) | F77: =DATE(1900,2,29) -> 60 | M77: oracle_probe | N77: =IF(ISERROR(F77),"ERROR "&IFERROR(ERROR.TYPE(F77),""),"OK") -> OK | O77: Uses only deterministic workbook inputs; result must be cached by Excel. | P77: =IFERROR(N(F77),0)+IFERROR(N(Lookup!$F$65),0)+ROW()/100000 -> 60.00077
A78: curated:textdate:c004 | B78: Curated behaviour | C78: CURATED | D78: Hand-picked semantic boundary named by the oracle plan | E78: =DATE(1900,3,1)-DATE(1900,2,28) | F78: =DATE(1900,3,1)-DATE(1900,2,28) -> 2 | M78: oracle_probe | O78: Uses only deterministic workbook inputs; result must be cached by Excel.
A79: curated:textdate:c005 | B79: Curated behaviour | C79: CURATED | D79: Hand-picked semantic boundary named by the oracle plan | E79: =WEEKDAY(60,1) | F79: =WEEKDAY(60,1) -> 4 | M79: oracle_probe | O79: Uses only deterministic workbook inputs; result must be cached by Excel.
A80: curated:textdate:c006 | B80: Curated behaviour | C80: CURATED | D80: Hand-picked semantic boundary named by the oracle plan | E80: =WEEKDAY(61,1) | F80: =WEEKDAY(61,1) -> 5 | M80: oracle_probe | O80: Uses only deterministic workbook inputs; result must be cached by Excel.
A81: curated:textdate:c007 | B81: Curated behaviour | C81: CURATED | D81: Hand-picked semantic boundary named by the oracle plan | E81: =TEXT(60,"yyyy-mm-dd") | F81: =TEXT(60,"yyyy-mm-dd") -> 1900-02-29 | M81: oracle_probe | O81: Uses only deterministic workbook inputs; result must be cached by Excel.
A82: curated:textdate:c008 | B82: Curated behaviour | C82: CURATED | D82: Hand-picked semantic boundary named by the oracle plan | E82: =DAY(60) | F82: =DAY(60) -> 29 | M82: oracle_probe | O82: Uses only deterministic workbook inputs; result must be cached by Excel.
A83: curated:textdate:c009 | B83: Curated behaviour | C83: CURATED | D83: Hand-picked semantic boundary named by the oracle plan | E83: =YEARFRAC(DATE(2020,2,29),DATE(2024,2,29),1) | F83: =YEARFRAC(DATE(2020,2,29),DATE(2024,2,29),1) -> 3.998358 | M83: oracle_probe | O83: Uses only deterministic workbook inputs; result must be cached by Excel.
A84: curated:textdate:c010 | B84: Curated behaviour | C84: CURATED | D84: Hand-picked semantic boundary named by the oracle plan | E84: =TEXTAFTER(TEXTBEFORE("alpha|beta|gamma","|",-1),"|") | F84: =_xlfn.TEXTAFTER(_xlfn.TEXTBEFORE("alpha|beta|gamma","|",-1),"|") -> beta | M84: oracle_probe | O84: Uses only deterministic workbook inputs; result must be cached by Excel.
A85: curated:textdate:c011 | B85: Curated behaviour | C85: CURATED | D85: Hand-picked semantic boundary named by the oracle plan | E85: =REGEXREPLACE(LOWER(TEXTJOIN("-",TRUE,'SharedData'!$B$6:$B$10)),"[^a-z0-9-]","") | F85: =_xlfn.REGEXREPLACE(LOWER(_xlfn.TEXTJOIN("-",TRUE,SharedData!$B$6:$B$10)),"[^a-z0-9-]","") -> k001-k002-k003-k004-k005 | M85: oracle_probe | N85: =IF(ISERROR(F85),"ERROR "&IFERROR(ERROR.TYPE(F85),""),"OK") -> OK | O85: Uses only deterministic workbook inputs; result must be cached by Excel.
A86: curated:textdate:c012 | B86: Curated behaviour | C86: CURATED | D86: Hand-picked semantic boundary named by the oracle plan | E86: =NUMBERVALUE(SUBSTITUTE("1 234,56"," ",""),",",".") | F86: =_xlfn.NUMBERVALUE(SUBSTITUTE("1 234,56"," ",""),",",".") -> 1234.56 | M86: oracle_probe | O86: Uses only deterministic workbook inputs; result must be cached by Excel.
A87: curated:textdate:c013 | B87: Curated behaviour | C87: CURATED | D87: Hand-picked semantic boundary named by the oracle plan | E87: =WORKDAY.INTL(DATE(2026,1,1),NETWORKDAYS(DATE(2026,1,1),DATE(2026,3,31)),1,'SharedData'!$D$8:$D$10) | F87: =WORKDAY.INTL(DATE(2026,1,1),NETWORKDAYS(DATE(2026,1,1),DATE(2026,3,31)),1,SharedData!$D$8:$D$10) -> 46113 | M87: oracle_probe | O87: Uses only deterministic workbook inputs; result must be cached by Excel.
A88: curated:textdate:c014 | B88: Curated behaviour | C88: CURATED | D88: Hand-picked semantic boundary named by the oracle plan | E88: =DOLLAR(1.1-1,15) | F88: =DOLLAR(1.1-1,15) -> ₩0.100000000000000 | M88: oracle_probe | O88: Uses only deterministic workbook inputs; result must be cached by Excel.
A89: curated:textdate:c015 | B89: Curated behaviour | C89: CURATED | D89: Hand-picked semantic boundary named by the oracle plan | E89: =DOLLAR(1234.5,2) | F89: =DOLLAR(1234.5,2) -> ₩1,234.50 | M89: oracle_probe | O89: Uses only deterministic workbook inputs; result must be cached by Excel. | P89: =IFERROR(N(F89),0)+IFERROR(N(Lookup!$F$77),0)+ROW()/100000 -> 0.00089
A90: curated:textdate:c016 | B90: Curated behaviour | C90: CURATED | D90: Hand-picked semantic boundary named by the oracle plan | E90: =CONCAT(UNICHAR(9733)," ",PROPER('SharedData'!$B$6)," ",TEXT('SharedData'!$D$6,"yyyy-mm-dd")) | F90: =_xlfn.CONCAT(_xlfn.UNICHAR(9733)," ",PROPER(SharedData!$B$6)," ",TEXT(SharedData!$D$6,"yyyy-mm-dd")) -> ★ K001 2020-01-01 | M90: oracle_probe | O90: Uses only deterministic workbook inputs; result must be cached by Excel.

Sheet Errors
A1: Errors — CellRune Excel Oracle
A2: Blue cells are formulas. Gray rows are catalogued exclusions. Excel must recalculate and save cached values. | R2: Catalog rows | S2: =COUNTA(A5:A49) -> 45
R3: Primary cases | S3: =COUNTA(A5:A49) -> 45
A4: Case ID | B4: Category | C4: Function | D4: Scenario | E4: Formula text | F4: Result / spill zone | M4: Expectation | N4: Sentinel | O4: Note | P4: Dependency signature | R4: Active formulas | S4: =COUNTA(A5:A49)-COUNTIF(M5:M49,"excluded") -> 43
A5: function:and | B5: Logical / information / error | C5: AND | D5: Curated deterministic boundary with shared-data and cross-sheet inputs | E5: =AND('SharedData'!$G$6:$G$10) | F5: =AND(SharedData!$G$6:$G$10) -> FALSE | M5: oracle_probe | N5: =IF(ISERROR(F5),"ERROR "&IFERROR(ERROR.TYPE(F5),""),"OK") -> OK | O5: Recalculate in Excel and compare the saved result. | P5: =IFERROR(N(F5),0)+IFERROR(N(TextDate!$F$5),0)+ROW()/100000 -> 5e-05
A6: function:error-type | B6: Logical / information / error | C6: ERROR.TYPE | D6: Curated deterministic boundary with shared-data and cross-sheet inputs | E6: =ERROR.TYPE(NA()) | F6: =ERROR.TYPE(NA()) -> 7 | M6: oracle_probe | O6: Recalculate in Excel and compare the saved result.
A7: function:false | B7: Logical / information / error | C7: FALSE | D7: Function-catalog probe with a repaired call signature | E7: =FALSE() | F7: =FALSE() -> FALSE | M7: oracle_probe | O7: Recalculate in Excel and compare the saved result.
A8: function:if | B8: Logical / information / error | C8: IF | D8: Curated deterministic boundary with shared-data and cross-sheet inputs | E8: =IF('SharedData'!$A$6+'SharedData'!$A$7-'SharedData'!$A$8=0,"cancelled","residue") | F8: =IF(SharedData!$A$6+SharedData!$A$7-SharedData!$A$8=0,"cancelled","residue") -> residue | M8: oracle_probe | O8: Recalculate in Excel and compare the saved result.
A9: function:iferror | B9: Logical / information / error | C9: IFERROR | D9: Curated deterministic boundary with shared-data and cross-sheet inputs | E9: =IFERROR(1/0,"caught") | F9: =IFERROR(1/0,"caught") -> caught | M9: oracle_probe | O9: Recalculate in Excel and compare the saved result.
A10: function:ifna | B10: Logical / information / error | C10: IFNA | D10: Curated deterministic boundary with shared-data and cross-sheet inputs | E10: =IFNA(XLOOKUP("missing",'SharedData'!$B$6:$B$25,'SharedData'!$E$6:$E$25),"not found") | F10: =_xlfn.IFNA(_xlfn.XLOOKUP("missing",SharedData!$B$6:$B$25,SharedData!$E$6:$E$25),"not found") -> not found | M10: oracle_probe | O10: Recalculate in Excel and compare the saved result.
A11: function:ifs | B11: Logical / information / error | C11: IFS | D11: Curated deterministic boundary with shared-data and cross-sheet inputs | E11: =IFS('SharedData'!$E$6>150,"high",'SharedData'!$E$6>50,"mid",TRUE,"low") | F11: =_xlfn.IFS(SharedData!$E$6>150,"high",SharedData!$E$6>50,"mid",TRUE,"low") -> low | M11: oracle_probe | O11: Recalculate in Excel and compare the saved result.
A12: function:isblank | B12: Logical / information / error | C12: ISBLANK | D12: Curated deterministic boundary with shared-data and cross-sheet inputs | E12: =ISBLANK('SharedData'!$H$6) | F12: =ISBLANK(SharedData!$H$6) -> TRUE | M12: oracle_probe | O12: Recalculate in Excel and compare the saved result.
A13: function:iserr | B13: Logical / information / error | C13: ISERR | D13: Curated deterministic boundary with shared-data and cross-sheet inputs | E13: =ISERR(1/0) | F13: =ISERR(1/0) -> TRUE | M13: oracle_probe | N13: =IF(ISERROR(F13),"ERROR "&IFERROR(ERROR.TYPE(F13),""),"OK") -> OK | O13: Recalculate in Excel and compare the saved result.
A14: function:iserror | B14: Logical / information / error | C14: ISERROR | D14: Curated deterministic boundary with shared-data and cross-sheet inputs | E14: =ISERROR(NA()) | F14: =ISERROR(NA()) -> TRUE | M14: oracle_probe | O14: Recalculate in Excel and compare the saved result.
A15: function:iseven | B15: Logical / information / error | C15: ISEVEN | D15: Curated deterministic boundary with shared-data and cross-sheet inputs | E15: =ISEVEN('SharedData'!$E$6) | F15: =ISEVEN(SharedData!$E$6) -> TRUE | M15: oracle_probe | O15: Recalculate in Excel and compare the saved result.
A16: function:islogical | B16: Logical / information / error | C16: ISLOGICAL | D16: Curated deterministic boundary with shared-data and cross-sheet inputs | E16: =ISLOGICAL('SharedData'!$G$6) | F16: =ISLOGICAL(SharedData!$G$6) -> TRUE | M16: oracle_probe | O16: Recalculate in Excel and compare the saved result.
A17: function:isna | B17: Logical / information / error | C17: ISNA | D17: Curated deterministic boundary with shared-data and cross-sheet inputs | E17: =ISNA(NA()) | F17: =ISNA(NA()) -> TRUE | M17: oracle_probe | O17: Recalculate in Excel and compare the saved result. | P17: =IFERROR(N(F17),0)+IFERROR(N(TextDate!$F$5),0)+ROW()/100000 -> 1.00017
A18: function:isnontext | B18: Logical / information / error | C18: ISNONTEXT | D18: Curated deterministic boundary with shared-data and cross-sheet inputs | E18: =ISNONTEXT('SharedData'!$E$6) | F18: =ISNONTEXT(SharedData!$E$6) -> TRUE | M18: oracle_probe | O18: Recalculate in Excel and compare the saved result.
A19: function:isnumber | B19: Logical / information / error | C19: ISNUMBER | D19: Curated deterministic boundary with shared-data and cross-sheet inputs | E19: =ISNUMBER('SharedData'!$A$6) | F19: =ISNUMBER(SharedData!$A$6) -> TRUE | M19: oracle_probe | O19: Recalculate in Excel and compare the saved result.
A20: function:isodd | B20: Logical / information / error | C20: ISODD | D20: Curated deterministic boundary with shared-data and cross-sheet inputs | E20: =ISODD('SharedData'!$E$7) | F20: =ISODD(SharedData!$E$7) -> FALSE | M20: oracle_probe | O20: Recalculate in Excel and compare the saved result.
A21: function:isomitted | B21: Logical / information / error | C21: ISOMITTED | D21: Curated deterministic boundary with shared-data and cross-sheet inputs | E21: =LAMBDA(x,IF(ISOMITTED(x),"omitted",x))() | F21: =_xlfn.LAMBDA(_xlpm.x,IF(_xlfn.ISOMITTED(_xlpm.x),"omitted",_xlpm.x))() -> #VALUE! | M21: oracle_probe | N21: =IF(ISERROR(F21),"ERROR "&IFERROR(ERROR.TYPE(F21),""),"OK") -> ERROR 3 | O21: Recalculate in Excel and compare the saved result.
A22: function:istext | B22: Logical / information / error | C22: ISTEXT | D22: Curated deterministic boundary with shared-data and cross-sheet inputs | E22: =ISTEXT('SharedData'!$B$6) | F22: =ISTEXT(SharedData!$B$6) -> TRUE | M22: oracle_probe | O22: Recalculate in Excel and compare the saved result.
A23: function:n | B23: Logical / information / error | C23: N | D23: Curated deterministic boundary with shared-data and cross-sheet inputs | E23: =N('SharedData'!$G$6) | F23: =N(SharedData!$G$6) -> 1 | M23: oracle_probe | O23: Recalculate in Excel and compare the saved result.
A24: function:na | B24: Logical / information / error | C24: NA | D24: Curated deterministic boundary with shared-data and cross-sheet inputs | E24: =NA() | F24: =NA() -> #N/A | M24: oracle_probe | O24: Recalculate in Excel and compare the saved result.
A25: function:not | B25: Logical / information / error | C25: NOT | D25: Function-catalog probe with a repaired call signature | E25: =NOT('SharedData'!$G$6) | F25: =NOT(SharedData!$G$6) -> FALSE | M25: oracle_probe | O25: Recalculate in Excel and compare the saved result.
A26: function:or | B26: Logical / information / error | C26: OR | D26: Function-catalog probe; genuine error results are retained as oracle evidence | E26: =OR(TRUE,FALSE) | F26: =OR(TRUE,FALSE) -> TRUE | M26: oracle_probe | O26: Recalculate in Excel and compare the saved result.
A27: function:switch | B27: Logical / information / error | C27: SWITCH | D27: Curated deterministic boundary with shared-data and cross-sheet inputs | E27: =SWITCH('SharedData'!$C$6,"A",1,"B",2,"C",3,0) | F27: =_xlfn.SWITCH(SharedData!$C$6,"A",1,"B",2,"C",3,0) -> 1 | M27: oracle_probe | O27: Recalculate in Excel and compare the saved result.
A28: function:true | B28: Logical / information / error | C28: TRUE | D28: Function-catalog probe with a repaired call signature | E28: =TRUE() | F28: =TRUE() -> TRUE | M28: oracle_probe | O28: Recalculate in Excel and compare the saved result.
A29: function:type | B29: Logical / information / error | C29: TYPE | D29: Function-catalog probe with a repaired call signature | E29: =TYPE('SharedData'!$E$6) | F29: =TYPE(SharedData!$E$6) -> 1 | M29: oracle_probe | N29: =IF(ISERROR(F29),"ERROR "&IFERROR(ERROR.TYPE(F29),""),"OK") -> OK | O29: Recalculate in Excel and compare the saved result. | P29: =IFERROR(N(F29),0)+IFERROR(N(TextDate!$F$17),0)+ROW()/100000 -> 590.00029
A30: function:xor | B30: Logical / information / error | C30: XOR | D30: Function-catalog probe; genuine error results are retained as oracle evidence | E30: =XOR(TRUE,FALSE) | F30: =_xlfn.XOR(TRUE,FALSE) -> TRUE | M30: oracle_probe | O30: Recalculate in Excel and compare the saved result.
A31: curated:errors:c001 | B31: Curated behaviour | C31: CURATED | D31: Hand-picked semantic boundary named by the oracle plan | E31: =1/0 | F31: =1/0 -> #DIV/0! | M31: oracle_probe | O31: Uses only deterministic workbook inputs; result must be cached by Excel.
A32: curated:errors:c002 | B32: Curated behaviour | C32: CURATED | D32: Hand-picked semantic boundary named by the oracle plan | E32: =0/0 | F32: =0/0 -> #DIV/0! | M32: oracle_probe | O32: Uses only deterministic workbook inputs; result must be cached by Excel.
A33: curated:errors:c003 | B33: Curated behaviour | C33: CURATED | D33: Hand-picked semantic boundary named by the oracle plan | E33: =SQRT(-1) | F33: =SQRT(-1) -> #NUM! | M33: oracle_probe | O33: Uses only deterministic workbook inputs; result must be cached by Excel.
A34: curated:errors:c004 | B34: Curated behaviour | C34: CURATED | D34: Hand-picked semantic boundary named by the oracle plan | E34: =MATCH("missing",'SharedData'!$B$6:$B$25,0) | F34: =MATCH("missing",SharedData!$B$6:$B$25,0) -> #N/A | M34: oracle_probe | O34: Uses only deterministic workbook inputs; result must be cached by Excel.
A35: curated:errors:c005 | B35: Curated behaviour | C35: CURATED | D35: Hand-picked semantic boundary named by the oracle plan | E35: =INDEX('SharedData'!$E$6:$E$25,999) | F35: =INDEX(SharedData!$E$6:$E$25,999) -> #REF! | M35: oracle_probe | O35: Uses only deterministic workbook inputs; result must be cached by Excel.
A36: curated:errors:c006 | B36: Curated behaviour | C36: CURATED | D36: Hand-picked semantic boundary named by the oracle plan | E36: =VALUE("not a number") | F36: =VALUE("not a number") -> #VALUE! | M36: oracle_probe | O36: Uses only deterministic workbook inputs; result must be cached by Excel.
A37: curated:errors:c007 | B37: Curated behaviour | C37: CURATED | D37: Hand-picked semantic boundary named by the oracle plan | E37: =NONEXISTENTFUNC(1) | F37: =NONEXISTENTFUNC(1) -> #NAME? | M37: oracle_probe | N37: =IF(ISERROR(F37),"ERROR "&IFERROR(ERROR.TYPE(F37),""),"OK") -> ERROR 5 | O37: Uses only deterministic workbook inputs; result must be cached by Excel.
A38: curated:errors:c009 | B38: Curated behaviour | C38: CURATED | D38: Hand-picked semantic boundary named by the oracle plan | E38: =IFNA(NA(),"caught-na") | F38: =_xlfn.IFNA(NA(),"caught-na") -> caught-na | M38: oracle_probe | O38: Uses only deterministic workbook inputs; result must be cached by Excel.
A39: curated:errors:c010 | B39: Curated behaviour | C39: CURATED | D39: Hand-picked semantic boundary named by the oracle plan | E39: =IFNA(1/0,"not-reached") | F39: =_xlfn.IFNA(1/0,"not-reached") -> #DIV/0! | M39: oracle_probe | O39: Uses only deterministic workbook inputs; result must be cached by Excel.
A40: curated:errors:c012 | B40: Curated behaviour | C40: CURATED | D40: Hand-picked semantic boundary named by the oracle plan | E40: =ERROR.TYPE(1/0) | F40: =ERROR.TYPE(1/0) -> 2 | M40: oracle_probe | O40: Uses only deterministic workbook inputs; result must be cached by Excel.
A41: curated:errors:c013 | B41: Curated behaviour | C41: CURATED | D41: Hand-picked semantic boundary named by the oracle plan | E41: =SUM(1,NA(),3) | F41: =SUM(1,NA(),3) -> #N/A | M41: oracle_probe | O41: Uses only deterministic workbook inputs; result must be cached by Excel. | P41: =IFERROR(N(F41),0)+IFERROR(N(TextDate!$F$29),0)+ROW()/100000 -> 1.00041
A42: curated:errors:c014 | B42: Curated behaviour | C42: CURATED | D42: Hand-picked semantic boundary named by the oracle plan | E42: =SUM('SharedData'!$E$6:$E$25)+1/0 | F42: =SUM(SharedData!$E$6:$E$25)+1/0 -> #DIV/0! | M42: oracle_probe | O42: Uses only deterministic workbook inputs; result must be cached by Excel.
A43: curated:errors:c015 | B43: Curated behaviour | C43: CURATED | D43: Hand-picked semantic boundary named by the oracle plan | E43: =IF('SharedData'!$G$6,NA(),1/0) | F43: =IF(SharedData!$G$6,NA(),1/0) -> #N/A | M43: oracle_probe | O43: Uses only deterministic workbook inputs; result must be cached by Excel.
A44: curated:errors:c016 | B44: Curated behaviour | C44: CURATED | D44: Hand-picked semantic boundary named by the oracle plan | E44: =ISERROR(1/0) | F44: =ISERROR(1/0) -> TRUE | M44: oracle_probe | O44: Uses only deterministic workbook inputs; result must be cached by Excel.
A45: curated:errors:c017 | B45: Curated behaviour | C45: CURATED | D45: Hand-picked semantic boundary named by the oracle plan | E45: =ISERR(NA()) | F45: =ISERR(NA()) -> FALSE | M45: oracle_probe | N45: =IF(ISERROR(F45),"ERROR "&IFERROR(ERROR.TYPE(F45),""),"OK") -> OK | O45: Uses only deterministic workbook inputs; result must be cached by Excel.
A46: curated:errors:c018 | B46: Curated behaviour | C46: CURATED | D46: Hand-picked semantic boundary named by the oracle plan | E46: =AGGREGATE(9,6,{1,2,3,4}) | F46: =_xlfn.AGGREGATE(9,6,{1,2,3,4}) -> #VALUE! | M46: oracle_probe | O46: Uses only deterministic workbook inputs; result must be cached by Excel.
A47: curated:errors:c019 | B47: Curated behaviour | C47: CURATED | D47: Hand-picked semantic boundary named by the oracle plan | E47: =AGGREGATE(9,6,'SharedData'!$E$6:$E$25) | F47: =_xlfn.AGGREGATE(9,6,SharedData!$E$6:$E$25) -> 2100 | M47: oracle_probe | O47: Uses only deterministic workbook inputs; result must be cached by Excel.
A48: curated:errors:c020 | B48: Curated behaviour | C48: CURATED | D48: Hand-picked semantic boundary named by the oracle plan | E48: ='SharedData'!$O$2 | F48: EXCLUDED | M48: excluded | O48: Circular reference with iteration off has no deterministic semantic cache.
A49: curated:errors:c021 | B49: Curated behaviour | C49: CURATED | D49: Hand-picked semantic boundary named by the oracle plan | E49: =ISNUMBER('SharedData'!$O$2) | F49: EXCLUDED | M49: excluded | O49: Predicate over a circular reference has no deterministic semantic cache.

Sheet Unsupported
A1: Unsupported — CellRune Excel Oracle
A2: Blue cells are formulas. Gray rows are catalogued exclusions. Excel must recalculate and save cached values. | R2: Catalog rows | S2: =COUNTA(A5:A1157) -> 49
R3: Primary cases | S3: =COUNTA(A5:A1157) -> 49
A4: Case ID | B4: Category | C4: Function | D4: Scenario | E4: Formula text | F4: Result / spill zone | M4: Expectation | N4: Sentinel | O4: Note | P4: Dependency signature | R4: Active formulas | S4: =COUNTA(A5:A1157)-COUNTIF(M5:M1157,"excluded") -> 20
A5: function:call | B5: Native automation exclusion | C5: CALL | D5: Catalogued but inactive because a native automation server is required | E5: =CALL(0.5) | F5: EXCLUDED | M5: excluded | O5: Native add-in automation is host- and architecture-dependent.
A29: function:cell | B29: Host-dependent exclusion | C29: CELL | D29: Catalogued but inactive because the value identifies the saving host | E29: =CELL("address",'SharedData'!$E$6) | F29: EXCLUDED | M29: excluded | O29: Result depends on the workbook filename and path.
A53: function:copilot | B53: External service exclusion | C53: COPILOT | D53: Catalogued but inactive because an external service is required | E53: =COPILOT(0.5) | F53: EXCLUDED | M53: excluded | O53: Requires an external AI service and account context.
A77: function:cubekpimember | B77: External connection exclusion | C77: CUBEKPIMEMBER | D77: Catalogued but inactive because an external data connection is required | E77: =CUBEKPIMEMBER(0.5) | F77: EXCLUDED | M77: excluded | O77: Requires an OLAP connection.
A101: function:cubemember | B101: External connection exclusion | C101: CUBEMEMBER | D101: Catalogued but inactive because an external data connection is required | E101: =CUBEMEMBER(0.5) | F101: EXCLUDED | M101: excluded | O101: Requires an OLAP connection.
A125: function:cubememberproperty | B125: External connection exclusion | C125: CUBEMEMBERPROPERTY | D125: Catalogued but inactive because an external data connection is required | E125: =CUBEMEMBERPROPERTY(0.5) | F125: EXCLUDED | M125: excluded | O125: Requires an OLAP connection.
A149: function:cuberankedmember | B149: External connection exclusion | C149: CUBERANKEDMEMBER | D149: Catalogued but inactive because an external data connection is required | E149: =CUBERANKEDMEMBER(0.5) | F149: EXCLUDED | M149: excluded | O149: Requires an OLAP connection.
A173: function:cubeset | B173: External connection exclusion | C173: CUBESET | D173: Catalogued but inactive because an external data connection is required | E173: =CUBESET(0.5) | F173: EXCLUDED | M173: excluded | O173: Requires an OLAP connection.
A197: function:cubesetcount | B197: External connection exclusion | C197: CUBESETCOUNT | D197: Catalogued but inactive because an external data connection is required | E197: =CUBESETCOUNT(0.5) | F197: EXCLUDED | M197: excluded | O197: Requires an OLAP connection.
A221: function:cubevalue | B221: External connection exclusion | C221: CUBEVALUE | D221: Catalogued but inactive because an external data connection is required | E221: =CUBEVALUE(0.5) | F221: EXCLUDED | M221: excluded | O221: Requires an OLAP connection.
A245: function:detectlanguage | B245: External service exclusion | C245: DETECTLANGUAGE | D245: Catalogued but inactive because an external service is required | E245: =DETECTLANGUAGE(0.5) | F245: EXCLUDED | M245: excluded | O245: Requires an external translation service.
A269: function:encodeurl | B269: Required host matrix unavailable | C269: ENCODEURL | D269: Catalogued for future profiles but inactive in the required 0.1.7 host matrix | E269: =ENCODEURL("CellRune 오라클") | F269: EXCLUDED | M269: excluded | O269: Neither required host profile implements ENCODEURL.
... A653: function:webservice | B653: External service exclusion | C653: WEBSERVICE | D653: Catalogued but inactive because an external service is required | E653: =WEBSERVICE(0.5) | F653: EXCLUDED | M653: excluded | O653: Requires an external network request.
A677: curated:unsupported:c001 | B677: Curated behaviour | C677: CURATED | D677: Hand-picked semantic boundary named by the oracle plan | E677: =LET(x,'SharedData'!$E$6:$E$25,SUM(FILTER(x,x>100))) | F677: =_xlfn.LET(_xlpm.x,SharedData!$E$6:$E$25,SUM(_xlfn._xlws.FILTER(_xlpm.x,_xlpm.x>100))) -> 1550 | M677: not_implemented | O677: Uses only deterministic workbook inputs; result must be cached by Excel.
A701: curated:unsupported:c002 | B701: Curated behaviour | C701: CURATED | D701: Hand-picked semantic boundary named by the oracle plan | E701: =LET(a,'SharedData'!$E$6,b,'SharedData'!$F$6,c,a*b,c+a) | F701: =_xlfn.LET(_xlpm.a,SharedData!$E$6,_xlpm.b,SharedData!$F$6,_xlpm.c,_xlpm.a*_xlpm.b,_xlpm.c+_xlpm.a) -> 20 | M701: not_implemented | O701: Uses only deterministic workbook inputs; result must be cached by Excel.
A725: curated:unsupported:c003 | B725: Curated behaviour | C725: CURATED | D725: Hand-picked semantic boundary named by the oracle plan | E725: =LAMBDA(x,x+1)(5) | F725: =_xlfn.LAMBDA(_xlpm.x,_xlpm.x+1)(5) -> 6 | M725: not_implemented | O725: Uses only deterministic workbook inputs; result must be cached by Excel.
A749: curated:unsupported:c004 | B749: Curated behaviour | C749: CURATED | D749: Hand-picked semantic boundary named by the oracle plan | E749: =LAMBDA(x,y,x*y)(6,7) | F749: =_xlfn.LAMBDA(_xlpm.x,_xlpm.y,_xlpm.x*_xlpm.y)(6,7) -> 42 | M749: not_implemented | O749: Uses only deterministic workbook inputs; result must be cached by Excel.
A773: curated:unsupported:c005 | B773: Curated behaviour | C773: CURATED | D773: Hand-picked semantic boundary named by the oracle plan | E773: =SUM(Arithmetic:TextDate!F5) | F773: =SUM(Arithmetic:TextDate!F5) -> #VALUE! | M773: not_implemented | N773: =IF(ISERROR(F773),"ERROR "&IFERROR(ERROR.TYPE(F773),""),"OK") -> ERROR 3 | O773: Uses only deterministic workbook inputs; result must be cached by Excel.
A797: curated:unsupported:c006 | B797: Curated behaviour | C797: CURATED | D797: Hand-picked semantic boundary named by the oracle plan | E797: =COUNT(Arithmetic:TextDate!F5) | F797: =COUNT(Arithmetic:TextDate!F5) -> 5 | M797: not_implemented | O797: Uses only deterministic workbook inputs; result must be cached by Excel.
A821: curated:unsupported:c007 | B821: Curated behaviour | C821: CURATED | D821: Hand-picked semantic boundary named by the oracle plan | E821: =SUM(DataTable[Amount]) | F821: =SUM(DataTable[Amount]) -> 2100 | M821: not_implemented | O821: Uses only deterministic workbook inputs; result must be cached by Excel.
A845: curated:unsupported:c008 | B845: Curated behaviour | C845: CURATED | D845: Hand-picked semantic boundary named by the oracle plan | E845: =AVERAGEIFS(DataTable[Amount],DataTable[Category],"A") | F845: =AVERAGEIFS(DataTable[Amount],DataTable[Category],"A") -> 100 | M845: not_implemented | O845: Uses only deterministic workbook inputs; result must be cached by Excel.
A869: curated:unsupported:c009 | B869: Curated behaviour | C869: CURATED | D869: Hand-picked semantic boundary named by the oracle plan | E869: =XLOOKUP("K010",DataTable[Key],DataTable[Amount]) | F869: =_xlfn.XLOOKUP("K010",DataTable[Key],DataTable[Amount]) -> 100 | M869: not_implemented | O869: Uses only deterministic workbook inputs; result must be cached by Excel. | P869: =IFERROR(N(F869),0)+IFERROR(N(Errors!$F$5),0)+ROW()/100000 -> 100.00869
A893: curated:unsupported:c010 | B893: Curated behaviour | C893: CURATED | D893: Hand-picked semantic boundary named by the oracle plan | E893: =SUMPRODUCT(DataTable[Amount],DataTable[Quantity]) | F893: =SUMPRODUCT(DataTable[Amount],DataTable[Quantity]) -> 8610 | M893: not_implemented | O893: Uses only deterministic workbook inputs; result must be cached by Excel.
A917: curated:unsupported:c011 | B917: Curated behaviour | C917: CURATED | D917: Hand-picked semantic boundary named by the oracle plan | E917: =SUM(DataTable[[Amount]:[Quantity]]) | F917: =SUM(DataTable[[Amount]:[Quantity]]) -> 2177 | M917: not_implemented | O917: Uses only deterministic workbook inputs; result must be cached by Excel.
A941: curated:unsupported:c012 | B941: Curated behaviour | C941: CURATED | D941: Hand-picked semantic boundary named by the oracle plan | E941: =GROUPBY(DataTable[Category],DataTable[Amount],SUM) | F941: {=_xlfn.GROUPBY(DataTable[Category],DataTable[Amount],_xleta.SUM)} -> A | G941: 700 | M941: not_implemented | O941: Uses only deterministic workbook inputs; result must be cached by Excel.
F942: B | G942: 770
F943: C | G943: 630
F944: 합계 | G944: 2100
A965: curated:unsupported:c013 | B965: Curated behaviour | C965: CURATED | D965: Hand-picked semantic boundary named by the oracle plan | E965: =PIVOTBY(DataTable[Category],DataTable[Flag],DataTable[Amount],SUM) | F965: {=_xlfn.PIVOTBY(DataTable[Category],DataTable[Flag],DataTable[Amount],_xleta.SUM)} | G965: FALSE | H965: TRUE | I965: 합계 | M965: not_implemented | N965: =IF(ISERROR(F965),"ERROR "&IFERROR(ERROR.TYPE(F965),""),"OK") -> OK | O965: Uses only deterministic workbook inputs; result must be cached by Excel.
F966: A | G966: 300 | H966: 400 | I966: 700
F967: B | G967: 440 | H967: 330 | I967: 770
F968: C | G968: 360 | H968: 270 | I968: 630
F969: 합계 | G969: 1100 | H969: 1000 | I969: 2100
A989: curated:unsupported:c014 | B989: Curated behaviour | C989: CURATED | D989: Hand-picked semantic boundary named by the oracle plan | E989: =TRIMRANGE('SharedData'!$H$5:$J$27) | F989: {=_xlfn.TRIMRANGE(SharedData!$H$5:$J$27)} -> Mixed | G989: X | H989: Y = 2X+3 | M989: not_implemented | O989: Uses only deterministic workbook inputs; result must be cached by Excel.
F990: 0 | G990: 1 | H990: 5
F991: text | G991: 2 | H991: 7
F992: TRUE | G992: 3 | H992: 9
F993: FALSE | G993: 4 | H993: 11
F994: 0 | G994: 5 | H994: 13
F995: 0 | G995: 6 | H995: 15
F996: 0 | G996: 7 | H996: 17
F997: CellRune | G997: 8 | H997: 19
F998: TRUE | G998: 9 | H998: 21
F999: -1 | G999: 10 | H999: 23
F1000: 0 | G1000: 11 | H1000: 25
F1001: text | G1001: 12 | H1001: 27
F1002: TRUE | G1002: 13 | H1002: 29
F1003: FALSE | G1003: 14 | H1003: 31
F1004: 0 | G1004: 15 | H1004: 33
F1005: 0 | G1005: 16 | H1005: 35
F1006: 0 | G1006: 17 | H1006: 37
F1007: CellRune | G1007: 18 | H1007: 39
F1008: TRUE | G1008: 19 | H1008: 41
F1009: -1 | G1009: 20 | H1009: 43
A1013: curated:unsupported:c015 | B1013: Curated behaviour | C1013: CURATED | D1013: Hand-picked semantic boundary named by the oracle plan | E1013: =SUM('SharedData'!T:T*'SharedData'!U:U) | F1013: {=SUM(SharedData!T:T*SharedData!U:U)} -> 5740 | M1013: not_implemented | O1013: Uses only deterministic workbook inputs; result must be cached by Excel.
A1037: curated:unsupported:c016 | B1037: Curated behaviour | C1037: CURATED | D1037: Hand-picked semantic boundary named by the oracle plan | E1037: =SUM('SharedData'!T:T*'SharedData'!V:V) | F1037: {=SUM(SharedData!T:T*SharedData!V:V)} -> 650 | M1037: not_implemented | O1037: Uses only deterministic workbook inputs; result must be cached by Excel.
A1061: curated:unsupported:c017 | B1061: Curated behaviour | C1061: CURATED | D1061: Hand-picked semantic boundary named by the oracle plan | E1061: =SUM(SpanStart:SpanEnd!A1) | F1061: =SUM(SpanStart:SpanEnd!A1) -> 111 | M1061: not_implemented | O1061: Uses only deterministic workbook inputs; result must be cached by Excel.
A1085: curated:unsupported:c018 | B1085: Curated behaviour | C1085: CURATED | D1085: Hand-picked semantic boundary named by the oracle plan | E1085: =SUM(SpanStart:SpanEnd!A:A) | F1085: =SUM(SpanStart:SpanEnd!A:A) -> 1665 | M1085: not_implemented | O1085: Uses only deterministic workbook inputs; result must be cached by Excel.
A1109: curated:unsupported:c019 | B1109: Curated behaviour | C1109: CURATED | D1109: Hand-picked semantic boundary named by the oracle plan | E1109: =INDEX(SpanStart:SpanEnd!A1:A5,1) | F1109: =INDEX(SpanStart:SpanEnd!A1:A5,1) -> #VALUE! | M1109: not_implemented | O1109: Uses only deterministic workbook inputs; result must be cached by Excel.
A1133: curated:unsupported:c020 | B1133: Curated behaviour | C1133: CURATED | D1133: Hand-picked semantic boundary named by the oracle plan | E1133: =VLOOKUP(1,SpanStart:SpanEnd!A1:B5,2,FALSE) | F1133: =VLOOKUP(1,SpanStart:SpanEnd!A1:B5,2,FALSE) -> #VALUE! | M1133: not_implemented | O1133: Uses only deterministic workbook inputs; result must be cached by Excel.
A1157: curated:unsupported:c021 | B1157: Curated behaviour | C1157: CURATED | D1157: Hand-picked semantic boundary named by the oracle plan | E1157: =TABLE(input_row,input_col) | F1157: EXCLUDED | M1157: excluded | O1157: What-if data table. Must be created in Excel (Data ▸ What-If Analysis ▸ Data Table); see the runbook.

Sheet SpanStart
A1: 1 | B1: 11
A2: 2 | B2: 12
A3: 3 | B3: 13
A4: 4 | B4: 14
A5: 5 | B5: 15

Sheet SpanMid
A1: 10 | B1: 101
A2: 20 | B2: 102
A3: 30 | B3: 103
A4: 40 | B4: 104
A5: 50 | B5: 105

Sheet SpanEnd
A1: 100 | B1: 1001
A2: 200 | B2: 1002
A3: 300 | B3: 1003
A4: 400 | B4: 1004
A5: 500 | B5: 1005
